Workbook

Sheet Final set of papers
A1: Title | B1: ref doi | C1: Library | D1: Tool's name | E1: What - Technology Dependecy | F1: What - Which techno | G1: What - Defects (Categories) | H1: When | I1: Where - Granularity | J1: Where - Level | K1: How - Techniques | L1: How - Categories of techniques | M1: How - Lifecycle | N1: Tool based ? | O1: Data sets / Replication packages | P1: Ranks | Q1: Year | R1: Code access | S1: Maturity | T1: Links
A2: Does your configuration code smell? | B2: https://dl.acm.org/doi/pdf/10.1145/2901739.2901761 | C2: acm (done) | D2: Puppeteer | E2: Technology Specifi - TS | F2: Puppet | G2: 2-3- Language constructs, 2-1- Naming & conventions, 1-3- Code structure, 2-2- Syntax & Formatting, 1- Structural Quality, 2- Syntactic & Linguistic Quality, 1-1- Abstraction issues, 1-2- Modularity & Organization | H2: Implementation, Design | I2: Script, Module | J2: Config management | K2: Regular Expressions - RegX | L2: 1 - Rule-Based and Pattern-Matching Approaches | M2: Static | N2: Yes | O2: https://github.com/tushartushar/Puppeteer | P2: RankA | Q2: {=IF(A2:A945="","", IFERROR( VLOOKUP(A2:A945, {'All papers'!C:C, 'All papers'!A:A}, 2, FALSE), "Not Found" ) )} -> 2016 | R2: WhiteBox | S2: Both | T2: Github
D3: PuppetLint | O3: https://github.com/tushartushar/configSmellData
A4: Gang of Eight: A Defect Taxonomy for Infrastructure as Code Scripts | B4: https://ieeexplore.ieee.org/document/9284113 | C4: ieee (done) | D4: ACID | E4: Technology Specifi - TS | F4: Puppet | G4: 8-1- Program Flow, 7-1- Configuration Data, 4-3- Dependecies & integration, 6-1- Code Readability, 9-3- Infra components, 4-1- Idempotency & State management, 3- Security, 4- Operational Quality, 8- Control Flow & Logic, 7- Data & Variable management, 6- Maintability & Documentation, 9- Domain Specific Issues | H4: Implementation | I4: Script | J4: Config management | K4: Regular Expressions - RegX | L4: 1 - Rule-Based and Pattern-Matching Approaches | M4: Static | N4: Yes | O4: https://hub.docker.com/r/akondrahman/acid-puppet https://figshare.com/s/b2633bd4b1929267a451 | P4: RankA* | Q4: 2020 | R4: WhiteBox | S4: Code access | T4: Figshare, Docker hub
A5: DeepIaC: deep learning-based linguistic anti-pattern detection in IaC | B5: https://dl.acm.org/doi/10.1145/3416505.3423564 | C5: acm (done) | D5: DeepIaC | E5: Technology Specifi - TS | F5: Ansible | G5: 2-1- Naming & conventions, 2- Syntactic & Linguistic Quality | H5: Implementation | I5: Script | J5: Config management | K5: Deep Learning - DL | L5: 4 - Statistical and Learning-Based Methods | M5: Static | N5: Yes | O5: https://github.com/SODALITE-EU/defect-prediction | P5: RankA* | Q5: 2020 | R5: WhiteBox | S5: Code access | T5: Github
A6: Polyglot Code Smell Detection for Infrastructure as Code with GLITCH; GLITCH: Automated Polyglot Security Smell Detection in Infrastructure as Code | B6: https://www.computer.org/csdl/proceedings-article/ase/2023/299600c042/1SBGsb6PvS8 https://dl.acm.org/doi/10.1145/3551349.3556945 | C6: acm (done) | D6: Glitch | E6: Technology Agnostic - TA | F6: Multi (for TA) | G6: 6-1- Code Readability, 2-2- Syntax & Formatting, 1-3- Code structure, 7-2- Vraibale management, 1-1- Abstraction issues, 1- Structural Quality, 2- Syntactic & Linguistic Quality, 6- Maintability & Documentation, 7- Data & Variable management, 3- Security | H6: Implementation | I6: Script | J6: Other | K6: Pattern Matching, Regular Expressions - RegX | L6: 1 - Rule-Based and Pattern-Matching Approaches | M6: Static | N6: Yes | O6: https://figshare.com/articles/dataset/GLITCH_Replication_Package_with_Code_and_Datasets_ASE_2022_/19726603/2?file=36939973 | P6: RankA* | Q6: 2023 | R6: WhiteBox | S6: Both | T6: Figshare
A7: Smelly variables in ansible infrastructure code: detection, prevalence, and lifetime | B7: https://dl.acm.org/doi/10.1145/3524842.3527964 | C7: acm (done) | D7: Smelly variables | E7: Technology Specifi - TS | F7: Ansible | G7: 7-2- Vraibale management, 7- Data & Variable management | H7: Implementation | I7: Script | J7: Config management | K7: Program Dependncy Graph - PDG | L7: 2 - Graph-Based Analyses | M7: Static | N7: Yes | O7: https://figshare.com/articles/dataset/Replication_package_for_Smelly_Variables_in_Ansible_Infrastructure_Code_Detection_Prevalence_and_Lifetime_/18819074 | P7: RankA | Q7: 2022 | R7: WhiteBox | S7: Dataset | T7: Figshare
A8: Source Code Properties of Defective Infrastructure as Code Scripts | B8: https://arxiv.org/abs/1810.09605 https://www.sciencedirect.com/science/article/pii/S0950584919300965 https://dl.acm.org/doi/10.1016/j.infsof.2019.04.013 | C8: acm (done) | D8: -------------- | E8: Technology Specifi - TS | F8: Puppet | G8: 2-3- Language constructs, 2- Syntactic & Linguistic Quality | H8: Implementation | I8: Script | J8: Config management | K8: Statistical Learners | L8: 4 - Statistical and Learning-Based Methods | M8: Static | N8: Yes | O8: https://figshare.com/s/ad26e370c833e8aa9712 | P8: Journal | Q8: 2019 | R8: WhiteBox | S8: Dataset | T8: Figshare
A9: As Code Testing: Characterizing Test Quality in Open Source Ansible Development | B9: https://ieeexplore.ieee.org/document/9787876 | C9: ieee (done) | D9: TAMA | E9: Technology Specifi - TS | F9: Ansible | G9: 9-3- Infra components, 4-3- Dependecies & integration, 4-1- Idempotency & State management, 5-1- Resource Optimization, 5-2- Scalability, 6-1- Code Readability, 9- Domain Specific Issues, 6- Maintability & Documentation, 4- Operational Quality, 5- Performance & Resource management, 1- Structural Quality, 2- Syntactic & Linguistic Quality, 3- Security | H9: Implementation | I9: Script | J9: Config management | K9: Pattern Algorithms | L9: 1 - Rule-Based and Pattern-Matching Approaches | M9: Static | N9: Yes | O9: https://github.com/akondrahman/IaCTesting https://figshare.com/s/4aa50ec7c34c18c71223 https://hub.docker.com/r/talismanic/tama | P9: RankA | Q9: 2022 | R9: WhiteBox | S9: Both | T9: Figshare, Docker hub, Github
A10: State Reconciliation Defects in Infrastructure as Code | B10: https://dl.acm.org/doi/10.1145/3660790 | C10: acm (done) | D10: -------------- | E10: Technology Agnostic - TA | F10: Multi (for TA) | G10: 4-3- Dependecies & integration, 8-1- Program Flow, 4-1- Idempotency & State management, 9-3- Infra components, 9-2- Cloud Provider Specfic, 4-2- Error Handling & Reliability, 7-2- Vraibale management, 8-2- Function & Method Logic, 3-1- Authentication & Authorization, 3-2- Secrets Management, 2-3- Language constructs, 5- Performance & Resource management, 2- Syntactic & Linguistic Quality, 4- Operational Quality, 7- Data & Variable management, 8- Control Flow & Logic, 9- Domain Specific Issues, 3- Security | H10: Runtime | I10: Script | J10: Other | K10: Other | L10: 5 - Testing & Excution based | M10: Hybrid | N10: Yes | O10: https://figshare.com/articles/dataset/State_Reconciliation_Defects_in_Infrastructure_as_Code/24129996?file=44810890 | P10: RankA* | Q10: 2024 | R10: WhiteBox | S10: Both | T10: Figshare
A11: Toward a catalog of software quality metrics for infrastructure code | B11: https://www.sciencedirect.com/science/article/pii/S0164121220301618 | C11: science direct (done) | D11: -------------- | E11: Technology Agnostic - TA | F11: Ansible | G11: 1-3- Code structure, 6-1- Code Readability, 2-2- Syntax & Formatting, 8-1- Program Flow, 8-2- Function & Method Logic, 4-1- Idempotency & State management, 3-1- Authentication & Authorization, 6-3- Code Reusability, 1-2- Modularity & Organization, 7-2- Vraibale management, 3-3- Network Security, 2-3- Language constructs, 6-2- Version control & Compatibility, 4-2- Error Handling & Reliability, 4-3- Dependecies & integration, 3-4- Cryptography & Integrity, 2-1- Naming & conventions, 1- Structural Quality, 2- Syntactic & Linguistic Quality, 3- Security, 4- Operational Quality, 6- Maintability & Documentation, 7- Data & Variable management, 8- Control Flow & Logic | H11: Implementation | I11: Script | J11: Config management | K11: NA | L11: NA | M11: NA | N11: No | O11: Not available | Q11: 2020 | R11: NA | S11: Not available | T11: NA
A12: Smells-sus: Sustainability Smells in IaC | B12: https://arxiv.org/abs/2501.07676 https://www.computer.org/csdl/proceedings-article/msr/2025/018300a801/27vTr57za7K https://ieeexplore.ieee.org/document/11025603 | C12: ieee (done) | D12: -------------- | E12: Technology Specifi - TS | F12: Terraform | G12: 5-1- Resource Optimization, 5-2- Scalability, 5-3- Lifecycle management, 4-1- Idempotency & State management, 1-2- Modularity & Organization, 5- Performance & Resource management, 4- Operational Quality, 1- Structural Quality | H12: Implementation | I12: Script | J12: Provisioning | K12: Regular Expressions - RegX | L12: 1 - Rule-Based and Pattern-Matching Approaches | M12: Static | N12: Yes | O12: https://zenodo.org/records/14020461 | Q12: 2025 | R12: WhiteBox | S12: Both | T12: Zenodo
A13: Security Smells in Ansible and Chef Scripts: A Replication Study | B13: https://dl.acm.org/doi/10.1145/3408897 | C13: acm (done) | D13: SLAC | E13: Technology Dependent - TD | F13: Chef, Ansible | G13: 3-1- Authentication & Authorization, 3-2- Secrets Management, 3-3- Network Security, 3-4- Cryptography & Integrity, 2-3- Language constructs, 3- Security, 2- Syntactic & Linguistic Quality | H13: Implementation | I13: Script | J13: Config management | K13: Regular Expressions - RegX | L13: 1 - Rule-Based and Pattern-Matching Approaches | M13: Static | N13: Yes | O13: https://figshare.com/articles/dataset/Dataset_for_Security_Smells_for_Ansible_and_Chef_Scripts_A_Replication_Study_/8085755 | P13: Journal | Q13: 2021 | R13: WhiteBox | S13: Dataset | T13: Figshare
A14: Rehearsal: a configuration verification tool for puppet | B14: https://dl.acm.org/doi/10.1145/2908080.2908083 | C14: acm | D14: Rehearsal | E14: Technology Specifi - TS | F14: Puppet | G14: 4-1- Idempotency & State management, 4-2- Error Handling & Reliability, 4-3- Dependecies & integration, 4- Operational Quality | H14: Implementation | I14: Script | J14: Config management | K14: Resource Graph - RG, SMT solvers | L14: 3 - Formal Methods, 2 - Graph-Based Analyses | M14: Static | N14: Yes | O14: https://github.com/plasma-umass/Rehearsal/ | Q14: 2016 | R14: WhiteBox | S14: Both | T14: Github
A18: Within-Project Defect Prediction of Infrastructure-as-Code Using Product and Process Metrics | B18: https://ieeexplore.ieee.org/document/9321740 | C18: ieee (done) | D18: RADON | E18: Technology Specifi - TS | F18: Ansible | G18: 1- Structural Quality, 2- Syntactic & Linguistic Quality, 6- Maintability & Documentation, 8- Control Flow & Logic, 7- Data & Variable management | H18: Implementation | I18: Script | J18: Config management | K18: Machine Learning - ML | L18: 4 - Statistical and Learning-Based Methods | M18: Static | N18: Yes | O18: https://www.kaggle.com/datasets/stefadp/ansibledefectsprediction https://github.com/stefanodallapalma/TSE-2020-05-0217 https://github.com/radon-h2020/radon-defect-prediction-api | Q18: 2022 | R18: WhiteBox | S18: Both | T18: Kaggle, Github
A19: Defuse: A Data Annotator and Model Builder for Software Defect Prediction | B19: https://ieeexplore.ieee.org/document/9978237 | C19: ieee (done) | D19: DEFUSE | E19: Technology Agnostic - TA | F19: Ansible, TOSCA | G19: 8-1- Program Flow, 7-1- Configuration Data, 4-3- Dependecies & integration, 6-1- Code Readability, 9-3- Infra components, 4-1- Idempotency & State management, 3- Security, 4- Operational Quality, 8- Control Flow & Logic, 7- Data & Variable management, 6- Maintability & Documentation, 9- Domain Specific Issues | H19: Implementation | I19: Script | J19: Config management | K19: Machine Learning - ML | L19: 4 - Statistical and Learning-Based Methods | M19: Static | N19: Yes | O19: https://github.com/radon-h2020/radon-defuse | P19: RankA (short paper) | Q19: 2022 | R19: WhiteBox | S19: Both | T19: Github
A20: TerraMetrics: An Open Source Tool for Infrastructure-as-Code (IaC) Quality Metrics in Terraform | B20: https://dl.acm.org/doi/10.1145/3643916.3644439 | C20: acm (done) | D20: Terrametrics | E20: Technology Specifi - TS | F20: Terraform | G20: 1-3- Code structure, 2-2- Syntax & Formatting, 7-2- Vraibale management, 2-3- Language constructs, 4-3- Dependecies & integration, 6-1- Code Readability, 8-1- Program Flow, 8-2- Function & Method Logic, 4-2- Error Handling & Reliability, 1- Structural Quality, 2- Syntactic & Linguistic Quality, 4- Operational Quality, 6- Maintability & Documentation, 7- Data & Variable management, 8- Control Flow & Logic | H20: Implementation | I20: Script | J20: Provisioning | K20: AST traversal, Visitor Pattern | L20: 2 - Graph-Based Analyses | M20: Static | N20: Yes | O20: https://github.com/stilab-ets/terametrics | P20: RankA | Q20: 2024 | R20: WhiteBox | S20: Both | T20: Github
A21: Repairing Infrastructure-as-Code using Large Language Models | B21: https://ieeexplore.ieee.org/document/10734039 | C21: ieee (done) | D21: -------------- | E21: Technology Specifi - TS | F21: Terraform | G21: 3- Security | H21: Implementation | I21: Script | J21: Provisioning | K21: LLMs | L21: 4 - Statistical and Learning-Based Methods | M21: Static | N21: Yes | O21: Not available | Q21: 2024 | R21: WhiteBox | S21: Not available | T21: NA
A22: Security in DevSecOps: Applying Tools and Machine Learning to Verification and Monitoring Steps | B22: https://dl.acm.org/doi/10.1145/3578245.3584943 | C22: acm (done) | D22: - IaC Scan Runner - LOMOS | E22: Technology Specifi - TS | F22: Ansible | G22: 3- Security | H22: Implementation, Runtime | I22: Script | J22: Config management | K22: Rule-based checks, NLP | L22: 1 - Rule-Based and Pattern-Matching Approaches, 4 - Statistical and Learning-Based Methods | M22: Hybrid | N22: Yes | O22: https://github.com/xlab-si/iac-scan-runner https://xlab-si.github.io/iac-scanner-docs/02-runner.html | P22: RankB (short paper) | Q22: 2023 | R22: WhiteBox | S22: Both | T22: Github
A23: InfraFix: Technology-Agnostic Repair of Infrastructure as Code | B23: https://dl.acm.org/doi/10.1145/3713081.3731735 https://arxiv.org/abs/2503.17220 https://conf.researchr.org/details/issta-2025/issta-2025-tool-demonstrations/15/InfraFix-Technology-Agnostic-Repair-of-Infrastructure-as-Codehttps://dl.acm.org/doi/10.1145/3713081.3731735 | C23: acm (done) | D23: InfraFix | E23: Technology Agnostic - TA | F23: Multi (for TA) | G23: 3- Security, 7- Data & Variable management, 8- Control Flow & Logic | H23: Implementation | I23: Script | J23: Other | K23: SMT solvers | L23: 3 - Formal Methods | M23: Static | N23: Yes | O23: https://zenodo.org/records/15198041 | P23: RankA (short paper) | Q23: 2025 | R23: WhiteBox | S23: Both | T23: Zenodo
A24: Towards Sustainable Cloud Deployments: A Cost (Anti)Patterns Catalog for Terraform and Cloudformation | B24: https://papers.ssrn.com/sol3/papers.cfm?abstract_id=5137165 | C24: Not peer reviewed | D24: IaC-Cost Linter | E24: Technology Specifi - TS | F24: Terraform, Cloud Formation | G24: 5-1- Resource Optimization, 5-3- Lifecycle management, 9-2- Cloud Provider Specfic, 9- Domain Specific Issues, 5- Performance & Resource management | H24: Implementation | I24: Script | J24: Provisioning | K24: Regular Expressions - RegX | L24: 1 - Rule-Based and Pattern-Matching Approaches | M24: Static | N24: Yes | O24: https://zenodo.org/records/11319775 (dataset of cost awerness) https://github.com/search-rug/iac-cost-linter/ https://zenodo.org/records/14501830 (IaC cost patterns) | Q24: 2025 | R24: WhiteBox | S24: Both | T24: Github, Zenodo
A26: A Framework for Measuring the Quality of Infrastructure-as-Code Scripts | B26: https://arxiv.org/abs/2502.03127 | C26: Not peer reviewed | D26: ------------- (Freamwork for IaC quality based on the standard ISO/IEC 25010:2011⁦) | E26: Technology Specifi - TS | F26: Ansible | G26: 6-1- Code Readability, 1-3- Code structure, 1-2- Modularity & Organization, 4-2- Error Handling & Reliability, 6-2- Version control & Compatibility, 2-1- Naming & conventions, 2-2- Syntax & Formatting, 8-2- Function & Method Logic, 8-1- Program Flow, 3-2- Secrets Management, 3-3- Network Security, 3-4- Cryptography & Integrity, 4-3- Dependecies & integration, 4-1- Idempotency & State management, 7-2- Vraibale management, 1- Structural Quality, 2- Syntactic & Linguistic Quality, 3- Security, 4- Operational Quality, 6- Maintability & Documentation, 7- Data & Variable management, 8- Control Flow & Logic | H26: Implementation | I26: Script | J26: Config management | L26: 1 - Rule-Based and Pattern-Matching Approaches, 4 - Statistical and Learning-Based Methods | M26: Static | N26: Yes | O26: https://figshare.com/s/b78d2c82767ab7d86beb | Q26: 2025 | R26: WhiteBox | S26: Both | T26: Figshare
A35: Statically Inferring Usage Bounds for Infrastructure as Code | B35: https://link.springer.com/chapter/10.1007/978-3-031-86695-1_6 https://link.springer.com/chapter/10.1007/978-3-031-86695-1_6 | C35: springer | D35: IaCAnalysis (Cost prediction) | E35: Technology Specifi - TS | F35: Cloud Formation | G35: 5-1- Resource Optimization, 5- Performance & Resource management | H35: Implementation | I35: Project | J35: Provisioning | K35: SMT solvers, Resource Graph - RG | L35: 2 - Graph-Based Analyses, 3 - Formal Methods | M35: Static | N35: Yes | O35: https://zenodo.org/records/10173400 https://github.com/Barnard-PL-Labs/IaCAnalysis/tree/main/pipr_dataset | Q35: 2024 | R35: WhiteBox | S35: Both | T35: Github, Zenodo
A36: A Comparative Study on the Security of Kubernetes Deployments | B36: https://ieeexplore.ieee.org/document/10592468 | C36: ieee | D36: kubesecurity-scanner | E36: Technology Specifi - TS | F36: Kubernetes | G36: 3-1- Authentication & Authorization, 3-2- Secrets Management, 3-3- Network Security, 5-1- Resource Optimization, 3- Security, 5- Performance & Resource management | H36: Implementation | I36: Project | J36: Orchestration | K36: Other | L36: 6 - Other | M36: Static | N36: Yes | O36: https://github.com/kamieniarzk/kube-security-scanner | P36: RankB | Q36: 2024 | R36: WhiteBox | S36: Both | T36: Github
A47: A Pilot Study of Testing Infrastructure as Code for Cloud Systems | B47: https://ieeexplore.ieee.org/document/10479426 | C47: ieee (done) | D47: ------------- (Server IaC test types) | E47: Technology Agnostic - TA | F47: Multi (for TA) | G47: 8-2- Function & Method Logic, 4-3- Dependecies & integration, 7- Data & Variable management, 4-2- Error Handling & Reliability, 3-1- Authentication & Authorization, 3-2- Secrets Management, 3-3- Network Security, 3- Security, 4- Operational Quality, 8- Control Flow & Logic | H47: Implementation | I47: Script | J47: Other | K47: NA | L47: NA | M47: NA | N47: No | O47: https://github.com/nabhan-au/Testing-IaC-Research/tree/main | P47: RankC (short paper) | Q47: 2023 | R47: NA | S47: Dataset | T47: Github
A54: An Empirical Study of Task Infections in Ansible Scripts | B54: https://akondrahman.github.io/files/papers/emse2024-tidal.pdf https://link.springer.com/article/10.1007/s10664-023-10432-6 https://dl.acm.org/doi/10.1007/s10664-023-10432-6 | C54: springer (done) | D54: TIDAL (Task Infection Detector for Ansible Scripts) | E54: Technology Specifi - TS | F54: Ansible | G54: 3-1- Authentication & Authorization, 3-2- Secrets Management, 3-4- Cryptography & Integrity, 3-3- Network Security, 9-2- Cloud Provider Specfic, 9-3- Infra components, 3- Security, 9- Domain Specific Issues | H54: Implementation | I54: Script | J54: Config management | K54: Pattern Matching, Data Dependecy Graph - DDG | L54: 1 - Rule-Based and Pattern-Matching Approaches, 2 - Graph-Based Analyses | M54: Static | N54: Yes | O54: https://figshare.com/s/c9d7b8aa973f53f02234?file=42146865 | Q54: 2023 | R54: WhiteBox | S54: Both | T54: Figshare
A60: Unearthing Semantic Checks for Cloud Infrastructure-as-Code Programs | B60: https://dl.acm.org/doi/10.1145/3694715.3695974 | C60: acm (done) | D60: Zodiac (Very good tool) | E60: Technology Dependent - TD | F60: Terraform | G60: 9- Domain Specific Issues | H60: Runtime | I60: Script | J60: Provisioning | K60: Configuration mining, LLMs, SMT solvers, Resource Graph - RG | L60: 4 - Statistical and Learning-Based Methods, 2 - Graph-Based Analyses, 3 - Formal Methods | M60: Dynamic | N60: Yes | O60: https://github.com/824728350/Zodiac | P60: RankA* | Q60: 2025 | R60: WhiteBox | S60: Both | T60: Github
A61: KubeHound: Detecting Microservices’ Security Smells in Kubernetes Deployments | B61: https://www.mdpi.com/1999-5903/15/7/228 | C61: other | D61: KubeHound | E61: Technology Specifi - TS | F61: Kubernetes | G61: 3-1- Authentication & Authorization, 3-2- Secrets Management, 3-3- Network Security, 3-4- Cryptography & Integrity, 3- Security | H61: Implementation | I61: Project | J61: Orchestration | L61: 1 - Rule-Based and Pattern-Matching Approaches, 2 - Graph-Based Analyses, 5 - Testing & Excution based | M61: Hybrid | N61: Yes | O61: https://github.com/di-unipi-socc/kube-hound https://github.com/di-unipi-socc/kube-hound/tree/master/data/examples https://archive.softwareheritage.org/browse/origin/directory/?origin_url=https://github.com/di-unipi-socc/kube-hound&path=data/examples | P61: Journal | Q61: 2023 | R61: WhiteBox | S61: Both | T61: Github
A67: Towards a Taxonomy of Infrastructure as Code Misconfigurations: An Ansible Study | B67: https://drive.google.com/file/d/101WCE65iQBGi4cWxln1_3Y2xKRb-2DUc/view?usp=sharing https://link.springer.com/chapter/10.1007/978-3-031-72578-4_5 | C67: springer (done) | D67: ------------- | E67: Technology Agnostic - TA | F67: Ansible | G67: 4-3- Dependecies & integration, 4-1- Idempotency & State management, 7-1- Configuration Data, 7-2- Vraibale management, 3-2- Secrets Management, 6-2- Version control & Compatibility, 3- Security, 4- Operational Quality, 6- Maintability & Documentation, 7- Data & Variable management | H67: Implementation | I67: Module | J67: Config management | K67: Other | L67: 6 - Other | M67: Static | N67: Yes | O67: https://github.com/SODALITE-EU/defect-prediction https://zenodo.org/records/13147770 | P67: Journal | Q67: 2025 | R67: WhiteBox | S67: Both | T67: Github, Zenodo
A68: Automated Infrastructure as Code Program Testing | B68: https://ieeexplore.ieee.org/document/10516612 | C68: ieee (done) | D68: ProTI | E68: Technology Dependent - TD | F68: Pulumi | G68: 4-2- Error Handling & Reliability, 4-3- Dependecies & integration, 7-1- Configuration Data, 2-3- Language constructs, 7- Data & Variable management, 2- Syntactic & Linguistic Quality, 4- Operational Quality | H68: Runtime, Implementation | I68: Script | J68: Provisioning | K68: Tests | L68: 6 - Other | M68: Dynamic | N68: Yes | O68: https://zenodo.org/records/14203377 https://github.com/proti-iac/proti/tree/v1.3.0 | P68: Journal | Q68: 2024 | R68: WhiteBox | S68: Code access | T68: Github, Zenodo
A69: Detecting and Characterizing Propagation of Security Weaknesses in Puppet-Based Infrastructure Management | B69: https://dl.acm.org/doi/10.1109/TSE.2023.3265962 | C69: acm (done) | D69: TaintPup | E69: Technology Specifi - TS | F69: Puppet | G69: 3- Security, 3-2- Secrets Management, 3-4- Cryptography & Integrity, 3-1- Authentication & Authorization, 3-3- Network Security | H69: Implementation | I69: Script | J69: Config management | K69: Data Dependecy Graph - DDG, Regular Expressions - RegX | L69: 2 - Graph-Based Analyses, 1 - Rule-Based and Pattern-Matching Approaches | M69: Static | N69: Yes | O69: Not available | P69: Journal | Q69: 2023 | R69: WhiteBox | S69: Not available | T69: NA
A70: Patterns of Multi-Container Composition for Service Orchestration with Docker Compose | B70: http://arxiv.org/abs/2305.11293 https://link.springer.com/article/10.1007/s10664-024-10462-8 | C70: springer (done) | D70: ------------- | E70: Technology Specifi - TS | F70: Docker-compose | G70: 6-3- Code Reusability, 1-3- Code structure, 1-1- Abstraction issues, 1-2- Modularity & Organization, 3-4- Cryptography & Integrity, 3-3- Network Security, 5-3- Lifecycle management, 4-3- Dependecies & integration, 4-1- Idempotency & State management, 9-3- Infra components, 5-2- Scalability, 9- Domain Specific Issues, 4- Operational Quality, 3- Security, 1- Structural Quality, 5- Performance & Resource management, 6- Maintability & Documentation | H70: Design, Implementation | I70: Project | J70: Orchestration | K70: NA | L70: NA | M70: NA | N70: No | O70: https://zenodo.org/records/10648448 | P70: Journal | Q70: 2024 | R70: NA | S70: Both | T70: Zenodo
A71: Exploring LLM-Based Automated Repairing of Ansible Script in Edge-Cloud Infrastructures | B71: https://ieeexplore.ieee.org/abstract/document/10376418 | C71: ieee (done) | D71: ------------- | E71: Technology Specifi - TS | F71: Ansible | G71: 4- Operational Quality | H71: Implementation | I71: Script | J71: Config management | K71: LLMs | L71: 4 - Statistical and Learning-Based Methods | M71: Static | N71: Yes | O71: Not available | P71: Journal | Q71: 2023 | R71: WhiteBox | S71: Not available | T71: NA
A72: An Empirical Study on Kubernetes Operator Bugs | B72: https://dl.acm.org/doi/10.1145/3650212.3680396 | C72: acm | D72: ------------- | E72: Technology Specifi - TS | F72: Kubernetes | G72: 4- Operational Quality | H72: Implementation | I72: Module | J72: Orchestration | K72: NA | L72: NA | M72: NA | N72: No | O72: yes (list of bugs) https://zenodo.org/records/13340387 | P72: RankA | Q72: 2024 | R72: NA | S72: Dataset | T72: Zenodo
A73: Control and Data Flow in Security Smell Detection for Infrastructure as Code: Is It Worth the Effort? | B73: https://ieeexplore.ieee.org/document/10174011 | C73: ieee (done) | D73: GASEL | E73: Technology Specifi - TS | F73: Ansible | G73: 3- Security | H73: Implementation | I73: Project | J73: Config management | K73: Control Flow Graph, Program Dependncy Graph - PDG | L73: 2 - Graph-Based Analyses | M73: Static | N73: Yes | O73: Andromeda dataset + Saavedra et al. [12]. https://figshare.com/articles/dataset/Replication_package_for_Control_and_Data_Flow_in_Security_Smell_Detection_for_Infrastructure_as_Code_Is_It_Worth_the_Effort_/21929856 | P73: RankA | Q73: 2023 | R73: WhiteBox | S73: Both | T73: Figshare
A74: On the Prevalence, Co-occurrence, and Impact of Infrastructure-as-Code Smells | B74: https://ieeexplore.ieee.org/document/10589858 | C74: ieee (done) | D74: Puppeteer + PuppetLint | E74: Technology Specifi - TS | F74: Puppet | G74: 1- Structural Quality | H74: Design, Implementation | I74: Script, Module | J74: Config management | K74: Rule-based checks, AST traversal | L74: 1 - Rule-Based and Pattern-Matching Approaches, 2 - Graph-Based Analyses | M74: Static | N74: Yes | O74: https://zenodo.org/records/10060209 | P74: RankA | Q74: 2024 | R74: WhiteBox | S74: Both | T74: Figshare
A75: Fine-Grained Just-In-Time Defect Prediction at the Block Level in Infrastructure-as-Code (IaC) | Proceedings of the 21st International Conference on Mining Software Repositories | B75: https://dl.acm.org/doi/10.1145/3643991.3644934 | C75: acm (done) | D75: ------------- | E75: Technology Specifi - TS | F75: Terraform | G75: 1- Structural Quality, 1-3- Code structure, 4- Operational Quality, 4-2- Error Handling & Reliability | H75: Design | I75: Project | J75: Provisioning | K75: Machine Learning - ML | L75: 4 - Statistical and Learning-Based Methods | M75: Static | N75: Yes | O75: https://figshare.com/s/facf0404c96b32274a35?file=44159249 | P75: RankA | Q75: 2024 | R75: WhiteBox | S75: Both | T75: Figshare
A76: Smoke Testing of Cloud Systems | B76: https://ieeexplore.ieee.org/document/9787844 | C76: ieee | D76: ------------- | E76: Technology Agnostic - TA | F76: Multi (for TA) | G76: 5- Performance & Resource management, 5-1- Resource Optimization, 5-3- Lifecycle management, 1- Structural Quality | H76: Implementation | I76: Project | J76: Other | K76: Tests | L76: 5 - Testing & Excution based | M76: Dynamic | N76: Yes | O76: https://github.com/cannavit/smoke-test.git | P76: RankA | Q76: 2022 | R76: WhiteBox | S76: Code access | T76: Github
A77: Source code properties of defective infrastructure as code scripts | B77: https://dl.acm.org/doi/10.1016/j.infsof.2019.04.013 | C77: science direct (done) | D77: ------------- | E77: Technology Dependent - TD | F77: Puppet | G77: 1- Structural Quality, 1-3- Code structure, 6- Maintability & Documentation, 6-1- Code Readability, 7- Data & Variable management, 7-2- Vraibale management | H77: Design | I77: Script | J77: Config management | K77: Configuration mining, Statistical Learners | L77: 4 - Statistical and Learning-Based Methods | M77: NA | N77: No | O77: https://figshare.com/s/ad26e370c833e8aa9712 | Q77: 2019 | R77: NA | S77: Dataset | T77: Figshare
A78: Security Misconfigurations in Open Source Kubernetes Manifests: An Empirical Study | B78: https://dl.acm.org/doi/10.1145/3579639 | C78: acm (done) | D78: SLI-KUBE | E78: Technology Dependent - TD | F78: Kubernetes | G78: 3- Security, 3-1- Authentication & Authorization, 3-2- Secrets Management, 3-3- Network Security, 9- Domain Specific Issues, 9-1- Container & Orchestration | H78: Design | I78: Script | J78: Orchestration | K78: Rule-based checks | L78: 1 - Rule-Based and Pattern-Matching Approaches | M78: Static | N78: Yes | O78: https://figshare.com/s/bced7c8353853a983cd7 | Q78: 2023 | R78: WhiteBox | S78: Both | T78: Figshare
A79: Infrastructure as code for dynamic deployments | B79: https://dl.acm.org/doi/10.1145/3540250.3558912 | C79: acm (done) | D79: DIaC ProTI | E79: Technology Dependent - TD | F79: Pulumi | G79: NA | H79: Implementation | I79: Script | J79: Provisioning | K79: Resource Graph - RG | L79: 2 - Graph-Based Analyses | M79: Static | N79: Yes | O79: Not available | P79: RankA* | Q79: 2022 | R79: WhiteBox | S79: Not available | T79: NA
A80: Towards the self-healing of Infrastructure as Code projects using constrained LLM technologies | Proceedings of the 5th ACM/IEEE International Workshop on Automated Program Repair | B80: https://dl.acm.org/doi/10.1145/3643788.3648014 | C80: acm (done) | D80: ------------- | E80: Technology Specifi - TS | F80: Ansible | G80: 2- Syntactic & Linguistic Quality | H80: Implementation | I80: Script | J80: Config management | K80: LLMs, RAG | L80: 4 - Statistical and Learning-Based Methods | M80: Static | N80: Yes | O80: Not available | P80: RankA* | Q80: 2024 | R80: WhiteBox | S80: Not available | T80: NA
A81: Leveraging Practitioners’ Feedback to Improve a Security Linter | Proceedings of the 37th IEEE/ACM International Conference on Automated Software Engineering | B81: https://dl.acm.org/doi/10.1145/3551349.3560419 | C81: acm (done) | D81: InfraSecure | E81: Technology Specifi - TS | F81: Puppet | G81: 3-1- Authentication & Authorization, 3-2- Secrets Management, 3-3- Network Security, 3-4- Cryptography & Integrity, 3- Security | H81: Implementation | I81: Script | J81: Config management | K81: AST traversal, Pattern Matching | L81: 1 - Rule-Based and Pattern-Matching Approaches, 2 - Graph-Based Analyses | M81: Static | N81: Yes | O81: https://figshare.com/s/6b6a769b1393eae0774c?file=36708486 | P81: RankA* | Q81: 2023 | R81: WhiteBox | S81: Both | T81: Figshare
A82: Characterizing Co-located Insecure Coding Patterns in Infrastructure as Code Scripts | B82: https://ieeexplore.ieee.org/document/9319290 | C82: ieee (done) | D82: ------------- | E82: Technology Specifi - TS | F82: Puppet | G82: 3-1- Authentication & Authorization, 3-2- Secrets Management, 3-3- Network Security, 3-4- Cryptography & Integrity, 3- Security | H82: Implementation | I82: Script | J82: Config management | K82: NA | L82: 6 - Other | M82: Static | N82: Yes | O82: https://figshare.com/s/f64f56ec9eaf2eab1af4 | P82: RankA* | Q82: 2020 | R82: WhiteBox | S82: Dataset | T82: Figshare
A83: Unleashing the Giants: Enabling Advanced Testing for Infrastructure as Code | B83: https://dl.acm.org/doi/10.1145/3639478.3643078 | C83: acm (done) | D83: ProTI | E83: Technology Dependent - TD | F83: Pulumi | G83: 4-2- Error Handling & Reliability, 4-1- Idempotency & State management, 4- Operational Quality, 3- Security | H83: Implementation | I83: Script | J83: Provisioning | K83: Tests | L83: 5 - Testing & Excution based | M83: Static | N83: Yes | O83: https://github.com/proti-iac/proti/tree/v1.3.0 https://zenodo.org/records/14203377 | P83: RankA* | Q83: 2024 | R83: WhiteBox | S83: Both | T83: Zenodo, Github
A84: Ansible Lightspeed: A Code Generation Service for IT Automation | B84: https://dl.acm.org/doi/abs/10.1145/3691620.3695277 | C84: acm (done) | D84: Ansible Lightspeed | E84: Technology Specifi - TS | F84: Ansible | G84: 2-3- Language constructs, 2-1- Naming & conventions, 1-3- Code structure, 1- Structural Quality, 2- Syntactic & Linguistic Quality | H84: Implementation | I84: Module | J84: Config management | K84: LLMs | L84: 4 - Statistical and Learning-Based Methods | M84: Static | N84: Yes | O84: https://github.com/ansible/ansible-ai-connect-service https://github.com/ansible-community/lightspeed-analysis-framework | P84: RankA* | Q84: 2024 | R84: WhiteBox | S84: Code access | T84: Github
A85: The Seven Sins: Security Smells in Infrastructure as Code Scripts | B85: https://ieeexplore.ieee.org/document/8812041 | C85: ieee (done) | D85: SLIC - Security Linters for Infrastructure as Code | E85: Technology Specifi - TS | F85: Puppet | G85: 3-1- Authentication & Authorization, 3-2- Secrets Management, 3-4- Cryptography & Integrity, 3-3- Network Security, 3- Security | H85: Implementation | I85: Script | J85: Config management | K85: Pattern Matching, Rule-based checks | L85: 1 - Rule-Based and Pattern-Matching Approaches | M85: Static | N85: Yes | O85: https://doi.org/10.6084/m9.figshare.6943316 | P85: RankA* | Q85: 2019 | R85: WhiteBox | S85: Both | T85: Figshare
A86: Tortoise: Interactive system configuration repair | B86: https://ieeexplore.ieee.org/document/8115673/citations | C86: ieee | D86: Tortoise | E86: Technology Dependent - TD | F86: Puppet | G86: 6-2- Version control & Compatibility, 4-1- Idempotency & State management, 6- Maintability & Documentation, 4- Operational Quality | H86: Runtime | I86: Script | J86: Config management | K86: SMT solvers | L86: 3 - Formal Methods | M86: Static | N86: Yes | O86: https://github.com/plasma-umass/Tortoise | P86: RankA* | Q86: 2017 | R86: WhiteBox | S86: Both | T86: Github
A87: Dockerlive : A live development environment for Dockerfiles | B87: https://ieeexplore.ieee.org/document/9833145 | C87: ieee | D87: Dockerlive | E87: Technology Specifi - TS | F87: Docker | G87: 4- Operational Quality, 2- Syntactic & Linguistic Quality, 5- Performance & Resource management, 7- Data & Variable management | H87: Implementation, Runtime | I87: Script | J87: Image building | K87: Other | L87: 5 - Testing & Excution based | M87: Hybrid | N87: Yes | O87: https://github.com/SoftwareForHumans/Dockerlive | P87: Short | Q87: 2022 | R87: WhiteBox | S87: Code access | T87: Github
A88: Code Smells in Infrastructure as Code | B88: https://ieeexplore.ieee.org/document/8590193 | C88: ieee (done) | D88: foodcritic | E88: Technology Dependent - TD | F88: Chef, Puppet | G88: 1- Structural Quality, 2- Syntactic & Linguistic Quality | H88: Design, Implementation | I88: Script | J88: Config management | K88: Pattern Matching, Rule-based checks, AST traversal, Visitor Pattern | L88: 1 - Rule-Based and Pattern-Matching Approaches, 2 - Graph-Based Analyses | M88: Static | N88: Yes | O88: Not available | P88: RankC | Q88: 2018 | R88: WhiteBox | S88: Not available | T88: NA
A89: Towards Reliable Infrastructure as Code | B89: https://ieeexplore.ieee.org/document/10092598/citations#citations | C89: ieee (done) | D89: ProTI | E89: Technology Dependent - TD | F89: Pulumi | G89: 4- Operational Quality | H89: Implementation | I89: Script | J89: Provisioning | K89: Tests | L89: 5 - Testing & Excution based | M89: Dynamic | N89: Yes | O89: Not available | P89: RankA | Q89: 2023 | R89: WhiteBox | S89: Not available | T89: NA
A90: Securing Infrastructure as Code (IaC) through DevSecOps:A Comprehensive Risk Management Framework | B90: https://ieeexplore.ieee.org/document/10671452 | C90: ieee (done) | D90: ------------- | E90: Technology Agnostic - TA | F90: Multi (for TA) | G90: 3- Security | H90: Design, Runtime | I90: Project | J90: Other | K90: NA | L90: NA | M90: NA | N90: No | O90: Not available | Q90: 2023 | R90: NA | S90: Not available | T90: NA
A91: Extensible Testing for Infrastructure as Code | B91: https://dl.acm.org/doi/10.1145/3618305.3623607 | C91: acm (done) | D91: ProTI | E91: Technology Dependent - TD | F91: Pulumi | G91: 4-2- Error Handling & Reliability, 4-1- Idempotency & State management, 4- Operational Quality, 3- Security | H91: Implementation | I91: Script | J91: Provisioning | K91: Tests, Resource Graph - RG | L91: 2 - Graph-Based Analyses, 5 - Testing & Excution based | M91: Static | N91: Yes | O91: Not available | Q91: 2023 | R91: WhiteBox | S91: Not available | T91: NA
A92: K8s Pro Sentinel: Extend Secret Security in Kubernetes Cluster | B92: https://ieeexplore.ieee.org/document/10857769 | C92: ieee | D92: K8s Pro Sentinel | E92: Technology Specifi - TS | F92: Kubernetes | G92: 3-2- Secrets Management, 3- Security | H92: Runtime | I92: Script | J92: Orchestration | K92: Other | L92: 6 - Other | M92: Dynamic | N92: Yes | O92: https://github.com/kavinduxo/k8s-pro-sentinel | Q92: 2024 | R92: WhiteBox | S92: Code access | T92: Github
A93: Uncovering Threats in Container Systems: A Study on Misconfigured Container Components in the Wild | B93: https://ieeexplore.ieee.org/document/10788674 | C93: ieee | D93: ------------- | E93: Technology Dependent - TD | F93: Docker, Kubernetes | G93: 3- Security | H93: Runtime | I93: Script | J93: Image building, Orchestration | K93: Other | L93: 6 - Other | M93: Dynamic | N93: Yes | O93: Not available | Q93: 2024 | R93: BlackBox | S93: Not available | T93: NA
A94: Automatically Generating Dockerfiles via Deep Learning: Challenges and Promises | B94: https://ieeexplore.ieee.org/document/10169074 | C94: ieee | D94: ------------- | E94: Technology Specifi - TS | F94: Docker | G94: 2- Syntactic & Linguistic Quality, 4- Operational Quality, 6- Maintability & Documentation, 7- Data & Variable management, 8- Control Flow & Logic | H94: Implementation | I94: Script | J94: Image building | K94: Deep Learning - DL | L94: 4 - Statistical and Learning-Based Methods | M94: Static | N94: Yes | O94: https://figshare.com/articles/dataset/Replication_Package_for_Automatically_Generating_Dockerfiles_via_Deep-Learning_Challenges_and_Promises_/20722396?file=37028938 | Q94: 2023 | R94: WhiteBox | S94: Both | T94: Figshare
A95: Assessing and Improving the Quality of Docker Artifacts | B95: https://ieeexplore.ieee.org/document/9978228 | C95: ieee | D95: ------------- | E95: Technology Specifi - TS | F95: Docker | G95: 2- Syntactic & Linguistic Quality, 3- Security, 4- Operational Quality, 5- Performance & Resource management, 6- Maintability & Documentation | H95: Implementation | I95: Script | J95: Image building | K95: NA | L95: NA | M95: NA | N95: No | O95: Not available | P95: RankA | Q95: 2022 | R95: NA | S95: Not available | T95: NA
A96: AnsibleMetrics: A Python library for measuring Infrastructure-as-Code blueprints in Ansible | B96: https://www.sciencedirect.com/science/article/pii/S2352711020303460 | C96: science direct (done) | D96: Ansible Metrics | E96: Technology Specifi - TS | F96: Ansible | G96: 2-2- Syntax & Formatting, 1-3- Code structure, 2- Syntactic & Linguistic Quality, 1- Structural Quality | H96: Implementation | I96: Script | J96: Config management | K96: Other | L96: 6 - Other | M96: Static | N96: Yes | O96: https://github.com/ElsevierSoftwareX/SOFTX_2020_231 | P96: Q3 | Q96: 2020 | R96: WhiteBox | S96: Code access | T96: Github
A97: How good is your puppet? An empirically defined and validated quality model for puppet | B97: https://ieeexplore.ieee.org/document/8330206 | C97: ieee | D97: ------------- | E97: Technology Specifi - TS | F97: Puppet | G97: 1-2- Modularity & Organization, 1-3- Code structure, 2-2- Syntax & Formatting, 4-1- Idempotency & State management, 6-1- Code Readability, 8- Control Flow & Logic | H97: Implementation | I97: Project | J97: Config management | K97: AST traversal, Configuration mining, Rule-based checks, Statistical Learners | L97: 2 - Graph-Based Analyses, 4 - Statistical and Learning-Based Methods, 1 - Rule-Based and Pattern-Matching Approaches | M97: Static | N97: Yes | O97: https://github.com/evanderbent/PuppetSurveyData | P97: RankA | Q97: 2018 | R97: WhiteBox | S97: Dataset | T97: Github
A98: Empirical Study of the Docker Smells Impact on the Image Size | B98: https://dl.acm.org/doi/10.1145/3597503.3639143 | C98: acm | D98: Parfum | E98: Technology Specifi - TS | F98: Docker | G98: 5-3- Lifecycle management, 5-1- Resource Optimization, 5- Performance & Resource management | H98: Implementation | I98: Script | J98: Image building | K98: AST traversal, Manual annotation, Pattern Matching | L98: 2 - Graph-Based Analyses, 1 - Rule-Based and Pattern-Matching Approaches | M98: Static | N98: Yes | O98: https://zenodo.org/records/10439580 https://zenodo.org/records/10439571 | Q98: 2024 | R98: WhiteBox | S98: Both | T98: Zenodo
A99: The Docker Hub Image Inheritance Network: Construction and Empirical Insights | B99: https://ieeexplore.ieee.org/document/10356403 | C99: ieee | D99: ------------- | E99: Technology Specifi - TS | F99: Docker | G99: 1- Structural Quality, 1-2- Modularity & Organization, 9-1- Container & Orchestration, 3- Security, 9- Domain Specific Issues | H99: Runtime | I99: Module | J99: Image building | K99: Program Dependncy Graph - PDG, Statistical Learners | L99: 2 - Graph-Based Analyses, 4 - Statistical and Learning-Based Methods | M99: NA | N99: No | O99: https://zenodo.org/records/8119368 | Q99: 2023 | R99: NA | S99: Both | T99: Zenodo
A100: Detecting and Resolving Coupling-Related Infrastructure as Code Based Architecture Smells in Microservice Deployments | B100: https://ieeexplore.ieee.org/document/10254973 | C100: ieee | E100: Technology Agnostic - TA | F100: Kubernetes, Docker, Terraform, Helm | G100: 1-2- Modularity & Organization, 1-3- Code structure, 1- Structural Quality | H100: Implementation, Design | I100: Project, Script | J100: Provisioning, Orchestration, Image building | K100: Program Dependncy Graph - PDG, Pattern Matching, Rewriting / Refactoring | L100: 2 - Graph-Based Analyses, 1 - Rule-Based and Pattern-Matching Approaches | M100: Static | N100: Yes | O100: https://zenodo.org/records/7692017 | Q100: 2023 | R100: WhiteBox | S100: Both | T100: Zenodo
A101: Characterizing Static Analysis Alerts for Terraform Manifests: An Experience Report | B101: https://ieeexplore.ieee.org/document/10305615 | C101: ieee (done) | E101: Technology Specifi - TS | F101: Terraform | G101: 3-4- Cryptography & Integrity, 3-1- Authentication & Authorization, 3-3- Network Security, 4-2- Error Handling & Reliability, 4-3- Dependecies & integration, 6-1- Code Readability, 4- Operational Quality, 3- Security, 6- Maintability & Documentation | H101: Implementation | I101: Script | J101: Provisioning | K101: Data Dependecy Graph - DDG, Manual annotation, Pattern Matching | L101: 1 - Rule-Based and Pattern-Matching Approaches, 2 - Graph-Based Analyses | M101: Static | N101: Yes | O101: Not available | P101: Not ranked | Q101: 2023 | R101: WhiteBox | S101: Not available | T101: NA
A102: Co-evolution of Infrastructure and Source Code - An Empirical Study | B102: https://dl.acm.org/doi/10.5555/2820518.2820527 | C102: acm (done) | D102: ------------- | E102: Technology Dependent - TD | F102: Puppet, Chef | G102: 6- Maintability & Documentation | H102: Implementation | I102: Project | J102: Config management | L102: 4 - Statistical and Learning-Based Methods, 1 - Rule-Based and Pattern-Matching Approaches | M102: Static | N102: Yes | O102: https://github.com/yujuanjiang/OpenStackClassificationList | Q102: 2015 | R102: WhiteBox | S102: Dataset | T102: Github
A103: LLM Agentic Workflow for Automated Vulnerability Detection and Remediation in Infrastructure-as-Code | B103: https://ieeexplore.ieee.org/abstract/document/10965635 | C103: ieee (done) | D103: ------------- | E103: Technology Specifi - TS | F103: Cloud Formation | G103: 3- Security | H103: Implementation | I103: Script | J103: Provisioning | K103: LLMs | L103: 4 - Statistical and Learning-Based Methods | M103: Static | N103: Yes | O103: Not available | Q103: 2025 | R103: WhiteBox | S103: Not available | T103: NA
A104: Assessing the adoption of security policies by developers in terraform across different cloud providers | B104: https://doi.org/10.1007/s10664-024-10610-0 | C104: springer (done) | D104: ------------- | E104: Technology Specifi - TS | F104: Terraform | G104: 3- Security | H104: Implementation | I104: Project | J104: Provisioning | L104: 6 - Other | M104: Static | N104: Yes | O104: https://github.com/averdet/master-terraform-sec-adoption | Q104: 2025 | R104: WhiteBox | S104: Both | T104: Github
A105: “Through the looking-glass …” An empirical study on blob infrastructure blueprints in the Topology and Orchestration Specification for Cloud Applications | B105: https://onlinelibrary.wiley.com/doi/abs/10.1002/smr.2533 | C105: wiley | D105: radon-tosca-metrics | E105: Technology Specifi - TS | F105: TOSCA | G105: 1- Structural Quality | H105: Implementation | I105: Script | J105: Other | L105: 1 - Rule-Based and Pattern-Matching Approaches, 4 - Statistical and Learning-Based Methods | M105: Static | N105: Yes | O105: https://github.com/jade-lab/tosca-smells | Q105: 2024 | R105: WhiteBox | S105: Both | T105: Github

Sheet Visualizations2
A1: =IFERROR(__xludf.DUMMYFUNCTION("UNIQUE(ARRAYFORMULA(TRIM(FLATTEN(SPLIT(TEXTJOIN("","", TRUE, 'Final set of papers'!E2:E1000), "","")))))"),"Technology Specifi - TS") -> Technology Specifi - TS | B1: =COUNTIF('Final set of papers'!E2:E1000, "*" & A1 & "*") -> 42 | D1: =IFERROR(__xludf.DUMMYFUNCTION("SORT(UNIQUE(ARRAYFORMULA(TRIM(FLATTEN(SPLIT(TEXTJOIN("","", TRUE, 'Final set of papers'!G2:G1000), "",""))))))"),"1- Structural Quality") -> 1- Structural Quality | E1: =COUNTIF('Final set of papers'!G2:G1000, "*" & D1 & "*") -> 19 | G1: =IFERROR(__xludf.DUMMYFUNCTION("SORT(UNIQUE(ARRAYFORMULA(TRIM(FLATTEN(SPLIT(TEXTJOIN("","", TRUE, 'Final set of papers'!K2:K1000), "",""))))))"),"AST traversal") -> AST traversal | H1: =COUNTIF('Final set of papers'!K2:K1000, "*" & G1 & "*") -> 6 | J1: 1 - Rule-Based and Pattern-Matching Approaches | N1: =IFERROR(__xludf.DUMMYFUNCTION("SORT(UNIQUE(ARRAYFORMULA(TRIM(FLATTEN(SPLIT(TEXTJOIN("","", TRUE, 'Final set of papers'!Q2:Q1000), "",""))))))"),"2015") -> 2015 | O1: =COUNTIF('Final set of papers'!Q2:Q1000, N1) -> 1
A2: =IFERROR(__xludf.DUMMYFUNCTION("""COMPUTED_VALUE"""),"Technology Agnostic - TA") -> Technology Agnostic - TA | B2: =COUNTIF('Final set of papers'!E2:E1000, "*" & A2 & "*") -> 10 | D2: =IFERROR(__xludf.DUMMYFUNCTION("""COMPUTED_VALUE"""),"1-1- Abstraction issues") -> 1-1- Abstraction issues | E2: =COUNTIF('Final set of papers'!G2:G1000, "*" & D2 & "*") -> 3 | G2: =IFERROR(__xludf.DUMMYFUNCTION("""COMPUTED_VALUE"""),"Configuration mining") -> Configuration mining | H2: =COUNTIF('Final set of papers'!K2:K1000, "*" & G2 & "*") -> 3 | J2: Regular Expressions - RegX | N2: =IFERROR(__xludf.DUMMYFUNCTION("""COMPUTED_VALUE"""),"2016") -> 2016 | O2: =COUNTIF('Final set of papers'!Q2:Q1000, N2) -> 2
A3: =IFERROR(__xludf.DUMMYFUNCTION("""COMPUTED_VALUE"""),"Technology Dependent - TD") -> Technology Dependent - TD | B3: =COUNTIF('Final set of papers'!E3:E1000, "*" & A3 & "*") -> 13 | D3: =IFERROR(__xludf.DUMMYFUNCTION("""COMPUTED_VALUE"""),"1-2- Modularity & Organization") -> 1-2- Modularity & Organization | E3: =COUNTIF('Final set of papers'!G2:G1000, "*" & D3 & "*") -> 8 | G3: =IFERROR(__xludf.DUMMYFUNCTION("""COMPUTED_VALUE"""),"Control Flow Graph") -> Control Flow Graph | H3: =COUNTIF('Final set of papers'!K2:K1000, "*" & G3 & "*") -> 1 | J3: Rule-based checks | N3: =IFERROR(__xludf.DUMMYFUNCTION("""COMPUTED_VALUE"""),"2017") -> 2017 | O3: =COUNTIF('Final set of papers'!Q2:Q1000, N3) -> 1
D4: =IFERROR(__xludf.DUMMYFUNCTION("""COMPUTED_VALUE"""),"1-3- Code structure") -> 1-3- Code structure | E4: =COUNTIF('Final set of papers'!G2:G1000, "*" & D4 & "*") -> 12 | G4: =IFERROR(__xludf.DUMMYFUNCTION("""COMPUTED_VALUE"""),"Data Dependecy Graph - DDG") -> Data Dependecy Graph - DDG | H4: =COUNTIF('Final set of papers'!K5:K1000, "*" & G4 & "*") -> 3 | J4: Pattern Matching | N4: =IFERROR(__xludf.DUMMYFUNCTION("""COMPUTED_VALUE"""),"2018") -> 2018 | O4: =COUNTIF('Final set of papers'!Q2:Q1000, N4) -> 2
D5: =IFERROR(__xludf.DUMMYFUNCTION("""COMPUTED_VALUE"""),"2- Syntactic & Linguistic Quality") -> 2- Syntactic & Linguistic Quality | E5: =COUNTIF('Final set of papers'!G2:G1000, "*" & D5 & "*") -> 19 | G5: =IFERROR(__xludf.DUMMYFUNCTION("""COMPUTED_VALUE"""),"Deep Learning - DL") -> Deep Learning - DL | H5: =COUNTIF('Final set of papers'!K2:K1000, "*" & G5 & "*") -> 2 | J5: Pattern Algorithms | N5: =IFERROR(__xludf.DUMMYFUNCTION("""COMPUTED_VALUE"""),"2019") -> 2019 | O5: =COUNTIF('Final set of papers'!Q2:Q1000, N5) -> 3
A6: =IFERROR(__xludf.DUMMYFUNCTION("UNIQUE(ARRAYFORMULA(TRIM(FLATTEN(SPLIT(TEXTJOIN("","", TRUE, 'Final set of papers'!F2:F1000), "","")))))"),"Puppet") -> Puppet | B6: =IFERROR(__xludf.DUMMYFUNCTION("COUNTIF(FLATTEN(ARRAYFORMULA(TRIM(SPLIT('Final set of papers'!F2:F1000, "","")))),A6)"),14.0) -> 14 | D6: =IFERROR(__xludf.DUMMYFUNCTION("""COMPUTED_VALUE"""),"2-1- Naming & conventions") -> 2-1- Naming & conventions | E6: =COUNTIF('Final set of papers'!G2:G1000, "*" & D6 & "*") -> 5 | G6: =IFERROR(__xludf.DUMMYFUNCTION("""COMPUTED_VALUE"""),"LLMs") -> LLMs | H6: =COUNTIF('Final set of papers'!K7:K1000, "*" & G6 & "*") -> 6 | J6: Visitor Pattern | N6: =IFERROR(__xludf.DUMMYFUNCTION("""COMPUTED_VALUE"""),"2020") -> 2020 | O6: =COUNTIF('Final set of papers'!Q2:Q1000, N6) -> 5
A7: =IFERROR(__xludf.DUMMYFUNCTION("""COMPUTED_VALUE"""),"Ansible") -> Ansible | B7: =IFERROR(__xludf.DUMMYFUNCTION("COUNTIF(FLATTEN(ARRAYFORMULA(TRIM(SPLIT('Final set of papers'!F2:F1000, "","")))),A7)"),16.0) -> 16 | D7: =IFERROR(__xludf.DUMMYFUNCTION("""COMPUTED_VALUE"""),"2-2- Syntax & Formatting") -> 2-2- Syntax & Formatting | E7: =COUNTIF('Final set of papers'!G2:G1000, "*" & D7 & "*") -> 7 | G7: =IFERROR(__xludf.DUMMYFUNCTION("""COMPUTED_VALUE"""),"Machine Learning - ML") -> Machine Learning - ML | H7: =COUNTIF('Final set of papers'!K8:K1000, "*" & G7 & "*") -> 3 | J7: 2 - Graph-Based Analyses | N7: =IFERROR(__xludf.DUMMYFUNCTION("""COMPUTED_VALUE"""),"2021") -> 2021 | O7: =COUNTIF('Final set of papers'!Q2:Q1000, N7) -> 1
A8: =IFERROR(__xludf.DUMMYFUNCTION("""COMPUTED_VALUE"""),"Multi (for TA)") -> Multi (for TA) | B8: =COUNTIF('Final set of papers'!F2:F1000, "*" & A8 & "*") -> 6 | D8: =IFERROR(__xludf.DUMMYFUNCTION("""COMPUTED_VALUE"""),"2-3- Language constructs") -> 2-3- Language constructs | E8: =COUNTIF('Final set of papers'!G2:G1000, "*" & D8 & "*") -> 8 | G8: =IFERROR(__xludf.DUMMYFUNCTION("""COMPUTED_VALUE"""),"Manual annotation") -> Manual annotation | H8: =COUNTIF('Final set of papers'!K9:K1000, "*" & G8 & "*") -> 2 | J8: AST Traversal | N8: =IFERROR(__xludf.DUMMYFUNCTION("""COMPUTED_VALUE"""),"2022") -> 2022 | O8: =COUNTIF('Final set of papers'!Q2:Q1000, N8) -> 8
A9: =IFERROR(__xludf.DUMMYFUNCTION("""COMPUTED_VALUE"""),"Terraform") -> Terraform | B9: =IFERROR(__xludf.DUMMYFUNCTION("COUNTIF(FLATTEN(ARRAYFORMULA(TRIM(SPLIT('Final set of papers'!F2:F1000, "","")))),A9)"),9.0) -> 9 | D9: =IFERROR(__xludf.DUMMYFUNCTION("""COMPUTED_VALUE"""),"3- Security") -> 3- Security | E9: =COUNTIF('Final set of papers'!G2:G1000, "*" & D9 & "*") -> 33 | G9: =IFERROR(__xludf.DUMMYFUNCTION("""COMPUTED_VALUE"""),"NA") -> NA | H9: =COUNTIF('Final set of papers'!K10:K1000, "*" & G9 & "*") -> 7 | J9: Control Flow Graph | N9: =IFERROR(__xludf.DUMMYFUNCTION("""COMPUTED_VALUE"""),"2023") -> 2023 | O9: =COUNTIF('Final set of papers'!Q2:Q1000, N9) -> 17
A10: =IFERROR(__xludf.DUMMYFUNCTION("""COMPUTED_VALUE"""),"Chef") -> Chef | B10: =COUNTIF('Final set of papers'!F2:F1000, "*" & A10 & "*") -> 3 | D10: =IFERROR(__xludf.DUMMYFUNCTION("""COMPUTED_VALUE"""),"3-1- Authentication & Authorization") -> 3-1- Authentication & Authorization | E10: =COUNTIF('Final set of papers'!G11:G1000, "*" & D10 & "*") -> 12 | G10: =IFERROR(__xludf.DUMMYFUNCTION("""COMPUTED_VALUE"""),"NLP") -> NLP | H10: =COUNTIF('Final set of papers'!K11:K1000, "*" & G10 & "*") -> 1 | J10: Data Dependecy Graph - DDG | N10: =IFERROR(__xludf.DUMMYFUNCTION("""COMPUTED_VALUE"""),"2024") -> 2024 | O10: =COUNTIF('Final set of papers'!Q2:Q1000, N10) -> 17
A11: =IFERROR(__xludf.DUMMYFUNCTION("""COMPUTED_VALUE"""),"TOSCA") -> TOSCA | B11: =COUNTIF('Final set of papers'!F2:F1000, "*" & A11 & "*") -> 2 | D11: =IFERROR(__xludf.DUMMYFUNCTION("""COMPUTED_VALUE"""),"3-2- Secrets Management") -> 3-2- Secrets Management | E11: =COUNTIF('Final set of papers'!G12:G1000, "*" & D11 & "*") -> 13 | G11: =IFERROR(__xludf.DUMMYFUNCTION("""COMPUTED_VALUE"""),"Other") -> Other | H11: =COUNTIF('Final set of papers'!K2:K1000, "*" & G11 & "*") -> 7 | J11: Program Dependncy Graph - PDG | N11: =IFERROR(__xludf.DUMMYFUNCTION("""COMPUTED_VALUE"""),"2025") -> 2025 | O11: =COUNTIF('Final set of papers'!Q2:Q1000, N11) -> 8
A12: =IFERROR(__xludf.DUMMYFUNCTION("""COMPUTED_VALUE"""),"Cloud Formation") -> Cloud Formation | B12: =COUNTIF('Final set of papers'!F2:F1000, "*" & A12 & "*") -> 3 | D12: =IFERROR(__xludf.DUMMYFUNCTION("""COMPUTED_VALUE"""),"3-3- Network Security") -> 3-3- Network Security | E12: =COUNTIF('Final set of papers'!G13:G1000, "*" & D12 & "*") -> 13 | G12: =IFERROR(__xludf.DUMMYFUNCTION("""COMPUTED_VALUE"""),"Pattern Algorithms") -> Pattern Algorithms | H12: =COUNTIF('Final set of papers'!K2:K1000, "*" & G12 & "*") -> 1 | J12: Resource Graph - RG
A13: =IFERROR(__xludf.DUMMYFUNCTION("""COMPUTED_VALUE"""),"Kubernetes") -> Kubernetes | B13: =COUNTIF('Final set of papers'!F2:F1000, "*" & A13 & "*") -> 7 | D13: =IFERROR(__xludf.DUMMYFUNCTION("""COMPUTED_VALUE"""),"3-4- Cryptography & Integrity") -> 3-4- Cryptography & Integrity | E13: =COUNTIF('Final set of papers'!G14:G1000, "*" & D13 & "*") -> 9 | G13: =IFERROR(__xludf.DUMMYFUNCTION("""COMPUTED_VALUE"""),"Pattern Matching") -> Pattern Matching | H13: =COUNTIF('Final set of papers'!K2:K1000, "*" & G13 & "*") -> 8 | J13: 3 - Formal Methods
A14: =IFERROR(__xludf.DUMMYFUNCTION("""COMPUTED_VALUE"""),"Pulumi") -> Pulumi | B14: =COUNTIF('Final set of papers'!F2:F1000, "*" & A14 & "*") -> 5 | D14: =IFERROR(__xludf.DUMMYFUNCTION("""COMPUTED_VALUE"""),"4- Operational Quality") -> 4- Operational Quality | E14: =COUNTIF('Final set of papers'!G2:G1000, "*" & D14 & "*") -> 24 | G14: =IFERROR(__xludf.DUMMYFUNCTION("""COMPUTED_VALUE"""),"Program Dependncy Graph - PDG") -> Program Dependncy Graph - PDG | H14: =COUNTIF('Final set of papers'!K2:K1000, "*" & G14 & "*") -> 4 | J14: SMT solvers | N14: 1- Structural Quality | O14: 19
A15: =IFERROR(__xludf.DUMMYFUNCTION("""COMPUTED_VALUE"""),"Docker-compose") -> Docker-compose | B15: =COUNTIF('Final set of papers'!F2:F1000, "*" & A15 & "*") -> 1 | D15: =IFERROR(__xludf.DUMMYFUNCTION("""COMPUTED_VALUE"""),"4-1- Idempotency & State management") -> 4-1- Idempotency & State management | E15: =COUNTIF('Final set of papers'!G16:G1000, "*" & D15 & "*") -> 8 | G15: =IFERROR(__xludf.DUMMYFUNCTION("""COMPUTED_VALUE"""),"RAG") -> RAG | H15: =COUNTIF('Final set of papers'!K16:K1000, "*" & G15 & "*") -> 1 | J15: 4 - Statistical and Learning-Based Methods | N15: 2- Syntactic & Linguistic Quality | O15: 19
A16: =IFERROR(__xludf.DUMMYFUNCTION("""COMPUTED_VALUE"""),"Docker") -> Docker | B16: =IFERROR(__xludf.DUMMYFUNCTION("COUNTIF(FLATTEN(ARRAYFORMULA(TRIM(SPLIT('Final set of papers'!F2:F1000, "","")))),A16)"),7.0) -> 7 | D16: =IFERROR(__xludf.DUMMYFUNCTION("""COMPUTED_VALUE"""),"4-2- Error Handling & Reliability") -> 4-2- Error Handling & Reliability | E16: =COUNTIF('Final set of papers'!G17:G1000, "*" & D16 & "*") -> 8 | G16: =IFERROR(__xludf.DUMMYFUNCTION("""COMPUTED_VALUE"""),"Regular Expressions - RegX") -> Regular Expressions - RegX | H16: =COUNTIF('Final set of papers'!K2:K1000, "*" & J2 & "*") -> 7 | J16: Machine Learning - ML | N16: 3- Security | O16: 33
A17: =IFERROR(__xludf.DUMMYFUNCTION("""COMPUTED_VALUE"""),"Helm") -> Helm | B17: =COUNTIF('Final set of papers'!F2:F1000, "*" & A17 & "*") -> 1 | D17: =IFERROR(__xludf.DUMMYFUNCTION("""COMPUTED_VALUE"""),"4-3- Dependecies & integration") -> 4-3- Dependecies & integration | E17: =COUNTIF('Final set of papers'!G18:G1000, "*" & D17 & "*") -> 8 | G17: =IFERROR(__xludf.DUMMYFUNCTION("""COMPUTED_VALUE"""),"Resource Graph - RG") -> Resource Graph - RG | H17: =COUNTIF('Final set of papers'!K2:K1000, "*" & G17 & "*") -> 5 | J17: Statistical Learners | N17: 4- Operational Quality | O17: 24
D18: =IFERROR(__xludf.DUMMYFUNCTION("""COMPUTED_VALUE"""),"5- Performance & Resource management") -> 5- Performance & Resource management | E18: =COUNTIF('Final set of papers'!G2:G1000, "*" & D18 & "*") -> 11 | G18: =IFERROR(__xludf.DUMMYFUNCTION("""COMPUTED_VALUE"""),"Rewriting / Refactoring") -> Rewriting / Refactoring | H18: =COUNTIF('Final set of papers'!K2:K1000, "*" & G18 & "*") -> 1 | J18: Deep Learning - DL | N18: 5- Performance & Resource management | O18: 11
D19: =IFERROR(__xludf.DUMMYFUNCTION("""COMPUTED_VALUE"""),"5-1- Resource Optimization") -> 5-1- Resource Optimization | E19: =COUNTIF('Final set of papers'!G20:G1000, "*" & D19 & "*") -> 5 | G19: =IFERROR(__xludf.DUMMYFUNCTION("""COMPUTED_VALUE"""),"Rule-based checks") -> Rule-based checks | H19: =COUNTIF('Final set of papers'!K2:K1000, "*" & G19 & "*") -> 6 | J19: LLMs | N19: 6- Maintability & Documentation | O19: 16
A20: =IFERROR(__xludf.DUMMYFUNCTION("UNIQUE(ARRAYFORMULA(TRIM(FLATTEN(SPLIT(TEXTJOIN("","", TRUE, 'Final set of papers'!H2:H1000), "","")))))"),"Implementation") -> Implementation | B20: =COUNTIF('Final set of papers'!H2:H1000, "*" & A20 & "*") -> 55 | D20: =IFERROR(__xludf.DUMMYFUNCTION("""COMPUTED_VALUE"""),"5-2- Scalability") -> 5-2- Scalability | E20: =COUNTIF('Final set of papers'!G21:G1000, "*" & D20 & "*") -> 1 | G20: =IFERROR(__xludf.DUMMYFUNCTION("""COMPUTED_VALUE"""),"SMT solvers") -> SMT solvers | H20: =COUNTIF('Final set of papers'!K21:K1000, "*" & G20 & "*") -> 4 | J20: RAG | N20: 7- Data & Variable management | O20: 16
A21: =IFERROR(__xludf.DUMMYFUNCTION("""COMPUTED_VALUE"""),"Design") -> Design | B21: =COUNTIF('Final set of papers'!H2:H1000, "*" & A21 & "*") -> 9 | D21: =IFERROR(__xludf.DUMMYFUNCTION("""COMPUTED_VALUE"""),"5-3- Lifecycle management") -> 5-3- Lifecycle management | E21: =COUNTIF('Final set of papers'!G22:G1000, "*" & D21 & "*") -> 4 | G21: =IFERROR(__xludf.DUMMYFUNCTION("""COMPUTED_VALUE"""),"Statistical Learners") -> Statistical Learners | H21: =COUNTIF('Final set of papers'!K2:K1000, "*" & G21 & "*") -> 4 | J21: NLP | N21: 8- Control Flow & Logic | O21: 11
A22: =IFERROR(__xludf.DUMMYFUNCTION("""COMPUTED_VALUE"""),"Runtime") -> Runtime | B22: =COUNTIF('Final set of papers'!H2:H1000, "*" & A22 & "*") -> 10 | D22: =IFERROR(__xludf.DUMMYFUNCTION("""COMPUTED_VALUE"""),"6- Maintability & Documentation") -> 6- Maintability & Documentation | E22: =COUNTIF('Final set of papers'!G2:G1000, "*" & D22 & "*") -> 16 | G22: =IFERROR(__xludf.DUMMYFUNCTION("""COMPUTED_VALUE"""),"Tests") -> Tests | H22: =COUNTIF('Final set of papers'!K23:K1000, "*" & G22 & "*") -> 5 | J22: 5 - Testing Methods | N22: 9- Domain Specific Issues | O22: 10
D23: =IFERROR(__xludf.DUMMYFUNCTION("""COMPUTED_VALUE"""),"6-1- Code Readability") -> 6-1- Code Readability | E23: =COUNTIF('Final set of papers'!G24:G1000, "*" & D23 & "*") -> 4 | G23: =IFERROR(__xludf.DUMMYFUNCTION("""COMPUTED_VALUE"""),"Visitor Pattern") -> Visitor Pattern | H23: =COUNTIF('Final set of papers'!K2:K1000, "*" & G23 & "*") -> 2 | J23: Tests
A24: =IFERROR(__xludf.DUMMYFUNCTION("UNIQUE(ARRAYFORMULA(TRIM(FLATTEN(SPLIT(TEXTJOIN("","", TRUE, 'Final set of papers'!I2:I1000), "","")))))"),"Script") -> Script | B24: =COUNTIF('Final set of papers'!I2:I1000, "*" & A24 & "*") -> 50 | D24: =IFERROR(__xludf.DUMMYFUNCTION("""COMPUTED_VALUE"""),"6-2- Version control & Compatibility") -> 6-2- Version control & Compatibility | E24: =COUNTIF('Final set of papers'!G25:G1000, "*" & D24 & "*") -> 3
A25: =IFERROR(__xludf.DUMMYFUNCTION("""COMPUTED_VALUE"""),"Module") -> Module | B25: =COUNTIF('Final set of papers'!I2:I1000, "*" & A25 & "*") -> 6 | D25: =IFERROR(__xludf.DUMMYFUNCTION("""COMPUTED_VALUE"""),"6-3- Code Reusability") -> 6-3- Code Reusability | E25: =COUNTIF('Final set of papers'!G26:G1000, "*" & D25 & "*") -> 1
A26: =IFERROR(__xludf.DUMMYFUNCTION("""COMPUTED_VALUE"""),"Project") -> Project | B26: =COUNTIF('Final set of papers'!I4:I1000, "*" & A26 & "*") -> 12 | D26: =IFERROR(__xludf.DUMMYFUNCTION("""COMPUTED_VALUE"""),"7- Data & Variable management") -> 7- Data & Variable management | E26: =COUNTIF('Final set of papers'!G2:G1000, "*" & D26 & "*") -> 16 | G26: =IFERROR(__xludf.DUMMYFUNCTION("SORT(UNIQUE(ARRAYFORMULA(TRIM(FLATTEN(SPLIT(TEXTJOIN("","", TRUE, #REF!), "",""))))))"),"#REF!") -> #REF! | H26: =COUNTIF(#REF!, "*" & G26 & "*") -> 1 | J26: =IFERROR(__xludf.DUMMYFUNCTION("SORT(UNIQUE(ARRAYFORMULA(TRIM(FLATTEN(SPLIT(TEXTJOIN("","", TRUE, 'Final set of papers'!L2:L1000), "",""))))))"),"1 - Rule-Based and Pattern-Matching Approaches") -> 1 - Rule-Based and Pattern-Matching Approaches | K26: =COUNTIF('Final set of papers'!L2:L1000, "*" & J26 & "*") -> 23 | N26: =IFERROR(__xludf.DUMMYFUNCTION("UNIQUE(ARRAYFORMULA(TRIM(FLATTEN(SPLIT(TEXTJOIN("","", TRUE, 'Final set of papers'!S2:S1000), "","")))))"),"Both") -> Both | O26: =COUNTIF('Final set of papers'!S2:S1000, "*" & N26 & "*") -> 34
D27: =IFERROR(__xludf.DUMMYFUNCTION("""COMPUTED_VALUE"""),"7-1- Configuration Data") -> 7-1- Configuration Data | E27: =COUNTIF('Final set of papers'!G28:G1000, "*" & D27 & "*") -> 2 | H27: =COUNTIF(#REF!, "*" & G27 & "*") -> 0 | J27: =IFERROR(__xludf.DUMMYFUNCTION("""COMPUTED_VALUE"""),"2 - Graph-Based Analyses") -> 2 - Graph-Based Analyses | K27: =COUNTIF('Final set of papers'!L2:L1000, "*" & J27 & "*") -> 19 | N27: =IFERROR(__xludf.DUMMYFUNCTION("""COMPUTED_VALUE"""),"Code access") -> Code access | O27: =COUNTIF('Final set of papers'!S2:S1000, "*" & N27 & "*") -> 8
D28: =IFERROR(__xludf.DUMMYFUNCTION("""COMPUTED_VALUE"""),"7-2- Vraibale management") -> 7-2- Vraibale management | E28: =COUNTIF('Final set of papers'!G29:G1000, "*" & D28 & "*") -> 2 | H28: =COUNTIF(#REF!, "*" & G28 & "*") -> 0 | J28: =IFERROR(__xludf.DUMMYFUNCTION("""COMPUTED_VALUE"""),"3 - Formal Methods") -> 3 - Formal Methods | K28: =COUNTIF('Final set of papers'!L2:L1000, "*" & J28 & "*") -> 5 | N28: =IFERROR(__xludf.DUMMYFUNCTION("""COMPUTED_VALUE"""),"Dataset") -> Dataset | O28: =COUNTIF('Final set of papers'!S2:S1000, "*" & N28 & "*") -> 9
D29: =IFERROR(__xludf.DUMMYFUNCTION("""COMPUTED_VALUE"""),"8- Control Flow & Logic") -> 8- Control Flow & Logic | E29: =COUNTIF('Final set of papers'!G2:G1000, "*" & D29 & "*") -> 11 | H29: =COUNTIF(#REF!, "*" & G29 & "*") -> 0 | J29: =IFERROR(__xludf.DUMMYFUNCTION("""COMPUTED_VALUE"""),"4 - Statistical and Learning-Based Methods") -> 4 - Statistical and Learning-Based Methods | K29: =COUNTIF('Final set of papers'!L2:L1000, "*" & J29 & "*") -> 19 | N29: =IFERROR(__xludf.DUMMYFUNCTION("""COMPUTED_VALUE"""),"Not available") -> Not available | O29: =COUNTIF('Final set of papers'!S2:S1000, "*" & N29 & "*") -> 14
A30: =IFERROR(__xludf.DUMMYFUNCTION("UNIQUE(ARRAYFORMULA(TRIM(FLATTEN(SPLIT(TEXTJOIN("","", TRUE, 'Final set of papers'!J2:J1000), "","")))))"),"Config management") -> Config management | B30: =COUNTIF('Final set of papers'!J2:J1000, "*" & A30 & "*") -> 30 | D30: =IFERROR(__xludf.DUMMYFUNCTION("""COMPUTED_VALUE"""),"8-1- Program Flow") -> 8-1- Program Flow | E30: =COUNTIF('Final set of papers'!G31:G1000, "*" & D30 & "*") -> 0 | H30: =COUNTIF(#REF!, "*" & G30 & "*") -> 0 | J30: =IFERROR(__xludf.DUMMYFUNCTION("""COMPUTED_VALUE"""),"5 - Testing & Excution based") -> 5 - Testing & Excution based | K30: =COUNTIF('Final set of papers'!L2:L1000, "*" & J30 & "*") -> 7
A31: =IFERROR(__xludf.DUMMYFUNCTION("""COMPUTED_VALUE"""),"Other") -> Other | B31: =COUNTIF('Final set of papers'!J2:J1000, "*" & A31 & "*") -> 7 | D31: =IFERROR(__xludf.DUMMYFUNCTION("""COMPUTED_VALUE"""),"8-2- Function & Method Logic") -> 8-2- Function & Method Logic | E31: =COUNTIF('Final set of papers'!G32:G1000, "*" & D31 & "*") -> 1 | H31: =COUNTIF(#REF!, "*" & G31 & "*") -> 0 | J31: =IFERROR(__xludf.DUMMYFUNCTION("""COMPUTED_VALUE"""),"6 - Other") -> 6 - Other | K31: =COUNTIF('Final set of papers'!L2:L1000, "*" & J31 & "*") -> 8
A32: =IFERROR(__xludf.DUMMYFUNCTION("""COMPUTED_VALUE"""),"Provisioning") -> Provisioning | B32: =COUNTIF('Final set of papers'!J2:J1000, "*" & A32 & "*") -> 16 | D32: =IFERROR(__xludf.DUMMYFUNCTION("""COMPUTED_VALUE"""),"9- Domain Specific Issues") -> 9- Domain Specific Issues | E32: =COUNTIF('Final set of papers'!G2:G1000, "*" & D32 & "*") -> 10 | J32: =IFERROR(__xludf.DUMMYFUNCTION("""COMPUTED_VALUE"""),"NA") -> NA | K32: =COUNTIF('Final set of papers'!L2:L1000, J32) -> 6 | N32: =IFERROR(__xludf.DUMMYFUNCTION("UNIQUE(ARRAYFORMULA(TRIM(FLATTEN(SPLIT(TEXTJOIN("","", TRUE, 'Final set of papers'!T2:T1000), "","")))))"),"Github") -> Github | O32: =COUNTIF('Final set of papers'!T2:T1000, "*" & N32 & "*") -> 27 | Q32: Github | R32: 27
A33: =IFERROR(__xludf.DUMMYFUNCTION("""COMPUTED_VALUE"""),"Orchestration") -> Orchestration | B33: =COUNTIF('Final set of papers'!J2:J1000, "*" & A33 & "*") -> 8 | D33: =IFERROR(__xludf.DUMMYFUNCTION("""COMPUTED_VALUE"""),"9-1- Container & Orchestration") -> 9-1- Container & Orchestration | E33: =COUNTIF('Final set of papers'!G34:G1000, "*" & D33 & "*") -> 2 | N33: =IFERROR(__xludf.DUMMYFUNCTION("""COMPUTED_VALUE"""),"Figshare") -> Figshare | O33: =COUNTIF('Final set of papers'!T2:T1000, "*" & N33 & "*") -> 18 | Q33: Figshare | R33: 18
A34: =IFERROR(__xludf.DUMMYFUNCTION("""COMPUTED_VALUE"""),"Image building") -> Image building | B34: =COUNTIF('Final set of papers'!J2:J1000, "*" & A34 & "*") -> 7 | D34: =IFERROR(__xludf.DUMMYFUNCTION("""COMPUTED_VALUE"""),"9-2- Cloud Provider Specfic") -> 9-2- Cloud Provider Specfic | E34: =COUNTIF('Final set of papers'!G35:G1000, "*" & D34 & "*") -> 1 | N34: =IFERROR(__xludf.DUMMYFUNCTION("""COMPUTED_VALUE"""),"Docker hub") -> Docker hub | O34: =COUNTIF('Final set of papers'!T2:T1000, "*" & N34 & "*") -> 2 | Q34: Docker hub | R34: 2
D35: =IFERROR(__xludf.DUMMYFUNCTION("""COMPUTED_VALUE"""),"9-3- Infra components") -> 9-3- Infra components | E35: =COUNTIF('Final set of papers'!G36:G1000, "*" & D35 & "*") -> 2 | N35: =IFERROR(__xludf.DUMMYFUNCTION("""COMPUTED_VALUE"""),"NA") -> NA | O35: =COUNTIF('Final set of papers'!T5:T1000, "*" & N35 & "*") -> 14 | Q35: Zenodo | R35: 12
D36: =IFERROR(__xludf.DUMMYFUNCTION("""COMPUTED_VALUE"""),"NA") -> NA | E36: =COUNTIF('Final set of papers'!G37:G1000,D36) -> 1 | N36: =IFERROR(__xludf.DUMMYFUNCTION("""COMPUTED_VALUE"""),"Zenodo") -> Zenodo | O36: =COUNTIF('Final set of papers'!T2:T1000, "*" & N36 & "*") -> 12 | Q36: Kaggle | R36: 1
N37: =IFERROR(__xludf.DUMMYFUNCTION("""COMPUTED_VALUE"""),"Kaggle") -> Kaggle | O37: =COUNTIF('Final set of papers'!T2:T1000, "*" & N37 & "*") -> 1
A38: =IFERROR(__xludf.DUMMYFUNCTION("UNIQUE(ARRAYFORMULA(TRIM(FLATTEN(SPLIT(TEXTJOIN("","", TRUE, 'Final set of papers'!N2:N1000), "","")))))"),"Yes") -> Yes | B38: =COUNTIF('Final set of papers'!N2:N1000, "*" & A38 & "*") -> 57
A39: =IFERROR(__xludf.DUMMYFUNCTION("""COMPUTED_VALUE"""),"No") -> No | B39: =COUNTIF('Final set of papers'!N2:N1000, "*" & A39 & "*") -> 8 | G39: =IFERROR(__xludf.DUMMYFUNCTION("SORT(UNIQUE(ARRAYFORMULA(TRIM(FLATTEN(SPLIT(TEXTJOIN("","", TRUE, 'Final set of papers'!M2:M1000), "",""))))))"),"Dynamic") -> Dynamic | H39: =COUNTIF('Final set of papers'!M2:M1000, "*" & G39 & "*") -> 6
G40: =IFERROR(__xludf.DUMMYFUNCTION("""COMPUTED_VALUE"""),"Hybrid") -> Hybrid | H40: =COUNTIF('Final set of papers'!M3:M1000, "*" & G40 & "*") -> 4
A41: =IFERROR(__xludf.DUMMYFUNCTION("UNIQUE(ARRAYFORMULA(TRIM(FLATTEN(SPLIT(TEXTJOIN("","", TRUE, 'Final set of papers'!R2:R1000), "","")))))"),"WhiteBox") -> WhiteBox | B41: =COUNTIF('Final set of papers'!R2:R1000, "*" & A41 & "*") -> 56 | G41: =IFERROR(__xludf.DUMMYFUNCTION("""COMPUTED_VALUE"""),"NA") -> NA | H41: =COUNTIF('Final set of papers'!M4:M1000, "*" & G41 & "*") -> 14
A42: =IFERROR(__xludf.DUMMYFUNCTION("""COMPUTED_VALUE"""),"NA") -> NA | B42: =COUNTIF('Final set of papers'!R3:R1000, A42) -> 8 | G42: =IFERROR(__xludf.DUMMYFUNCTION("""COMPUTED_VALUE"""),"Static") -> Static | H42: =COUNTIF('Final set of papers'!M2:M1000, "*" & G42 & "*") -> 47
A43: =IFERROR(__xludf.DUMMYFUNCTION("""COMPUTED_VALUE"""),"BlackBox") -> BlackBox | B43: =COUNTIF('Final set of papers'!R4:R1000, "*" & A43 & "*") -> 1

Sheet IaC_issues_across_platforms
A1: Column 1 | B1: 1- Structural Quality | C1: 2- Syntactic & Linguistic Quality | D1: 3- Security | E1: 4- Operational Quality | F1: 5- Performance & Resource management | G1: 6- Maintability & Documentation | H1: 7- Data & Variable management | I1: 8- Control Flow & Logic | J1: 9- Domain Specific Issues
A2: =IFERROR(__xludf.DUMMYFUNCTION("UNIQUE(ARRAYFORMULA(TRIM(FLATTEN(SPLIT(TEXTJOIN("","", TRUE, 'Final set of papers'!F2:F1000), "","")))))"),"Puppet") -> Puppet | B2: =COUNTIFS( 'Final set of papers'!$F$2:$F1000, "*"&A2&"*", 'Final set of papers'!$G$2:$G1000, "*"&Table1[[#HEADERS],[1- Structural Quality]]&"*" ) -> 4 | C2: =COUNTIFS( 'Final set of papers'!$F$2:$F1000, "*"&A2&"*", 'Final set of papers'!$G$2:$G1000, "*"&Table1[[#HEADERS],[2- Syntactic & Linguistic Quality]]&"*" ) -> 3 | D2: =COUNTIFS( 'Final set of papers'!$F$2:$F1000, "*"&A2&"*", 'Final set of papers'!$G$2:$G1000, "*"&Table1[[#HEADERS],[3- Security]]&"*" ) -> 5 | E2: =COUNTIFS( 'Final set of papers'!$F$2:$F1000, "*"&A2&"*", 'Final set of papers'!$G$2:$G1000, "*"&Table1[[#HEADERS],[4- Operational Quality]]&"*" ) -> 3 | F2: =COUNTIFS( 'Final set of papers'!$F$2:$F1000, "*"&A2&"*", 'Final set of papers'!$G$2:$G1000, "*"&Table1[[#HEADERS],[5- Performance & Resource management]]&"*" ) -> 0 | G2: =COUNTIFS( 'Final set of papers'!$F$2:$F1000, "*"&A2&"*", 'Final set of papers'!$G$2:$G1000, "*"&Table1[[#HEADERS],[6- Maintability & Documentation]]&"*" ) -> 4 | H2: =COUNTIFS( 'Final set of papers'!$F$2:$F1000, "*"&A2&"*", 'Final set of papers'!$G$2:$G1000, "*"&Table1[[#HEADERS],[7- Data & Variable management]]&"*" ) -> 2 | I2: =COUNTIFS( 'Final set of papers'!$F$2:$F1000, "*"&A2&"*", 'Final set of papers'!$G$2:$G1000, "*"&Table1[[#HEADERS],[8- Control Flow & Logic]]&"*" ) -> 2 | J2: =COUNTIFS( 'Final set of papers'!$F$2:$F1000, "*"&A2&"*", 'Final set of papers'!$G$2:$G1000, "*"&Table1[[#HEADERS],[9- Domain Specific Issues]]&"*" ) -> 1
A3: =IFERROR(__xludf.DUMMYFUNCTION("""COMPUTED_VALUE"""),"Ansible") -> Ansible | B3: =COUNTIFS( 'Final set of papers'!$F$2:$F1000, "*"&A3&"*", 'Final set of papers'!$G$2:$G1000, "*"&Table1[[#HEADERS],[1- Structural Quality]]&"*" ) -> 6 | C3: =COUNTIFS( 'Final set of papers'!$F$2:$F1000, "*"&A3&"*", 'Final set of papers'!$G$2:$G1000, "*"&Table1[[#HEADERS],[2- Syntactic & Linguistic Quality]]&"*" ) -> 9 | D3: =COUNTIFS( 'Final set of papers'!$F$2:$F1000, "*"&A3&"*", 'Final set of papers'!$G$2:$G1000, "*"&Table1[[#HEADERS],[3- Security]]&"*" ) -> 9 | E3: =COUNTIFS( 'Final set of papers'!$F$2:$F1000, "*"&A3&"*", 'Final set of papers'!$G$2:$G1000, "*"&Table1[[#HEADERS],[4- Operational Quality]]&"*" ) -> 6 | F3: =COUNTIFS( 'Final set of papers'!$F$2:$F1000, "*"&A3&"*", 'Final set of papers'!$G$2:$G1000, "*"&Table1[[#HEADERS],[5- Performance & Resource management]]&"*" ) -> 1 | G3: =COUNTIFS( 'Final set of papers'!$F$2:$F1000, "*"&A3&"*", 'Final set of papers'!$G$2:$G1000, "*"&Table1[[#HEADERS],[6- Maintability & Documentation]]&"*" ) -> 6 | H3: =COUNTIFS( 'Final set of papers'!$F$2:$F1000, "*"&A3&"*", 'Final set of papers'!$G$2:$G1000, "*"&Table1[[#HEADERS],[7- Data & Variable management]]&"*" ) -> 6 | I3: =COUNTIFS( 'Final set of papers'!$F$2:$F1000, "*"&A3&"*", 'Final set of papers'!$G$2:$G1000, "*"&Table1[[#HEADERS],[8- Control Flow & Logic]]&"*" ) -> 4 | J3: =COUNTIFS( 'Final set of papers'!$F$2:$F1000, "*"&A3&"*", 'Final set of papers'!$G$2:$G1000, "*"&Table1[[#HEADERS],[9- Domain Specific Issues]]&"*" ) -> 3
A4: =IFERROR(__xludf.DUMMYFUNCTION("""COMPUTED_VALUE"""),"Multi (for TA)") -> Multi (for TA) | B4: =COUNTIFS( 'Final set of papers'!$F$2:$F1000, "*"&A4&"*", 'Final set of papers'!$G$2:$G1000, "*"&Table1[[#HEADERS],[1- Structural Quality]]&"*" ) -> 2 | C4: =COUNTIFS( 'Final set of papers'!$F$2:$F1000, "*"&A4&"*", 'Final set of papers'!$G$2:$G1000, "*"&Table1[[#HEADERS],[2- Syntactic & Linguistic Quality]]&"*" ) -> 2 | D4: =COUNTIFS( 'Final set of papers'!$F$2:$F1000, "*"&A4&"*", 'Final set of papers'!$G$2:$G1000, "*"&Table1[[#HEADERS],[3- Security]]&"*" ) -> 5 | E4: =COUNTIFS( 'Final set of papers'!$F$2:$F1000, "*"&A4&"*", 'Final set of papers'!$G$2:$G1000, "*"&Table1[[#HEADERS],[4- Operational Quality]]&"*" ) -> 2 | F4: =COUNTIFS( 'Final set of papers'!$F$2:$F1000, "*"&A4&"*", 'Final set of papers'!$G$2:$G1000, "*"&Table1[[#HEADERS],[5- Performance & Resource management]]&"*" ) -> 2 | G4: =COUNTIFS( 'Final set of papers'!$F$2:$F1000, "*"&A4&"*", 'Final set of papers'!$G$2:$G1000, "*"&Table1[[#HEADERS],[6- Maintability & Documentation]]&"*" ) -> 1 | H4: =COUNTIFS( 'Final set of papers'!$F$2:$F1000, "*"&A4&"*", 'Final set of papers'!$G$2:$G1000, "*"&Table1[[#HEADERS],[7- Data & Variable management]]&"*" ) -> 4 | I4: =COUNTIFS( 'Final set of papers'!$F$2:$F1000, "*"&A4&"*", 'Final set of papers'!$G$2:$G1000, "*"&Table1[[#HEADERS],[8- Control Flow & Logic]]&"*" ) -> 3 | J4: =COUNTIFS( 'Final set of papers'!$F$2:$F1000, "*"&A4&"*", 'Final set of papers'!$G$2:$G1000, "*"&Table1[[#HEADERS],[9- Domain Specific Issues]]&"*" ) -> 1
A5: =IFERROR(__xludf.DUMMYFUNCTION("""COMPUTED_VALUE"""),"Terraform") -> Terraform | B5: =COUNTIFS( 'Final set of papers'!$F$2:$F1000, "*"&A5&"*", 'Final set of papers'!$G$2:$G1000, "*"&Table1[[#HEADERS],[1- Structural Quality]]&"*" ) -> 4 | C5: =COUNTIFS( 'Final set of papers'!$F$2:$F1000, "*"&A5&"*", 'Final set of papers'!$G$2:$G1000, "*"&Table1[[#HEADERS],[2- Syntactic & Linguistic Quality]]&"*" ) -> 1 | D5: =COUNTIFS( 'Final set of papers'!$F$2:$F1000, "*"&A5&"*", 'Final set of papers'!$G$2:$G1000, "*"&Table1[[#HEADERS],[3- Security]]&"*" ) -> 3 | E5: =COUNTIFS( 'Final set of papers'!$F$2:$F1000, "*"&A5&"*", 'Final set of papers'!$G$2:$G1000, "*"&Table1[[#HEADERS],[4- Operational Quality]]&"*" ) -> 4 | F5: =COUNTIFS( 'Final set of papers'!$F$2:$F1000, "*"&A5&"*", 'Final set of papers'!$G$2:$G1000, "*"&Table1[[#HEADERS],[5- Performance & Resource management]]&"*" ) -> 2 | G5: =COUNTIFS( 'Final set of papers'!$F$2:$F1000, "*"&A5&"*", 'Final set of papers'!$G$2:$G1000, "*"&Table1[[#HEADERS],[6- Maintability & Documentation]]&"*" ) -> 2 | H5: =COUNTIFS( 'Final set of papers'!$F$2:$F1000, "*"&A5&"*", 'Final set of papers'!$G$2:$G1000, "*"&Table1[[#HEADERS],[7- Data & Variable management]]&"*" ) -> 1 | I5: =COUNTIFS( 'Final set of papers'!$F$2:$F1000, "*"&A5&"*", 'Final set of papers'!$G$2:$G1000, "*"&Table1[[#HEADERS],[8- Control Flow & Logic]]&"*" ) -> 1 | J5: =COUNTIFS( 'Final set of papers'!$F$2:$F1000, "*"&A5&"*", 'Final set of papers'!$G$2:$G1000, "*"&Table1[[#HEADERS],[9- Domain Specific Issues]]&"*" ) -> 2
A6: =IFERROR(__xludf.DUMMYFUNCTION("""COMPUTED_VALUE"""),"Chef") -> Chef | B6: =COUNTIFS( 'Final set of papers'!$F$2:$F1000, "*"&A6&"*", 'Final set of papers'!$G$2:$G1000, "*"&Table1[[#HEADERS],[1- Structural Quality]]&"*" ) -> 1 | C6: =COUNTIFS( 'Final set of papers'!$F$2:$F1000, "*"&A6&"*", 'Final set of papers'!$G$2:$G1000, "*"&Table1[[#HEADERS],[2- Syntactic & Linguistic Quality]]&"*" ) -> 2 | D6: =COUNTIFS( 'Final set of papers'!$F$2:$F1000, "*"&A6&"*", 'Final set of papers'!$G$2:$G1000, "*"&Table1[[#HEADERS],[3- Security]]&"*" ) -> 1 | E6: =COUNTIFS( 'Final set of papers'!$F$2:$F1000, "*"&A6&"*", 'Final set of papers'!$G$2:$G1000, "*"&Table1[[#HEADERS],[4- Operational Quality]]&"*" ) -> 0 | F6: =COUNTIFS( 'Final set of papers'!$F$2:$F1000, "*"&A6&"*", 'Final set of papers'!$G$2:$G1000, "*"&Table1[[#HEADERS],[5- Performance & Resource management]]&"*" ) -> 0 | G6: =COUNTIFS( 'Final set of papers'!$F$2:$F1000, "*"&A6&"*", 'Final set of papers'!$G$2:$G1000, "*"&Table1[[#HEADERS],[6- Maintability & Documentation]]&"*" ) -> 1 | H6: =COUNTIFS( 'Final set of papers'!$F$2:$F1000, "*"&A6&"*", 'Final set of papers'!$G$2:$G1000, "*"&Table1[[#HEADERS],[7- Data & Variable management]]&"*" ) -> 0 | I6: =COUNTIFS( 'Final set of papers'!$F$2:$F1000, "*"&A6&"*", 'Final set of papers'!$G$2:$G1000, "*"&Table1[[#HEADERS],[8- Control Flow & Logic]]&"*" ) -> 0 | J6: =COUNTIFS( 'Final set of papers'!$F$2:$F1000, "*"&A6&"*", 'Final set of papers'!$G$2:$G1000, "*"&Table1[[#HEADERS],[9- Domain Specific Issues]]&"*" ) -> 0
A7: =IFERROR(__xludf.DUMMYFUNCTION("""COMPUTED_VALUE"""),"TOSCA") -> TOSCA | B7: =COUNTIFS( 'Final set of papers'!$F$2:$F1000, "*"&A7&"*", 'Final set of papers'!$G$2:$G1000, "*"&Table1[[#HEADERS],[1- Structural Quality]]&"*" ) -> 1 | C7: =COUNTIFS( 'Final set of papers'!$F$2:$F1000, "*"&A7&"*", 'Final set of papers'!$G$2:$G1000, "*"&Table1[[#HEADERS],[2- Syntactic & Linguistic Quality]]&"*" ) -> 0 | D7: =COUNTIFS( 'Final set of papers'!$F$2:$F1000, "*"&A7&"*", 'Final set of papers'!$G$2:$G1000, "*"&Table1[[#HEADERS],[3- Security]]&"*" ) -> 1 | E7: =COUNTIFS( 'Final set of papers'!$F$2:$F1000, "*"&A7&"*", 'Final set of papers'!$G$2:$G1000, "*"&Table1[[#HEADERS],[4- Operational Quality]]&"*" ) -> 1 | F7: =COUNTIFS( 'Final set of papers'!$F$2:$F1000, "*"&A7&"*", 'Final set of papers'!$G$2:$G1000, "*"&Table1[[#HEADERS],[5- Performance & Resource management]]&"*" ) -> 0 | G7: =COUNTIFS( 'Final set of papers'!$F$2:$F1000, "*"&A7&"*", 'Final set of papers'!$G$2:$G1000, "*"&Table1[[#HEADERS],[6- Maintability & Documentation]]&"*" ) -> 1 | H7: =COUNTIFS( 'Final set of papers'!$F$2:$F1000, "*"&A7&"*", 'Final set of papers'!$G$2:$G1000, "*"&Table1[[#HEADERS],[7- Data & Variable management]]&"*" ) -> 1 | I7: =COUNTIFS( 'Final set of papers'!$F$2:$F1000, "*"&A7&"*", 'Final set of papers'!$G$2:$G1000, "*"&Table1[[#HEADERS],[8- Control Flow & Logic]]&"*" ) -> 1 | J7: =COUNTIFS( 'Final set of papers'!$F$2:$F1000, "*"&A7&"*", 'Final set of papers'!$G$2:$G1000, "*"&Table1[[#HEADERS],[9- Domain Specific Issues]]&"*" ) -> 1
A8: =IFERROR(__xludf.DUMMYFUNCTION("""COMPUTED_VALUE"""),"Cloud Formation") -> Cloud Formation | B8: =COUNTIFS( 'Final set of papers'!$F$2:$F1000, "*"&A8&"*", 'Final set of papers'!$G$2:$G1000, "*"&Table1[[#HEADERS],[1- Structural Quality]]&"*" ) -> 0 | C8: =COUNTIFS( 'Final set of papers'!$F$2:$F1000, "*"&A8&"*", 'Final set of papers'!$G$2:$G1000, "*"&Table1[[#HEADERS],[2- Syntactic & Linguistic Quality]]&"*" ) -> 0 | D8: =COUNTIFS( 'Final set of papers'!$F$2:$F1000, "*"&A8&"*", 'Final set of papers'!$G$2:$G1000, "*"&Table1[[#HEADERS],[3- Security]]&"*" ) -> 1 | E8: =COUNTIFS( 'Final set of papers'!$F$2:$F1000, "*"&A8&"*", 'Final set of papers'!$G$2:$G1000, "*"&Table1[[#HEADERS],[4- Operational Quality]]&"*" ) -> 0 | F8: =COUNTIFS( 'Final set of papers'!$F$2:$F1000, "*"&A8&"*", 'Final set of papers'!$G$2:$G1000, "*"&Table1[[#HEADERS],[5- Performance & Resource management]]&"*" ) -> 2 | G8: =COUNTIFS( 'Final set of papers'!$F$2:$F1000, "*"&A8&"*", 'Final set of papers'!$G$2:$G1000, "*"&Table1[[#HEADERS],[6- Maintability & Documentation]]&"*" ) -> 0 | H8: =COUNTIFS( 'Final set of papers'!$F$2:$F1000, "*"&A8&"*", 'Final set of papers'!$G$2:$G1000, "*"&Table1[[#HEADERS],[7- Data & Variable management]]&"*" ) -> 0 | I8: =COUNTIFS( 'Final set of papers'!$F$2:$F1000, "*"&A8&"*", 'Final set of papers'!$G$2:$G1000, "*"&Table1[[#HEADERS],[8- Control Flow & Logic]]&"*" ) -> 0 | J8: =COUNTIFS( 'Final set of papers'!$F$2:$F1000, "*"&A8&"*", 'Final set of papers'!$G$2:$G1000, "*"&Table1[[#HEADERS],[9- Domain Specific Issues]]&"*" ) -> 1
A9: =IFERROR(__xludf.DUMMYFUNCTION("""COMPUTED_VALUE"""),"Kubernetes") -> Kubernetes | B9: =COUNTIFS( 'Final set of papers'!$F$2:$F1000, "*"&A9&"*", 'Final set of papers'!$G$2:$G1000, "*"&Table1[[#HEADERS],[1- Structural Quality]]&"*" ) -> 1 | C9: =COUNTIFS( 'Final set of papers'!$F$2:$F1000, "*"&A9&"*", 'Final set of papers'!$G$2:$G1000, "*"&Table1[[#HEADERS],[2- Syntactic & Linguistic Quality]]&"*" ) -> 0 | D9: =COUNTIFS( 'Final set of papers'!$F$2:$F1000, "*"&A9&"*", 'Final set of papers'!$G$2:$G1000, "*"&Table1[[#HEADERS],[3- Security]]&"*" ) -> 5 | E9: =COUNTIFS( 'Final set of papers'!$F$2:$F1000, "*"&A9&"*", 'Final set of papers'!$G$2:$G1000, "*"&Table1[[#HEADERS],[4- Operational Quality]]&"*" ) -> 1 | F9: =COUNTIFS( 'Final set of papers'!$F$2:$F1000, "*"&A9&"*", 'Final set of papers'!$G$2:$G1000, "*"&Table1[[#HEADERS],[5- Performance & Resource management]]&"*" ) -> 1 | G9: =COUNTIFS( 'Final set of papers'!$F$2:$F1000, "*"&A9&"*", 'Final set of papers'!$G$2:$G1000, "*"&Table1[[#HEADERS],[6- Maintability & Documentation]]&"*" ) -> 0 | H9: =COUNTIFS( 'Final set of papers'!$F$2:$F1000, "*"&A9&"*", 'Final set of papers'!$G$2:$G1000, "*"&Table1[[#HEADERS],[7- Data & Variable management]]&"*" ) -> 0 | I9: =COUNTIFS( 'Final set of papers'!$F$2:$F1000, "*"&A9&"*", 'Final set of papers'!$G$2:$G1000, "*"&Table1[[#HEADERS],[8- Control Flow & Logic]]&"*" ) -> 0 | J9: =COUNTIFS( 'Final set of papers'!$F$2:$F1000, "*"&A9&"*", 'Final set of papers'!$G$2:$G1000, "*"&Table1[[#HEADERS],[9- Domain Specific Issues]]&"*" ) -> 1
A10: =IFERROR(__xludf.DUMMYFUNCTION("""COMPUTED_VALUE"""),"Pulumi") -> Pulumi | B10: =COUNTIFS( 'Final set of papers'!$F$2:$F1000, "*"&A10&"*", 'Final set of papers'!$G$2:$G1000, "*"&Table1[[#HEADERS],[1- Structural Quality]]&"*" ) -> 0 | C10: =COUNTIFS( 'Final set of papers'!$F$2:$F1000, "*"&A10&"*", 'Final set of papers'!$G$2:$G1000, "*"&Table1[[#HEADERS],[2- Syntactic & Linguistic Quality]]&"*" ) -> 1 | D10: =COUNTIFS( 'Final set of papers'!$F$2:$F1000, "*"&A10&"*", 'Final set of papers'!$G$2:$G1000, "*"&Table1[[#HEADERS],[3- Security]]&"*" ) -> 2 | E10: =COUNTIFS( 'Final set of papers'!$F$2:$F1000, "*"&A10&"*", 'Final set of papers'!$G$2:$G1000, "*"&Table1[[#HEADERS],[4- Operational Quality]]&"*" ) -> 4 | F10: =COUNTIFS( 'Final set of papers'!$F$2:$F1000, "*"&A10&"*", 'Final set of papers'!$G$2:$G1000, "*"&Table1[[#HEADERS],[5- Performance & Resource management]]&"*" ) -> 0 | G10: =COUNTIFS( 'Final set of papers'!$F$2:$F1000, "*"&A10&"*", 'Final set of papers'!$G$2:$G1000, "*"&Table1[[#HEADERS],[6- Maintability & Documentation]]&"*" ) -> 0 | H10: =COUNTIFS( 'Final set of papers'!$F$2:$F1000, "*"&A10&"*", 'Final set of papers'!$G$2:$G1000, "*"&Table1[[#HEADERS],[7- Data & Variable management]]&"*" ) -> 1 | I10: =COUNTIFS( 'Final set of papers'!$F$2:$F1000, "*"&A10&"*", 'Final set of papers'!$G$2:$G1000, "*"&Table1[[#HEADERS],[8- Control Flow & Logic]]&"*" ) -> 0 | J10: =COUNTIFS( 'Final set of papers'!$F$2:$F1000, "*"&A10&"*", 'Final set of papers'!$G$2:$G1000, "*"&Table1[[#HEADERS],[9- Domain Specific Issues]]&"*" ) -> 0
A11: =IFERROR(__xludf.DUMMYFUNCTION("""COMPUTED_VALUE"""),"Docker-compose") -> Docker-compose | B11: =COUNTIFS( 'Final set of papers'!$F$2:$F1000, "*"&A11&"*", 'Final set of papers'!$G$2:$G1000, "*"&Table1[[#HEADERS],[1- Structural Quality]]&"*" ) -> 1 | C11: =COUNTIFS( 'Final set of papers'!$F$2:$F1000, "*"&A11&"*", 'Final set of papers'!$G$2:$G1000, "*"&Table1[[#HEADERS],[2- Syntactic & Linguistic Quality]]&"*" ) -> 0 | D11: =COUNTIFS( 'Final set of papers'!$F$2:$F1000, "*"&A11&"*", 'Final set of papers'!$G$2:$G1000, "*"&Table1[[#HEADERS],[3- Security]]&"*" ) -> 1 | E11: =COUNTIFS( 'Final set of papers'!$F$2:$F1000, "*"&A11&"*", 'Final set of papers'!$G$2:$G1000, "*"&Table1[[#HEADERS],[4- Operational Quality]]&"*" ) -> 1 | F11: =COUNTIFS( 'Final set of papers'!$F$2:$F1000, "*"&A11&"*", 'Final set of papers'!$G$2:$G1000, "*"&Table1[[#HEADERS],[5- Performance & Resource management]]&"*" ) -> 1 | G11: =COUNTIFS( 'Final set of papers'!$F$2:$F1000, "*"&A11&"*", 'Final set of papers'!$G$2:$G1000, "*"&Table1[[#HEADERS],[6- Maintability & Documentation]]&"*" ) -> 1 | H11: =COUNTIFS( 'Final set of papers'!$F$2:$F1000, "*"&A11&"*", 'Final set of papers'!$G$2:$G1000, "*"&Table1[[#HEADERS],[7- Data & Variable management]]&"*" ) -> 0 | I11: =COUNTIFS( 'Final set of papers'!$F$2:$F1000, "*"&A11&"*", 'Final set of papers'!$G$2:$G1000, "*"&Table1[[#HEADERS],[8- Control Flow & Logic]]&"*" ) -> 0 | J11: =COUNTIFS( 'Final set of papers'!$F$2:$F1000, "*"&A11&"*", 'Final set of papers'!$G$2:$G1000, "*"&Table1[[#HEADERS],[9- Domain Specific Issues]]&"*" ) -> 1
A12: =IFERROR(__xludf.DUMMYFUNCTION("""COMPUTED_VALUE"""),"Docker") -> Docker | B12: =IFERROR(__xludf.DUMMYFUNCTION("COUNTIF( FLATTEN( ARRAYFORMULA( TRIM( SPLIT( FILTER( 'Final set of papers'!$F$2:$F1000, REGEXMATCH('Final set of papers'!$G$2:$G1000, "".*""&Table1[[#HEADERS],[1- Structural "&"Quality]]&"".*"") ), "","" ) ) ) ), A12 )"),2.0) -> 2 | C12: =IFERROR(__xludf.DUMMYFUNCTION("COUNTIF( FLATTEN( ARRAYFORMULA( TRIM( SPLIT( FILTER( 'Final set of papers'!$F$2:$F1000, REGEXMATCH('Final set of papers'!$G$2:$G1000, "".*""&Table1[[#HEADERS],[2- Syntactic &"&" Linguistic Quality]]&"".*"") ), "","" ) ) ) ), A12 )"),3.0) -> 3 | D12: =IFERROR(__xludf.DUMMYFUNCTION("COUNTIF( FLATTEN( ARRAYFORMULA( TRIM( SPLIT( FILTER( 'Final set of papers'!$F$2:$F1000, REGEXMATCH('Final set of papers'!$G$2:$G1000, "".*""&Table1[[#HEADERS],[3- Security]]&"&""".*"") ), "","" ) ) ) ), A12 )"),3.0) -> 3 | E12: =IFERROR(__xludf.DUMMYFUNCTION("COUNTIF( FLATTEN( ARRAYFORMULA( TRIM( SPLIT( FILTER( 'Final set of papers'!$F$2:$F1000, REGEXMATCH('Final set of papers'!$G$2:$G1000, "".*""&Table1[[#HEADERS],[4- Operational"&" Quality]]&"".*"") ), "","" ) ) ) ), A12 )"),3.0) -> 3 | F12: =IFERROR(__xludf.DUMMYFUNCTION("COUNTIF( FLATTEN( ARRAYFORMULA( TRIM( SPLIT( FILTER( 'Final set of papers'!$F$2:$F1000, REGEXMATCH('Final set of papers'!$G$2:$G1000, "".*""&Table1[[#HEADERS],[5- Performance"&" & Resource management]]&"".*"") ), "","" ) ) ) ), A12 )"),3.0) -> 3 | G12: =IFERROR(__xludf.DUMMYFUNCTION("COUNTIF( FLATTEN( ARRAYFORMULA( TRIM( SPLIT( FILTER( 'Final set of papers'!$F$2:$F1000, REGEXMATCH('Final set of papers'!$G$2:$G1000, "".*""&Table1[[#HEADERS],[6- Maintabilit"&"y & Documentation]]&"".*"") ), "","" ) ) ) ), A12 )"),2.0) -> 2 | H12: =IFERROR(__xludf.DUMMYFUNCTION("COUNTIF( FLATTEN( ARRAYFORMULA( TRIM( SPLIT( FILTER( 'Final set of papers'!$F$2:$F1000, REGEXMATCH('Final set of papers'!$G$2:$G1000, "".*""&Table1[[#HEADERS],[7- Data & Vari"&"able management]]&"".*"") ), "","" ) ) ) ), A12 )"),2.0) -> 2 | I12: =IFERROR(__xludf.DUMMYFUNCTION("COUNTIF( FLATTEN( ARRAYFORMULA( TRIM( SPLIT( FILTER( 'Final set of papers'!$F$2:$F1000, REGEXMATCH('Final set of papers'!$G$2:$G1000, "".*""&Table1[[#HEADERS],[8- Control Flo"&"w & Logic]]&"".*"") ), "","" ) ) ) ), A12 )"),1.0) -> 1 | J12: =IFERROR(__xludf.DUMMYFUNCTION("COUNTIF( FLATTEN( ARRAYFORMULA( TRIM( SPLIT( FILTER( 'Final set of papers'!$F$2:$F1000, REGEXMATCH('Final set of papers'!$G$2:$G1000, "".*""&Table1[[#HEADERS],[9- Domain Spec"&"ific Issues]]&"".*"") ), "","" ) ) ) ), A12 )"),1.0) -> 1
A13: =IFERROR(__xludf.DUMMYFUNCTION("""COMPUTED_VALUE"""),"Helm") -> Helm | B13: =COUNTIFS( 'Final set of papers'!$F$2:$F1000, "*"&A13&"*", 'Final set of papers'!$G$2:$G1000, "*"&Table1[[#HEADERS],[1- Structural Quality]]&"*" ) -> 1 | C13: =COUNTIFS( 'Final set of papers'!$F$2:$F1000, "*"&A13&"*", 'Final set of papers'!$G$2:$G1000, "*"&Table1[[#HEADERS],[2- Syntactic & Linguistic Quality]]&"*" ) -> 0 | D13: =COUNTIFS( 'Final set of papers'!$F$2:$F1000, "*"&A13&"*", 'Final set of papers'!$G$2:$G1000, "*"&Table1[[#HEADERS],[3- Security]]&"*" ) -> 0 | E13: =COUNTIFS( 'Final set of papers'!$F$2:$F1000, "*"&A13&"*", 'Final set of papers'!$G$2:$G1000, "*"&Table1[[#HEADERS],[4- Operational Quality]]&"*" ) -> 0 | F13: =COUNTIFS( 'Final set of papers'!$F$2:$F1000, "*"&A13&"*", 'Final set of papers'!$G$2:$G1000, "*"&Table1[[#HEADERS],[5- Performance & Resource management]]&"*" ) -> 0 | G13: =COUNTIFS( 'Final set of papers'!$F$2:$F1000, "*"&A13&"*", 'Final set of papers'!$G$2:$G1000, "*"&Table1[[#HEADERS],[6- Maintability & Documentation]]&"*" ) -> 0 | H13: =COUNTIFS( 'Final set of papers'!$F$2:$F1000, "*"&A13&"*", 'Final set of papers'!$G$2:$G1000, "*"&Table1[[#HEADERS],[7- Data & Variable management]]&"*" ) -> 0 | I13: =COUNTIFS( 'Final set of papers'!$F$2:$F1000, "*"&A13&"*", 'Final set of papers'!$G$2:$G1000, "*"&Table1[[#HEADERS],[8- Control Flow & Logic]]&"*" ) -> 0 | J13: =COUNTIFS( 'Final set of papers'!$F$2:$F1000, "*"&A13&"*", 'Final set of papers'!$G$2:$G1000, "*"&Table1[[#HEADERS],[9- Domain Specific Issues]]&"*" ) -> 0

Sheet IaC_issues_across_layers
A1: IaC Layer | B1: 1- Structural Quality | C1: 2- Syntactic & Linguistic Quality | D1: 3- Security | E1: 4- Operational Quality | F1: 5- Performance & Resource management | G1: 6- Maintability & Documentation | H1: 7- Data & Variable management | I1: 8- Control Flow & Logic | J1: 9- Domain Specific Issues
A2: Config management | B2: =COUNTIFS( 'Final set of papers'!$J$2:$J990, "*"&A2&"*", 'Final set of papers'!$G$2:$G990, "*"&Table2[[#HEADERS],[1- Structural Quality]]&"*" ) -> 10 | C2: =COUNTIFS( 'Final set of papers'!$J$2:$J990, "*"&A2&"*", 'Final set of papers'!$G$2:$G990, "*"&Table2[[#HEADERS],[2- Syntactic & Linguistic Quality]]&"*" ) -> 12 | D2: =COUNTIFS( 'Final set of papers'!$J$2:$J990, "*"&A2&"*", 'Final set of papers'!$G$2:$G990, "*"&Table2[[#HEADERS],[3- Security]]&"*" ) -> 14 | E2: =COUNTIFS( 'Final set of papers'!$J$2:$J990, "*"&A2&"*", 'Final set of papers'!$G$2:$G990, "*"&Table2[[#HEADERS],[4- Operational Quality]]&"*" ) -> 9 | F2: =COUNTIFS( 'Final set of papers'!$J$2:$J990, "*"&A2&"*", 'Final set of papers'!$G$2:$G990, "*"&Table2[[#HEADERS],[5- Performance & Resource management]]&"*" ) -> 1 | G2: =COUNTIFS( 'Final set of papers'!$J$2:$J990, "*"&A2&"*", 'Final set of papers'!$G$2:$G990, "*"&Table2[[#HEADERS],[6- Maintability & Documentation]]&"*" ) -> 10 | H2: =COUNTIFS( 'Final set of papers'!$J$2:$J990, "*"&A2&"*", 'Final set of papers'!$G$2:$G990, "*"&Table2[[#HEADERS],[7- Data & Variable management]]&"*" ) -> 8 | I2: =COUNTIFS( 'Final set of papers'!$J$2:$J990, "*"&A2&"*", 'Final set of papers'!$G$2:$G990, "*"&Table2[[#HEADERS],[8- Control Flow & Logic]]&"*" ) -> 6 | J2: =COUNTIFS( 'Final set of papers'!$J$2:$J990, "*"&A2&"*", 'Final set of papers'!$G$2:$G990, "*"&Table2[[#HEADERS],[9- Domain Specific Issues]]&"*" ) -> 4
A3: Provisioning | B3: =COUNTIFS( 'Final set of papers'!$J$2:$J990, "*"&A3&"*", 'Final set of papers'!$G$2:$G990, "*"&Table2[[#HEADERS],[1- Structural Quality]]&"*" ) -> 4 | C3: =COUNTIFS( 'Final set of papers'!$J$2:$J990, "*"&A3&"*", 'Final set of papers'!$G$2:$G990, "*"&Table2[[#HEADERS],[2- Syntactic & Linguistic Quality]]&"*" ) -> 2 | D3: =COUNTIFS( 'Final set of papers'!$J$2:$J990, "*"&A3&"*", 'Final set of papers'!$G$2:$G990, "*"&Table2[[#HEADERS],[3- Security]]&"*" ) -> 6 | E3: =COUNTIFS( 'Final set of papers'!$J$2:$J990, "*"&A3&"*", 'Final set of papers'!$G$2:$G990, "*"&Table2[[#HEADERS],[4- Operational Quality]]&"*" ) -> 8 | F3: =COUNTIFS( 'Final set of papers'!$J$2:$J990, "*"&A3&"*", 'Final set of papers'!$G$2:$G990, "*"&Table2[[#HEADERS],[5- Performance & Resource management]]&"*" ) -> 3 | G3: =COUNTIFS( 'Final set of papers'!$J$2:$J990, "*"&A3&"*", 'Final set of papers'!$G$2:$G990, "*"&Table2[[#HEADERS],[6- Maintability & Documentation]]&"*" ) -> 2 | H3: =COUNTIFS( 'Final set of papers'!$J$2:$J990, "*"&A3&"*", 'Final set of papers'!$G$2:$G990, "*"&Table2[[#HEADERS],[7- Data & Variable management]]&"*" ) -> 2 | I3: =COUNTIFS( 'Final set of papers'!$J$2:$J990, "*"&A3&"*", 'Final set of papers'!$G$2:$G990, "*"&Table2[[#HEADERS],[8- Control Flow & Logic]]&"*" ) -> 1 | J3: =COUNTIFS( 'Final set of papers'!$J$2:$J990, "*"&A3&"*", 'Final set of papers'!$G$2:$G990, "*"&Table2[[#HEADERS],[9- Domain Specific Issues]]&"*" ) -> 2
A4: Orchestration | B4: =COUNTIFS( 'Final set of papers'!$J$2:$J990, "*"&A4&"*", 'Final set of papers'!$G$2:$G990, "*"&Table2[[#HEADERS],[1- Structural Quality]]&"*" ) -> 2 | C4: =COUNTIFS( 'Final set of papers'!$J$2:$J990, "*"&A4&"*", 'Final set of papers'!$G$2:$G990, "*"&Table2[[#HEADERS],[2- Syntactic & Linguistic Quality]]&"*" ) -> 0 | D4: =COUNTIFS( 'Final set of papers'!$J$2:$J990, "*"&A4&"*", 'Final set of papers'!$G$2:$G990, "*"&Table2[[#HEADERS],[3- Security]]&"*" ) -> 6 | E4: =COUNTIFS( 'Final set of papers'!$J$2:$J990, "*"&A4&"*", 'Final set of papers'!$G$2:$G990, "*"&Table2[[#HEADERS],[4- Operational Quality]]&"*" ) -> 2 | F4: =COUNTIFS( 'Final set of papers'!$J$2:$J990, "*"&A4&"*", 'Final set of papers'!$G$2:$G990, "*"&Table2[[#HEADERS],[5- Performance & Resource management]]&"*" ) -> 2 | G4: =COUNTIFS( 'Final set of papers'!$J$2:$J990, "*"&A4&"*", 'Final set of papers'!$G$2:$G990, "*"&Table2[[#HEADERS],[6- Maintability & Documentation]]&"*" ) -> 1 | H4: =COUNTIFS( 'Final set of papers'!$J$2:$J990, "*"&A4&"*", 'Final set of papers'!$G$2:$G990, "*"&Table2[[#HEADERS],[7- Data & Variable management]]&"*" ) -> 0 | I4: =COUNTIFS( 'Final set of papers'!$J$2:$J990, "*"&A4&"*", 'Final set of papers'!$G$2:$G990, "*"&Table2[[#HEADERS],[8- Control Flow & Logic]]&"*" ) -> 0 | J4: =COUNTIFS( 'Final set of papers'!$J$2:$J990, "*"&A4&"*", 'Final set of papers'!$G$2:$G990, "*"&Table2[[#HEADERS],[9- Domain Specific Issues]]&"*" ) -> 2
A5: Image building | B5: =COUNTIFS( 'Final set of papers'!$J$2:$J990, "*"&A5&"*", 'Final set of papers'!$G$2:$G990, "*"&Table2[[#HEADERS],[1- Structural Quality]]&"*" ) -> 2 | C5: =COUNTIFS( 'Final set of papers'!$J$2:$J990, "*"&A5&"*", 'Final set of papers'!$G$2:$G990, "*"&Table2[[#HEADERS],[2- Syntactic & Linguistic Quality]]&"*" ) -> 3 | D5: =COUNTIFS( 'Final set of papers'!$J$2:$J990, "*"&A5&"*", 'Final set of papers'!$G$2:$G990, "*"&Table2[[#HEADERS],[3- Security]]&"*" ) -> 3 | E5: =COUNTIFS( 'Final set of papers'!$J$2:$J990, "*"&A5&"*", 'Final set of papers'!$G$2:$G990, "*"&Table2[[#HEADERS],[4- Operational Quality]]&"*" ) -> 3 | F5: =COUNTIFS( 'Final set of papers'!$J$2:$J990, "*"&A5&"*", 'Final set of papers'!$G$2:$G990, "*"&Table2[[#HEADERS],[5- Performance & Resource management]]&"*" ) -> 3 | G5: =COUNTIFS( 'Final set of papers'!$J$2:$J990, "*"&A5&"*", 'Final set of papers'!$G$2:$G990, "*"&Table2[[#HEADERS],[6- Maintability & Documentation]]&"*" ) -> 2 | H5: =COUNTIFS( 'Final set of papers'!$J$2:$J990, "*"&A5&"*", 'Final set of papers'!$G$2:$G990, "*"&Table2[[#HEADERS],[7- Data & Variable management]]&"*" ) -> 2 | I5: =COUNTIFS( 'Final set of papers'!$J$2:$J990, "*"&A5&"*", 'Final set of papers'!$G$2:$G990, "*"&Table2[[#HEADERS],[8- Control Flow & Logic]]&"*" ) -> 1 | J5: =COUNTIFS( 'Final set of papers'!$J$2:$J990, "*"&A5&"*", 'Final set of papers'!$G$2:$G990, "*"&Table2[[#HEADERS],[9- Domain Specific Issues]]&"*" ) -> 1

Sheet Techniques_over_years
A1: Year | B1: 1 - Rule-Based and Pattern-Matching Approaches | C1: 2 - Graph-Based Analyses | D1: 3 - Formal Methods | E1: 4 - Statistical and Learning-Based Methods | F1: 5 - Testing Methods | G1: 6 - Other
A2: =IFERROR(__xludf.DUMMYFUNCTION("SORT(UNIQUE(ARRAYFORMULA(TRIM(FLATTEN(SPLIT(TEXTJOIN("","", TRUE, 'Final set of papers'!Q2:Q1000), "",""))))))"),"2015") -> 2015 | B2: =COUNTIFS( 'Final set of papers'!$Q$2:$Q1000, A2, 'Final set of papers'!$L$2:$L1000, "*"&Table3[[#HEADERS],[1 - Rule-Based and Pattern-Matching Approaches]]&"*" ) -> 1 | C2: =COUNTIFS( 'Final set of papers'!$Q$2:$Q1000, A2, 'Final set of papers'!$L$2:$L1000, "*"&Table3[[#HEADERS],[2 - Graph-Based Analyses]]&"*" ) -> 0 | D2: =COUNTIFS( 'Final set of papers'!$Q$2:$Q1000, A2, 'Final set of papers'!$L$2:$L1000, "*"&Table3[[#HEADERS],[3 - Formal Methods]]&"*" ) -> 0 | E2: =COUNTIFS( 'Final set of papers'!$Q$2:$Q1000, A2, 'Final set of papers'!$L$2:$L1000, "*"&Table3[[#HEADERS],[4 - Statistical and Learning-Based Methods]]&"*" ) -> 1 | F2: =COUNTIFS( 'Final set of papers'!$Q$2:$Q1000, A2, 'Final set of papers'!$L$2:$L1000, "*"&Table3[[#HEADERS],[5 - Testing Methods]]&"*" ) -> 0 | G2: =COUNTIFS( 'Final set of papers'!$Q$2:$Q1000, A2, 'Final set of papers'!$L$2:$L1000, "*"&Table3[[#HEADERS],[6 - Other]]&"*" ) -> 0
A3: =IFERROR(__xludf.DUMMYFUNCTION("""COMPUTED_VALUE"""),"2016") -> 2016 | B3: =COUNTIFS( 'Final set of papers'!$Q$2:$Q1000, A3, 'Final set of papers'!$L$2:$L1000, "*"&Table3[[#HEADERS],[1 - Rule-Based and Pattern-Matching Approaches]]&"*" ) -> 1 | C3: =COUNTIFS( 'Final set of papers'!$Q$2:$Q1000, A3, 'Final set of papers'!$L$2:$L1000, "*"&Table3[[#HEADERS],[2 - Graph-Based Analyses]]&"*" ) -> 1 | D3: =COUNTIFS( 'Final set of papers'!$Q$2:$Q1000, A3, 'Final set of papers'!$L$2:$L1000, "*"&Table3[[#HEADERS],[3 - Formal Methods]]&"*" ) -> 1 | E3: =COUNTIFS( 'Final set of papers'!$Q$2:$Q1000, A3, 'Final set of papers'!$L$2:$L1000, "*"&Table3[[#HEADERS],[4 - Statistical and Learning-Based Methods]]&"*" ) -> 0 | F3: =COUNTIFS( 'Final set of papers'!$Q$2:$Q1000, A3, 'Final set of papers'!$L$2:$L1000, "*"&Table3[[#HEADERS],[5 - Testing Methods]]&"*" ) -> 0 | G3: =COUNTIFS( 'Final set of papers'!$Q$2:$Q1000, A3, 'Final set of papers'!$L$2:$L1000, "*"&Table3[[#HEADERS],[6 - Other]]&"*" ) -> 0
A4: =IFERROR(__xludf.DUMMYFUNCTION("""COMPUTED_VALUE"""),"2017") -> 2017 | B4: =COUNTIFS( 'Final set of papers'!$Q$2:$Q1000, A4, 'Final set of papers'!$L$2:$L1000, "*"&Table3[[#HEADERS],[1 - Rule-Based and Pattern-Matching Approaches]]&"*" ) -> 0 | C4: =COUNTIFS( 'Final set of papers'!$Q$2:$Q1000, A4, 'Final set of papers'!$L$2:$L1000, "*"&Table3[[#HEADERS],[2 - Graph-Based Analyses]]&"*" ) -> 0 | D4: =COUNTIFS( 'Final set of papers'!$Q$2:$Q1000, A4, 'Final set of papers'!$L$2:$L1000, "*"&Table3[[#HEADERS],[3 - Formal Methods]]&"*" ) -> 1 | E4: =COUNTIFS( 'Final set of papers'!$Q$2:$Q1000, A4, 'Final set of papers'!$L$2:$L1000, "*"&Table3[[#HEADERS],[4 - Statistical and Learning-Based Methods]]&"*" ) -> 0 | F4: =COUNTIFS( 'Final set of papers'!$Q$2:$Q1000, A4, 'Final set of papers'!$L$2:$L1000, "*"&Table3[[#HEADERS],[5 - Testing Methods]]&"*" ) -> 0 | G4: =COUNTIFS( 'Final set of papers'!$Q$2:$Q1000, A4, 'Final set of papers'!$L$2:$L1000, "*"&Table3[[#HEADERS],[6 - Other]]&"*" ) -> 0
A5: =IFERROR(__xludf.DUMMYFUNCTION("""COMPUTED_VALUE"""),"2018") -> 2018 | B5: =COUNTIFS( 'Final set of papers'!$Q$2:$Q1000, A5, 'Final set of papers'!$L$2:$L1000, "*"&Table3[[#HEADERS],[1 - Rule-Based and Pattern-Matching Approaches]]&"*" ) -> 2 | C5: =COUNTIFS( 'Final set of papers'!$Q$2:$Q1000, A5, 'Final set of papers'!$L$2:$L1000, "*"&Table3[[#HEADERS],[2 - Graph-Based Analyses]]&"*" ) -> 2 | D5: =COUNTIFS( 'Final set of papers'!$Q$2:$Q1000, A5, 'Final set of papers'!$L$2:$L1000, "*"&Table3[[#HEADERS],[3 - Formal Methods]]&"*" ) -> 0 | E5: =COUNTIFS( 'Final set of papers'!$Q$2:$Q1000, A5, 'Final set of papers'!$L$2:$L1000, "*"&Table3[[#HEADERS],[4 - Statistical and Learning-Based Methods]]&"*" ) -> 1 | F5: =COUNTIFS( 'Final set of papers'!$Q$2:$Q1000, A5, 'Final set of papers'!$L$2:$L1000, "*"&Table3[[#HEADERS],[5 - Testing Methods]]&"*" ) -> 0 | G5: =COUNTIFS( 'Final set of papers'!$Q$2:$Q1000, A5, 'Final set of papers'!$L$2:$L1000, "*"&Table3[[#HEADERS],[6 - Other]]&"*" ) -> 0
A6: =IFERROR(__xludf.DUMMYFUNCTION("""COMPUTED_VALUE"""),"2019") -> 2019 | B6: =COUNTIFS( 'Final set of papers'!$Q$2:$Q1000, A6, 'Final set of papers'!$L$2:$L1000, "*"&Table3[[#HEADERS],[1 - Rule-Based and Pattern-Matching Approaches]]&"*" ) -> 1 | C6: =COUNTIFS( 'Final set of papers'!$Q$2:$Q1000, A6, 'Final set of papers'!$L$2:$L1000, "*"&Table3[[#HEADERS],[2 - Graph-Based Analyses]]&"*" ) -> 0 | D6: =COUNTIFS( 'Final set of papers'!$Q$2:$Q1000, A6, 'Final set of papers'!$L$2:$L1000, "*"&Table3[[#HEADERS],[3 - Formal Methods]]&"*" ) -> 0 | E6: =COUNTIFS( 'Final set of papers'!$Q$2:$Q1000, A6, 'Final set of papers'!$L$2:$L1000, "*"&Table3[[#HEADERS],[4 - Statistical and Learning-Based Methods]]&"*" ) -> 2 | F6: =COUNTIFS( 'Final set of papers'!$Q$2:$Q1000, A6, 'Final set of papers'!$L$2:$L1000, "*"&Table3[[#HEADERS],[5 - Testing Methods]]&"*" ) -> 0 | G6: =COUNTIFS( 'Final set of papers'!$Q$2:$Q1000, A6, 'Final set of papers'!$L$2:$L1000, "*"&Table3[[#HEADERS],[6 - Other]]&"*" ) -> 0
A7: =IFERROR(__xludf.DUMMYFUNCTION("""COMPUTED_VALUE"""),"2020") -> 2020 | B7: =COUNTIFS( 'Final set of papers'!$Q$2:$Q1000, A7, 'Final set of papers'!$L$2:$L1000, "*"&Table3[[#HEADERS],[1 - Rule-Based and Pattern-Matching Approaches]]&"*" ) -> 1 | C7: =COUNTIFS( 'Final set of papers'!$Q$2:$Q1000, A7, 'Final set of papers'!$L$2:$L1000, "*"&Table3[[#HEADERS],[2 - Graph-Based Analyses]]&"*" ) -> 0 | D7: =COUNTIFS( 'Final set of papers'!$Q$2:$Q1000, A7, 'Final set of papers'!$L$2:$L1000, "*"&Table3[[#HEADERS],[3 - Formal Methods]]&"*" ) -> 0 | E7: =COUNTIFS( 'Final set of papers'!$Q$2:$Q1000, A7, 'Final set of papers'!$L$2:$L1000, "*"&Table3[[#HEADERS],[4 - Statistical and Learning-Based Methods]]&"*" ) -> 1 | F7: =COUNTIFS( 'Final set of papers'!$Q$2:$Q1000, A7, 'Final set of papers'!$L$2:$L1000, "*"&Table3[[#HEADERS],[5 - Testing Methods]]&"*" ) -> 0 | G7: =COUNTIFS( 'Final set of papers'!$Q$2:$Q1000, A7, 'Final set of papers'!$L$2:$L1000, "*"&Table3[[#HEADERS],[6 - Other]]&"*" ) -> 2
A8: =IFERROR(__xludf.DUMMYFUNCTION("""COMPUTED_VALUE"""),"2021") -> 2021 | B8: =COUNTIFS( 'Final set of papers'!$Q$2:$Q1000, A8, 'Final set of papers'!$L$2:$L1000, "*"&Table3[[#HEADERS],[1 - Rule-Based and Pattern-Matching Approaches]]&"*" ) -> 1 | C8: =COUNTIFS( 'Final set of papers'!$Q$2:$Q1000, A8, 'Final set of papers'!$L$2:$L1000, "*"&Table3[[#HEADERS],[2 - Graph-Based Analyses]]&"*" ) -> 0 | D8: =COUNTIFS( 'Final set of papers'!$Q$2:$Q1000, A8, 'Final set of papers'!$L$2:$L1000, "*"&Table3[[#HEADERS],[3 - Formal Methods]]&"*" ) -> 0 | E8: =COUNTIFS( 'Final set of papers'!$Q$2:$Q1000, A8, 'Final set of papers'!$L$2:$L1000, "*"&Table3[[#HEADERS],[4 - Statistical and Learning-Based Methods]]&"*" ) -> 0 | F8: =COUNTIFS( 'Final set of papers'!$Q$2:$Q1000, A8, 'Final set of papers'!$L$2:$L1000, "*"&Table3[[#HEADERS],[5 - Testing Methods]]&"*" ) -> 0 | G8: =COUNTIFS( 'Final set of papers'!$Q$2:$Q1000, A8, 'Final set of papers'!$L$2:$L1000, "*"&Table3[[#HEADERS],[6 - Other]]&"*" ) -> 0
A9: =IFERROR(__xludf.DUMMYFUNCTION("""COMPUTED_VALUE"""),"2022") -> 2022 | B9: =COUNTIFS( 'Final set of papers'!$Q$2:$Q1000, A9, 'Final set of papers'!$L$2:$L1000, "*"&Table3[[#HEADERS],[1 - Rule-Based and Pattern-Matching Approaches]]&"*" ) -> 1 | C9: =COUNTIFS( 'Final set of papers'!$Q$2:$Q1000, A9, 'Final set of papers'!$L$2:$L1000, "*"&Table3[[#HEADERS],[2 - Graph-Based Analyses]]&"*" ) -> 2 | D9: =COUNTIFS( 'Final set of papers'!$Q$2:$Q1000, A9, 'Final set of papers'!$L$2:$L1000, "*"&Table3[[#HEADERS],[3 - Formal Methods]]&"*" ) -> 0 | E9: =COUNTIFS( 'Final set of papers'!$Q$2:$Q1000, A9, 'Final set of papers'!$L$2:$L1000, "*"&Table3[[#HEADERS],[4 - Statistical and Learning-Based Methods]]&"*" ) -> 2 | F9: =COUNTIFS( 'Final set of papers'!$Q$2:$Q1000, A9, 'Final set of papers'!$L$2:$L1000, "*"&Table3[[#HEADERS],[5 - Testing Methods]]&"*" ) -> 0 | G9: =COUNTIFS( 'Final set of papers'!$Q$2:$Q1000, A9, 'Final set of papers'!$L$2:$L1000, "*"&Table3[[#HEADERS],[6 - Other]]&"*" ) -> 0
A10: =IFERROR(__xludf.DUMMYFUNCTION("""COMPUTED_VALUE"""),"2023") -> 2023 | B10: =COUNTIFS( 'Final set of papers'!$Q$2:$Q1000, A10, 'Final set of papers'!$L$2:$L1000, "*"&Table3[[#HEADERS],[1 - Rule-Based and Pattern-Matching Approaches]]&"*" ) -> 9 | C10: =COUNTIFS( 'Final set of papers'!$Q$2:$Q1000, A10, 'Final set of papers'!$L$2:$L1000, "*"&Table3[[#HEADERS],[2 - Graph-Based Analyses]]&"*" ) -> 9 | D10: =COUNTIFS( 'Final set of papers'!$Q$2:$Q1000, A10, 'Final set of papers'!$L$2:$L1000, "*"&Table3[[#HEADERS],[3 - Formal Methods]]&"*" ) -> 0 | E10: =COUNTIFS( 'Final set of papers'!$Q$2:$Q1000, A10, 'Final set of papers'!$L$2:$L1000, "*"&Table3[[#HEADERS],[4 - Statistical and Learning-Based Methods]]&"*" ) -> 4 | F10: =COUNTIFS( 'Final set of papers'!$Q$2:$Q1000, A10, 'Final set of papers'!$L$2:$L1000, "*"&Table3[[#HEADERS],[5 - Testing Methods]]&"*" ) -> 0 | G10: =COUNTIFS( 'Final set of papers'!$Q$2:$Q1000, A10, 'Final set of papers'!$L$2:$L1000, "*"&Table3[[#HEADERS],[6 - Other]]&"*" ) -> 0
A11: =IFERROR(__xludf.DUMMYFUNCTION("""COMPUTED_VALUE"""),"2024") -> 2024 | B11: =COUNTIFS( 'Final set of papers'!$Q$2:$Q1000, A11, 'Final set of papers'!$L$2:$L1000, "*"&Table3[[#HEADERS],[1 - Rule-Based and Pattern-Matching Approaches]]&"*" ) -> 3 | C11: =COUNTIFS( 'Final set of papers'!$Q$2:$Q1000, A11, 'Final set of papers'!$L$2:$L1000, "*"&Table3[[#HEADERS],[2 - Graph-Based Analyses]]&"*" ) -> 4 | D11: =COUNTIFS( 'Final set of papers'!$Q$2:$Q1000, A11, 'Final set of papers'!$L$2:$L1000, "*"&Table3[[#HEADERS],[3 - Formal Methods]]&"*" ) -> 1 | E11: =COUNTIFS( 'Final set of papers'!$Q$2:$Q1000, A11, 'Final set of papers'!$L$2:$L1000, "*"&Table3[[#HEADERS],[4 - Statistical and Learning-Based Methods]]&"*" ) -> 5 | F11: =COUNTIFS( 'Final set of papers'!$Q$2:$Q1000, A11, 'Final set of papers'!$L$2:$L1000, "*"&Table3[[#HEADERS],[5 - Testing Methods]]&"*" ) -> 0 | G11: =COUNTIFS( 'Final set of papers'!$Q$2:$Q1000, A11, 'Final set of papers'!$L$2:$L1000, "*"&Table3[[#HEADERS],[6 - Other]]&"*" ) -> 4
A12: =IFERROR(__xludf.DUMMYFUNCTION("""COMPUTED_VALUE"""),"2025") -> 2025 | B12: =COUNTIFS( 'Final set of papers'!$Q$2:$Q1000, A12, 'Final set of papers'!$L$2:$L1000, "*"&Table3[[#HEADERS],[1 - Rule-Based and Pattern-Matching Approaches]]&"*" ) -> 3 | C12: =COUNTIFS( 'Final set of papers'!$Q$2:$Q1000, A12, 'Final set of papers'!$L$2:$L1000, "*"&Table3[[#HEADERS],[2 - Graph-Based Analyses]]&"*" ) -> 1 | D12: =COUNTIFS( 'Final set of papers'!$Q$2:$Q1000, A12, 'Final set of papers'!$L$2:$L1000, "*"&Table3[[#HEADERS],[3 - Formal Methods]]&"*" ) -> 2 | E12: =COUNTIFS( 'Final set of papers'!$Q$2:$Q1000, A12, 'Final set of papers'!$L$2:$L1000, "*"&Table3[[#HEADERS],[4 - Statistical and Learning-Based Methods]]&"*" ) -> 3 | F12: =COUNTIFS( 'Final set of papers'!$Q$2:$Q1000, A12, 'Final set of papers'!$L$2:$L1000, "*"&Table3[[#HEADERS],[5 - Testing Methods]]&"*" ) -> 0 | G12: =COUNTIFS( 'Final set of papers'!$Q$2:$Q1000, A12, 'Final set of papers'!$L$2:$L1000, "*"&Table3[[#HEADERS],[6 - Other]]&"*" ) -> 2

Sheet All papers
A1: Publication Year | B1: Author | C1: Title | D1: Url | E1: Abstract Note | F1: Manual Tags | G1: Automatic Tags | H1: Conference Name
A2: 2023 | B2: Dell’Immagine, Giorgio; Soldani, Jacopo; Brogi, Antonio | C2: KubeHound: Detecting Microservices’ Security Smells in Kubernetes Deployments | D2: https://www.mdpi.com/1999-5903/15/7/228 | E2: As microservice-based architectures are increasingly adopted, microservices security has become a crucial aspect to consider for IT businesses. Starting from a set of “security smells” for microservice applications that were recently proposed in the literature, we enable the automatic detection of such smells in microservice applications deployed with Kubernetes. We first introduce possible analysis techniques to automatically detect security smells in Kubernetes-deployed microservices. We then demonstrate the practical applicability of the proposed techniques by introducing KubeHound, an extensible prototype tool for automatically detecting security smells in microservice applications, and which already features a selected subset of the discussed analyses. We finally show that KubeHound can effectively detect instances of security smells in microservice applications by means of controlled experiments and by applying it to existing, third-party applications. | F2: Journal | G2: Kubernetes; microservices; security; smell detection
A3: 2019 | B3: Rahman, Akond; Mahdavi-Hezaveh, Rezvan; Williams, Laurie | C3: A systematic mapping study of infrastructure as code research | D3: https://www.sciencedirect.com/science/article/pii/S0950584918302507 | E3: Context: Infrastructure as code (IaC) is the practice to automatically configure system dependencies and to provision local and remote instances. Practitioners consider IaC as a fundamental pillar to implement DevOps practices, which helps them to rapidly deliver software and services to end-users. Information technology (IT) organizations, such as GitHub, Mozilla, Facebook, Google and Netflix have adopted IaC. A systematic mapping study on existing IaC research can help researchers to identify potential research areas related to IaC, for example defects and security flaws that may occur in IaC scripts. Objective: The objective of this paper is to help researchers identify research areas related to infrastructure as code (IaC) by conducting a systematic mapping study of IaC-related research. Method: We conduct our research study by searching five scholar databases. We collect a set of 31,498 publications by using seven search strings. By systematically applying inclusion and exclusion criteria, which includes removing duplicates and removing non-English and non peer-reviewed publications, we identify 32 publications related to IaC. We identify topics addressed in these publications by applying qualitative analysis. Results: We identify four topics studied in IaC-related publications: (i) framework/tool for infrastructure as code; (ii) adoption of infrastructure as code; (iii) empirical study related to infrastructure as code; and (iv) testing in infrastructure as code. According to our analysis, 50.0% of the studied 32 publications propose a framework or tool to implement the practice of IaC or extend the functionality of an existing IaC tool. Conclusion: Our findings suggest that framework or tools is a well-studied topic in IaC research. As defects and security flaws can have serious consequences for the deployment and development environments in DevOps, we observe the need for research studies that will study defects and security flaws for IaC. | F3: Journal | G3: Configuration as code; Configuration script; Continuous deployment; Devops; Infrastructure as code; Software engineering; Systematic mapping study
A4: 2025 | B4: Nasiri, Roya; Kumara, Indika; Tamburri, Damian Andrew; van den Heuvel, Willem-Jan | C4: Towards a Taxonomy of Infrastructure as Code Misconfigurations: An Ansible Study | D4: https://drive.google.com/file/d/101WCE65iQBGi4cWxln1_3Y2xKRb-2DUc/view?usp=sharing | E4: Infrastructure as Code (IaC) enables the management and provisioning of infrastructure using code instead of manual processes. While the IaC approach can simplify and automate infrastructure management, the configuration errors (i.e., misconfigurations) in the IaC scripts can significantly hinder achieving the benefits of the automation, incur undue costs, and leave the system faulty and insecure. In this paper, we present a taxonomy of IaC misconfigurations to assist practitioners and researchers in building tools for detecting misconfigurations. The user manuals of the IaC frameworks describe configuration parameters and their usage constraints, and provide recommendations on configuring certain parameters correctly. Hence, we systemically collected and analyzed 100 user manuals of the Ansible IaC language to compile a catalog of 25 configuration errors. We also developed a proof-of-concept tool for using the information in the user manuals to generate misconfiguration detection rules. | F4: Journal
A5: 2024 | B5: Drosos, Georgios-Petros; Sotiropoulos, Thodoris; Alexopoulos, Georgios; Mitropoulos, Dimitris; Su, Zhendong | C5: When Your Infrastructure Is a Buggy Program: Understanding Faults in Infrastructure as Code Ecosystems | D5: https://dl.acm.org/doi/10.1145/3689799 | E5: Modern applications have become increasingly complex and their manual installation and configuration is no longer practical. Instead, IT organizations heavily rely on Infrastructure as Code (IaC) technologies, to automate the provisioning, configuration, and maintenance of computing infrastructures and systems. IaC systems typically offer declarative, domain-specific languages (DSLs) that allow system administrators and developers to write high-level programs that specify the desired state of their infrastructure in a reliable, predictable, and documented fashion. Just like traditional programs, IaC software is not immune to faults, with issues ranging from deployment failures to critical misconfigurations that often impact production systems used by millions of end users. Surprisingly, despite its crucial role in global infrastructure management, the tooling and techniques for ensuring IaC reliability still have room for improvement. In this work, we conduct a comprehensive analysis of 360 bugs identified in IaC software within prominent IaC ecosystems including Ansible, Puppet, and Chef. Our work is the first in-depth exploration of bug characteristics in these widely-used IaC environments. Through our analysis we aim to understand: (1) how these bugs manifest, (2) their underlying root causes, (3) their reproduction requirements in terms of system state (e.g., operating system versions) or input characteristics, and (4) how these bugs are fixed. Based on our findings, we evaluate the state-of-the-art techniques for IaC reliability, identify their limitations, and provide a set of recommendations for future research. We believe that our study helps researchers to (1) better understand the complexity and peculiarities of IaC software, and (2) develop advanced tooling for more reliable and robust system configurations. | F5: Journal
A6: 2024 | B6: Sokolowski, Daniel; Spielmann, David; Salvaneschi, Guido | C6: Automated Infrastructure as Code Program Testing | D6: https://ieeexplore.ieee.org/document/10516612 | E6: Infrastructure as Code (IaC) enables efficient deployment and operation, which are crucial to releasing software quickly. As setups can be complex, developers implement IaC programs in general-purpose programming languages like TypeScript and Python, using PL-IaC solutions like Pulumi and AWS CDK. The reliability of such IaC programs is even more relevant than in traditional software because a bug in IaC impacts the whole system. Yet, even though testing is a standard development practice, it is rarely used for IaC programs. For instance, in August 2022, less than 1 % of the public Pulumi IaC programs on GitHub implemented tests. Available IaC program testing techniques severely limit the development velocity or require much development effort. To solve these issues, we propose Automated Configuration Testing (ACT), a methodology to test IaC programs in many configurations quickly and with low effort. ACT automatically mocks all resource definitions in the IaC program and uses generator and oracle plugins for test generation and validation. We implement ACT in ProTI, a testing tool for Pulumi TypeScript with a type-based generator and oracle, and support for application specifications. Our evaluation with 6 081 programs from GitHub and artificial benchmarks shows that ProTI can directly be applied to existing IaC programs, quickly finds bugs where current techniques are infeasible, and enables reusing existing generators and oracles thanks to its pluggable architecture. | F6: Journal | G6: Cloud computing; Codes; DevOps; Engines; fuzzing; Generators; infrastructure as code; Libraries; Property-based testing; Software; Testing
A7: 2023 | B7: Özdoğan, Erdal; Ceran, Onur; ÜSTÜNDAĞ, Mutlu | C7: Systematic Analysis of Infrastructure as Code Technologies | D7: https://dergipark.org.tr/tr/download/article-file/3463145 | E7: “Infrastructure as Code” technologies are the network automation concept used in configuring network devices, allocating network resources, and deploying developed applications. By using machine-readable codes, various tasks that previously required time and effort can now be done dynamically with infrastructure as code tools. Although Infrastructure as Code is a technology that brings many advantages and is still at the beginning of its popularity, there are not enough resource in the literature. In this study, the key concepts of Infrastructure as Code technologies are discussed and infrastructure as code tools are systematically examined. The four most used Infrastructure as Code tools were examined in terms of management, language, data representation, code approach, stateful and stateless, architectural perspectives. Also, they were compared over these key concepts. | F7: Journal
A8: 2023 | B8: RahmanAkond; ParninChris | C8: Detecting and Characterizing Propagation of Security Weaknesses in Puppet-Based Infrastructure Management | D8: https://dl.acm.org/doi/10.1109/TSE.2023.3265962 | E8: Despite being beneficial for managing computing infrastructure automatically, Puppet manifests are susceptible to security weaknesses, e.g., hard-coded secrets and use of weak cryptography algorithms. Adequate mitigation of security weaknesses in Puppet ... | F8: Journal
A9: 2024 | B9: Eng, Kalvin; Hindle, Abram; Stroulia, Eleni | C9: Patterns of Multi-Container Composition for Service Orchestration with Docker Compose | D9: http://arxiv.org/abs/2305.11293 | E9: Software design patterns present general code solutions to common software design problems. Modern software systems rely heavily on containers for running their constituent service components. Yet, despite the prevalence of ready-to-use Docker service images ready to participate in multi-container service compositions of applications, developers do not have much guidance on how to compose their own Docker service orchestrations. Thus in this work, we curate a dataset of successful projects that employ Docker Compose as an orchestration tool to run multiple service containers; then, we engage in qualitative and quantitative analysis of Docker Compose configurations. The collection of data and analysis enables the identification and naming of repeating multi-container composition patterns that are used in numerous successful open-source projects, much like software design patterns. These patterns highlight how software systems are orchestrated in the real-world and can give examples to anybody wishing to compose their own service orchestrations. These contributions also advance empirical research in software engineering patterns as evidence is provided about how Docker Compose is used. | F9: Journal | G9: Computer Science - Software Engineering
A10: 2023 | B10: Kwon, Sunjae; Lee, Sungu; Kim, Taehyoun; Ryu, Duksan; Baik, Jongmoon | C10: Exploring LLM-Based Automated Repairing of Ansible Script in Edge-Cloud Infrastructures | D10: https://ieeexplore.ieee.org/abstract/document/10376418 | E10: Edge-Cloud system requires massive infrastructures located in closer to the user to minimize latencies in handling Big data. Ansible is one of the most popular Infrastructure as Code (IaC) tools crucial for deploying these infrastructures of the Edge-cloud system. However, Ansible also consists of code, and its code quality is critical in ensuring the delivery of high-quality services within the Edge-Cloud system. On the other hand, the Large Langue Model (LLM) has performed remarkably on various Software Engineering (SE) tasks in recent years. One such task is Automated Program Repairing (APR), where LLMs assist developers in proposing code fixes for identified bugs. Nevertheless, prior studies in LLM-based APR have predominantly concentrated on widely used programming languages (PL), such as Java and C, and there has yet to be an attempt to apply it to Ansible. Hence, we explore the applicability of LLM-based APR on Ansible. We assess LLMs' performance (ChatGPT and Bard) on 58 Ansible script revision cases from Open Source Software (OSS). Our findings reveal promising prospects, with LLMs generating helpful responses in 70% of the sampled cases. Nonetheless, further research is necessary to harness this approach's potential fully. | F10: Journal | G10: Ansible; automated program repairing; Bard; Big Data; Chatbots; Codes; Computer bugs; Computer languages; Edge-cloud; Java; large langue model; Task analysis
A11: 2024 | B11: Xu, Qingxin; Gao, Yu; Wei, Jun | C11: An Empirical Study on Kubernetes Operator Bugs | D11: https://dl.acm.org/doi/10.1145/3650212.3680396 | E11: Kubernetes is the leading cluster management platform, and within Kubernetes, an operator is an application-specific program that leverages the Kubernetes API to automate operation tasks for managing an application deployed on a Kubernetes cluster. Users can declare a desired state for the managed cluster, specifying their configuration preferences. The operator program is responsible for reconciling the cluster’s actual state to align with the desired state. However, the complex, dynamic, and distributed nature of the overall system can introduce operator bugs, and lead to severe consequences, e.g., outages and undesired cluster state. In this paper, we conduct the first comprehensive study on 210 operator bugs from 36 Kubernetes operators. For all the studied bugs, we investigate their root causes, manifestations, impacts and fixing. Our study reveals many interesting findings that can guide the detection and testing of operator bugs, as well as the development of more reliable operators. | F11: RankA
A12: 2023 | B12: Opdebeeck, Ruben; Zerouali, Ahmed; De Roover, Coen | C12: Control and Data Flow in Security Smell Detection for Infrastructure as Code: Is It Worth the Effort? | D12: https://ieeexplore.ieee.org/document/10174011 | E12: Infrastructure as Code is the practice of developing and maintaining computing infrastructure through executable source code. Unfortunately, IaC has also brought about new cyber attack vectors. Prior work has therefore proposed static analyses that detect security smells in Infrastructure as Code files. However, they have so far remained at a shallow level, disregarding the control and data flow of the scripts under analysis, and may lack awareness of specific syntactic constructs. These limitations inhibit the quality of their results. To address these limitations, in this paper, we present GASEL, a novel security smell detector for the Ansible IaC language. It uses graph queries on program dependence graphs to detect 7 security smells. Our evaluation on an oracle of 243 real-world security smells and comparison against two state-of-the-art security smell detectors shows that awareness of syntax, control flow, and data flow enables our approach to substantially improve both precision and recall. We further question whether the additional effort required to develop and run such an approach is justified in practice. To this end, we investigate the prevalence of indirection through control and data flow in security smells across more than 15 000 Ansible scripts. We find that over 55% of security smells contain data-flow indirection, and over 32% require a whole-project analysis to detect. These findings motivate the need for deeper static analysis tools to detect security vulnerabilities in IaC. | F12: RankA | G12: security; code smells; Ansible; Codes; Detectors; empirical study; Infrastructure as Code; program dependence graph; Security; Software; Source coding; Static analysis; Syntactics | H12: 2023 IEEE/ACM 20th International Conference on Mining Software Repositories (MSR)
A13: 2024 | B13: Bessghaier, Narjes; Begoug, Mahi; Mebarki, Chemseddine; Ouni, Ali; Sayagh, Mohammed; Mkaouer, Mohamed Wiem | C13: On the Prevalence, Co-occurrence, and Impact of Infrastructure-as-Code Smells | D13: https://ieeexplore.ieee.org/document/10589858 | E13: In modern software systems, Infrastructure-as-Code (IaC) tools play a pivotal role in automating the management of various infrastructure resources such as networks, databases, and services. This automation is done through code-based specification files, commonly known as IaC files. Similarly to other code files, IaC files can suffer from violations of established implementation and design standards, i.e., IaC smells. Although prior research has studied various aspects of traditional smells in non-IaC artifacts, there is little knowledge of how IaC smells are prevalent, co-occurring, and impacting the change and defect proneness of IaC code. To fill this gap, we conduct an empirical study encompassing 82 Puppet-based open-source projects. Our investigation focused on 12 types of IaC smells in both implementation and design levels. Our findings reveal that IaC smells do not manifest uniformly, as IaC smells that are particularly associated with modularity issues, exhibit high prevalence rates across projects. Additionally, we found that 74% of IaC files are smelly and over 52% of the smelly IaC files have at least two co-occurring IaC smells. Furthermore, our findings highlight that, on average, smelly IaC files are modified nearly 3.8 times, in terms of number of commits, more frequently than non-smelly IaC files. Furthermore, smelly IaC files are found to be 3.1 times more prone to larger code changes, in terms of code churn, than non-smelly IaC files. Additionally, we found that smelly IaC files are 3.3 times more prone to the introduction of defects that are likely to persist in 1.65 more commits before being fixed than non-smelly IaC files. These findings advocate developers to be more aware of IaC smells in their projects and consider their correction. | F13: RankA | G13: Software systems; Codes; Automation; Code change; Computer bugs; Databases; Defects-proneness; Design standards; Encapsulation; IaC smells; Infrastructure-as-Code (IaC); Puppet | H13: 2024 IEEE International Conference on Software Analysis, Evolution and Reengineering (SANER)
A14: 2022 | B14: Chiari, Michele; De Pascalis, Michele; Pradella, Matteo | C14: Static Analysis of Infrastructure as Code: a Survey | D14: https://ieeexplore.ieee.org/document/9779848/citations?tabFilter=papers#citations | E14: The increasing use of Infrastructure as Code (IaC) in DevOps leads to benefits in speed and reliability of deployment operation, but extends to infrastructure challenges typical of software systems. IaC scripts can contain defects that result in security and reliability issues in the deployed infrastructure: techniques for detecting and preventing them are needed. We analyze and survey the current state of research in this respect by conducting a literature review on static analysis techniques for IaC. We describe analysis techniques, defect categories and platforms targeted by tools in the literature. | F14: RankA | G14: Bibliographies; cloud computing; Codes; Conferences; infrastructure as code; model checking; Software architecture; Software reliability; Software systems; static analysis; Static analysis; survey; verification | H14: 2022 IEEE 19th International Conference on Software Architecture Companion (ICSA-C)
C15: TerraDS: A Dataset for Terraform HCL Programs (MSR 2025 - Data and Tool Showcase Track) - MSR 2025 | D15: https://2025.msrconf.org/details/msr-2025-data-and-tool-showcase-track/12/TerraDS-A-Dataset-for-Terraform-HCL-Programs | E15: Infrastructure as Code (IaC) aims to automate infrastructure management by enabling the definition of infrastructure configurations in programs, rather than manually configuring hardware or cloud resources. Terraform is one of the most widely used IaC tools, gaining significant traction in recent years, as highlighted by its large and active user community and widespread adoption in both open-source and enterprise environments. Terraform’s code is written in the HashiCorp Configuration Language (HCL), which defines the infrastructure in a declarative manner. Despite the widespread adoption of Terraform, there is no large-scale dataset available for researchers to study IaC Terraform programs systematically. To address this gap, we present TerraDS, the first dataset of publicly available Terraform programs written in HCL. TerraDS contains the HCL code and the metadata of 67,360 open source repositories with permissive open-source licenses. The dataset includes 279,344 Terraform modules with 1,773,991 registered resources, all compiled into a reusable archive (~335 MB). | F15: RankA
A16: 2024 | C16: Fine-Grained Just-In-Time Defect Prediction at the Block Level in Infrastructure-as-Code (IaC) | Proceedings of the 21st International Conference on Mining Software Repositories | D16: https://dl.acm.org/doi/10.1145/3643991.3644934 | E16: Infrastructure-as-Code (IaC) is an emerging software engineering practice that leverages source code to facilitate automated configuration of software systems' infrastructure. IaC files are typically complex, containing hundreds of lines of code and dependencies, making them prone to defects, which can result in breaking online services at scale. To help developers early identify and fix IaC defects, research efforts have introduced IaC defect prediction models at the file level. However, the granularity of the proposed approaches remains coarse-grained, requiring developers to inspect hundreds of lines of code in a file, while only a small fragment of code is defective. To alleviate this issue, we introduce a machine-learning-based approach to predict IaC defects at a fine-grained level, focusing on IaC blocks, i.e., small code units that encapsulate specific behaviours within an IaC file. We trained various machine learning algorithms based on a mixture of code, process, and change-level metrics. We evaluated our approach on 19 open-source projects that use Terraform, a widely used IaC tool. The results indicated that there is no single algorithm that consistently outperforms the others in 19 projects. Overall, among the six algorithms, we observed that the LightGBM model achieved a higher average of 0.21 in terms of MCC and 0.71 in terms of AUC. Models analysis reveals that the developer's experience and the relative number of added lines tend to be the most important features. Additionally, we found that blocks belonging to the most frequent types are more prone to defects. Our defect prediction models have also shown sensitivity to concept drift, indicating that IaC practitioners should regularly retrain their models. | F16: RankA
A17: 2023 | B17: Begoug, Mahi; Bessghaier, Narjes; Ouni, Ali; AlOmar, Eman Abdullah; Mkaouer, Mohamed Wiem | C17: What Do Infrastructure-as-Code Practitioners Discuss: An Empirical Study on Stack Overflow | D17: https://ieeexplore.ieee.org/document/10304847 | E17: Background. Infrastructure-as-Code (IaC) is an emerging practice to manage cloud infrastructure resources for software systems. Modern software development has evolved to embrace IaC as a best practice for consistently provisioning and managing infrastructure using various tools such as Terraform and Ansible. However, recent studies highlighted that developers still encounter various challenges with IaC tools. Aims. We aim in this paper to understand the different challenges that developers encounter with IaC and analyze the trend of seeking assistance on Q&A platforms in the context of IaC. To this end, we conduct a large-scale empirical study investigating developers' discussions in Stack Overflow. Method. We first collect IaC-relevant tags on Stack Overflow, constituting a dataset that comprises 52,692 questions and 64,078 answers. Then, we group questions into specific topics using the Latent Dirichlet Allocation (LDA) method, which we optimize using a Genetic Algorithm (GA) for parameter's fine-tuning. Finally, to gain better insights, we analyze the identified topics based on different criteria such as popularity and difficulty. Results. Our findings reveal an average yearly increase of 150% in terms of IaC-related questions and 135% in terms of users between 2011 and 2022. Furthermore, we observe that IaC questions revolve around seven main topics: server configuration, policy configuration, networking, deployment pipelines, variable management, templating, and file management. Notably, we found that server configuration and file management are the most popular topics, i.e., the most discussed among IaC developers, while the deployment pipelines and templating topics are the most difficult. Conclusions. Our results shed light on IaC challenges that are often encountered by developers on popular Q&A platforms. These findings reveal important implications for practitioners seeking better support for IaC tools in real-world settings and for researchers to better understand the IaC community needs and further investigate IaC in different aspects. | F17: RankA | G17: Best practices; Software systems; Infrastructure-as-Code (IaC); Market research; Developers Discussions; Pipelines; Resource management; Servers; Software measurement; Stack Overflow; Topic Modeling | H17: 2023 ACM/IEEE International Symposium on Empirical Software Engineering and Measurement (ESEM)
A18: 2022 | B18: Cannavacciuolo, Cecilio; Mariani, Leonardo | C18: Smoke Testing of Cloud Systems | D18: https://ieeexplore.ieee.org/document/9787844 | E18: Setting up a reliable and automated testing environment for cloud systems can be challenging due to the many issues that might compromise the stability of the deployments, such as poorly configured services and faulty infrastructure scripts. Test failures due to deployment procedures that have not terminated correctly may cause a significant waste of effort, resources, and time to organizations. Smoke testing can be used to design test suites that can be quickly executed to check if a system under test is operational before running any other test suite, which is executed only once the smoke test cases pass. Indeed, smoke testing can help prevent the generation of spurious test failures that would not be worth inspecting. So far, the design of smoke test suites has been entirely left to the intuition of testers, who may apply arbitrary and potentially weak criteria for their design. This paper addresses this issue by approaching smoke testing of cloud applications systematically. In particular, it introduces a reference model and nine adequacy criteria that can help practitioners design effective smoke test suites for their cloud systems. The assessment of smoke test suites satisfying the nine adequacy criteria on 60 versions of two industrial systems provides evidence of the trade-offs between the cost and the failure detection capability of the criteria. | F18: RankA | G18: build verification testing; cloud testing; Conferences; Costs; flaky tests; kubernetes; microservices; Organizations; Reliability engineering; smoke testing; Software testing; Stability criteria; Systematics; testing distributed systems | H18: 2022 IEEE Conference on Software Testing, Verification and Validation (ICST)
A19: 2023 | B19: Sokolowski, Daniel; Salvaneschi, Guido | C19: Towards Reliable Infrastructure as Code | D19: https://ieeexplore.ieee.org/document/10092598/citations#citations | E19: Modern Infrastructure as Code (IaC) programs are increasingly complex and much closer to traditional software than to simple configuration scripts. Their reliability is crucial because their failure prevents the deployment of applications, and incorrect behavior can introduce malfunction and severe security issues. Yet, software engineering tools to develop reliable programs, such as testing and verification, are barely used in IaC. In fact, we observed that developers mainly rely on integration testing, a slow and expensive practice that can increase confidence in end-to-end functionality but is infeasible to systematically test IaC programs in various configurations—which is required to ensure robustness. On the other hand, fast testing techniques, such as unit testing, are cumbersome with IaC programs because, today, they require significant coding overhead while only providing limited confidence.To solve this issue, we envision the automated testing tool ProTI, reducing the manual overhead and boosting confidence in the test results. ProTI embraces modern unit testing techniques to test IaC programs in many different configurations. Out of the box, ProTI is a fuzzer for Pulumi TypeScript IaC programs, randomly testing the program in many different configurations for termination, configuration correctness, and existing policy compliance. Then developers can add specifications to their program to guide random-based value generation, test additional properties, and add further mocking, making ProTI a property-based testing tool. Lastly, we aim at automatically verifying IaC-specific properties, e.g., access paths between resources. | F19: RankA | G19: Codes; Infrastructure as Code; Software; Market research; Software architecture; Writing; Reliability engineering; Robustness; Cloud Engineering; Fuzzing; Property-based Testing; Verification | H19: 2023 IEEE 20th International Conference on Software Architecture Companion (ICSA-C)
A20: 2020 | B20: Vassallo, Carmine; Proksch, Sebastian; Jancso, Anna; Gall, Harald C.; Di Penta, Massimiliano | C20: Configuration smells in continuous delivery pipelines: a linter and a six-month study on GitLab | D20: https://dl.acm.org/doi/10.1145/3368089.3409709 | E20: An effective and efficient application of Continuous Integration (CI) and Delivery (CD) requires software projects to follow certain principles and good practices. Configuring such a CI/CD pipeline is challenging and error-prone. Therefore, automated linters have been proposed to detect errors in the pipeline. While existing linters identify syntactic errors, detect security vulnerabilities or misuse of the features provided by build servers, they do not support developers that want to prevent common misconfigurations of a CD pipeline that potentially violate CD principles (“CD smells”). To this end, we propose CD-Linter, a semantic linter that can automatically identify four different smells in pipeline configuration files. We have evaluated our approach through a large-scale and long-term study that consists of (i) monitoring 145 issues (opened in as many open-source projects) over a period of 6 months, (ii) manually validating the detection precision and recall on a representative sample of issues, and (iii) assessing the magnitude of the observed smells on 5,312 open-source projects on GitLab. Our results show that CD smells are accepted and fixed by most of the developers and our linter achieves a precision of 87% and a recall of 94%. Those smells can be frequently observed in the wild, as 31% of projects with long configurations are affected by at least one smell. | F20: RankA*
A21: 2022 | B21: Sokolowski, Daniel | C21: Infrastructure as code for dynamic deployments | D21: https://dl.acm.org/doi/10.1145/3540250.3558912 | E21: Modern DevOps organizations require a high degree of automation to achieve software stability at frequent changes. Further, there is a need for flexible, timely reconfiguration of the infrastructure, e.g., to use pay-per-use infrastructure efficiently based on application load. Infrastructure as Code (IaC) is the DevOps tool to automate infrastructure. However, modern static IaC solutions only support infrastructures that are deployed and do not change afterward. To implement infrastructures that change dynamically over time, static IaC programs have to be (updated and) re-run, e.g., in a CI/CD pipeline, or configure an external orchestrator that implements the dynamic behavior, e.g., an autoscaler or Kubernetes operator. Both do not capture the dynamic behavior in the IaC program and prevent analyzing and testing the infrastructure configuration jointly with its dynamic behavior. To fill this gap, we envision dynamic IaC, which augments static IaC with the ability to define dynamic behavior within the IaC program. In contrast to static IaC programs, dynamic IaC programs run continuously. They re-evaluate program parts that depend on external signals when these change and automatically adjust the infrastructure accordingly. We implement DIaC as the first dynamic IaC solution and demonstrate it in two realistic use cases of broader relevance. With dynamic IaC, ensuring the program’s correctness is even harder than for static IaC because programs may define many target configurations in contrast to only a few. However, for this reason, it is also more critical. To solve this issue, we propose automated, specialized property-based testing for IaC programs and implement it in ProTI. | F21: RankA*
A22: 2024 | C22: Towards the self-healing of Infrastructure as Code projects using constrained LLM technologies | Proceedings of the 5th ACM/IEEE International Workshop on Automated Program Repair | D22: https://dl.acm.org/doi/10.1145/3643788.3648014 | F22: RankA*
A23: 2020 | C23: Testing practices for infrastructure as code | Proceedings of the 1st ACM SIGSOFT International Workshop on Languages and Tools for Next-Generation Testing | D23: https://dl.acm.org/doi/10.1145/3416504.3424334 | E23: Infrastructure as code (IaC) helps practitioners to rapidly deploy software services to end-users. Despite reported benefits, IaC scripts are susceptible to defects. Defects in IaC scripts can cause serious consequences, for example, creating large-scale outages similar to the Amazon Web Services (AWS) incident in 2017. The prevalence of defects in IaC scripts necessitates practitioners to implement IaC testing and be aware of IaC testing practices. A synthesis of IaC testing practices can enable practitioners in early mitigation of IaC defects and also help researchers to identify potential research avenues. The goal of this paper is to help practitioners improve the quality of infrastructure as code (IaC) scripts by identifying a set of testing practices for IaC scripts. We apply open coding on 50 Internet artifacts, such as blog posts to derive IaC testing practices. We identify six testing practices that include behavior-focused test coverage, the practice of measuring coverage of IaC test cases in terms of expected behavior. We conclude our paper by discussing how practitioners and researchers can leverage our derived list of testing practices for IaC. | F23: RankA*
A24: 2023 | C24: Leveraging Practitioners’ Feedback to Improve a Security Linter | Proceedings of the 37th IEEE/ACM International Conference on Automated Software Engineering | D24: https://dl.acm.org/doi/10.1145/3551349.3560419 | E24: Infrastructure-as-Code (IaC) is a technology that enables the management and distribution of infrastructure through code instead of manual processes. In 2020, Palo Alto Network’s Unit 42 announced the discovery of over 199K vulnerable IaC templates through their “Cloud Threat” Report. This report highlights the importance of tools to prevent vulnerabilities from reaching production. Unfortunately, we observed through a comprehensive study that a security linter for IaC scripts is not reliable yet—high false positive rates. Our approach to tackling this problem was to leverage community expertise to improve the precision of this tool. More precisely, we interviewed professional developers to collect their feedback on the root causes of imprecision of the state-of-the-art security linter for Puppet. From that feedback, we developed a linter adjusting 7 rules of an existing linter ruleset and adding 3 new rules. We conducted a new study with 131 practitioners, which helped us improve the tool’s precision significantly and achieve a final precision of 83%. An important takeaway from this paper is that obtaining professional feedback is fundamental to improving the rules’ precision and extending the rulesets, which is critical for the usefulness and adoption of lightweight tools, such as IaC security linters. | F24: RankA*
A25: 2020 | B25: Bhuiyan, Farzana Ahamed; Rahman, Akond | C25: Characterizing Co-located Insecure Coding Patterns in Infrastructure as Code Scripts | D25: https://ieeexplore.ieee.org/document/9319290 | E25: Context: Insecure coding patterns (ICPs), such as hard-coded passwords can be inadvertently introduced in infrastructure as code (IaC) scripts, providing malicious users the opportunity to attack provisioned computing infrastructure. As performing code reviews is resource-intensive, a characterization of co-located ICPs, i.e., ICPs that occur together in a script can help practitioners to prioritize their review efforts and mitigate ICPs in IaC scripts. Objective: The goal of this paper is to help practitioners in prioritizing code review efforts for infrastructure as code (IaC) scripts by conducting an empirical study of co-located insecure coding patterns in IaC scripts. Methodology: We conduct an empirical study with 1613, 2764 and 2845 Puppet scripts respectively collected from three organizations namely, Mozilla, Openstack, and Wikimedia. We apply association rule mining to identify co-located ICPs in IaC scripts. Results: We observe 17.9%, 32.9%, and 26.7% of the scripts to include colocated ICPs respectively, for Mozilla, Openstack, and Wikimedia. The most frequent co-located ICP category is hard-coded secret and suspicious comment. Conclusion: Practitioners can prioritize code review efforts for IaC scripts by reviewing scripts that include co-located ICPs. | F25: RankA* | G25: security; Measurement; Tools; empirical study; Security; Software; devops; infrastructure as code; puppet; devsecops; co-location; configuration script; Correlation; Encoding; insecure coding pattern; IP networks | H25: 2020 35th IEEE/ACM International Conference on Automated Software Engineering Workshops (ASEW)
A26: 2024 | B26: Sokolowski, Daniel; https://orcid.org/0000-0003-2911-8304; View Profile; Spielmann, David; https://orcid.org/0009-0004-1715-2059; View Profile; Salvaneschi, Guido; https://orcid.org/0000-0002-9324-8894; View Profile | C26: Unleashing the Giants: Enabling Advanced Testing for Infrastructure as Code | D26: https://dl.acm.org/doi/10.1145/3639478.3643078 | E26: Infrastructure as Code (IaC) programs are written in imperative programming languages like Python or TypeScript while declaratively defining the target state of software deployments, which the IaC solution then sets up, e.g., Pulumi and AWS CDK. Through a repository mining study and analysis, we noticed that testing IaC programs poses a dilemma: current techniques are either slow and expensive or require prohibitively high development effort. To solve this issue, we introduce Automated Configuration Testing (ACT), enabling efficient testing with low development effort. ACT automates the tedious aspects of unit testing IaC programs and is extensible through a plugin system for test generators and oracles. ACT is already effective with simple type-based plugins, and leveraging existing giants, i.e., advanced test generation and oracle techniques, in new plugins will further boost its effectiveness. | F26: RankA* | G26: DevOps; infrastructure as code; fuzzing; property-based testing
A27: 2024 | B27: Sahoo, Priyam; Pujar, Saurabh; Nalawade, Ganesh; Gebhardt, Richard; Mandel, Louis; Buratti, Luca | C27: Ansible Lightspeed: A Code Generation Service for IT Automation | D27: https://ieeexplore.ieee.org/document/10764992 | E27: The availability of Large Language Models (LLMs) which can generate code, has made it possible to create tools that improve developer productivity. Integrated development environments or IDEs which developers use to write software are often used as an interface to interact with LLMs. Although many such tools have been re-leased, almost all of them focus on general-purpose programming languages. Domain-specific languages, such as those crucial for Information Technology (IT) automation, have not received much attention. Ansible is one such YAML-based IT automation-specific language. Ansible Lightspeed is an LLM-based service designed explicitly to generate Ansible YAML, given natural language prompt.In this paper, we present the design and implementation of the Ansible Lightspeed service. We then evaluate its utility to developers using diverse indicators, including extended utilization, analysis of user edited suggestions, as well as user sentiments analysis. The evaluation is based on data collected for 10,696 real users including 3,910 returning users. The code for Ansible Lightspeed service and the analysis framework is made available for others to use.To our knowledge, our study is the first to involve thousands of users of code assistants for domain-specific languages. We are also the first code completion tool to present N-Day user retention figures, which is 13.66% on Day 30. We propose an improved version of user acceptance rate, called Strong Acceptance rate, where a suggestion is considered accepted only if less than 50% of it is edited and these edits do not change critical parts of the suggestion. By focusing on Ansible, Lightspeed is able to achieve a strong acceptance rate of 49.08% for multi-line Ansible task suggestions. With our findings we provide insights into the effectiveness of small, dedicated models in a domain-specific context. We hope this work serves as a reference for software engineering and machine learning researchers exploring code completion. | F27: RankA* | G27: Software engineering; Codes; Software; Automation; Large language models; ansible; Machine learning; Natural languages; code completion; Domain specific languages; generative models; ide; large language models; Productivity; Sentiment analysis; user study | H27: 2024 39th IEEE/ACM International Conference on Automated Software Engineering (ASE)
A28: 2019 | B28: Rahman, Akond; Parnin, Chris; Williams, Laurie | C28: The Seven Sins: Security Smells in Infrastructure as Code Scripts | D28: https://ieeexplore.ieee.org/document/8812041 | E28: Practitioners use infrastructure as code (IaC) scripts to provision servers and development environments. While developing IaC scripts, practitioners may inadvertently introduce security smells. Security smells are recurring coding patterns that are indicative of security weakness and can potentially lead to security breaches. The goal of this paper is to help practitioners avoid insecure coding practices while developing infrastructure as code (IaC) scripts through an empirical study of security smells in IaC scripts. We apply qualitative analysis on 1,726 IaC scripts to identify seven security smells. Next, we implement and validate a static analysis tool called Security Linter for Infrastructure as Code scripts (SLIC) to identify the occurrence of each smell in 15,232 IaC scripts collected from 293 open source repositories. We identify 21,201 occurrences of security smells that include 1,326 occurrences of hard-coded passwords. We submitted bug reports for 1,000 randomly-selected security smell occurrences. We obtain 212 responses to these bug reports, of which 148 occurrences were accepted by the development teams to be fixed. We observe security smells can have a long lifetime, e.g., a hard-coded secret can persist for as long as 98 months, with a median lifetime of 20 months. | F28: RankA* | G28: Tools; Software; Static analysis; Encoding; Servers; devops, devsecops, empirical study, infrastructure as code, puppet, security, smell, static analysis; Password | H28: 2019 IEEE/ACM 41st International Conference on Software Engineering (ICSE)
A29: 2017 | B29: Weiss, Aaron; Guha, Arjun; Brun, Yuriy | C29: Tortoise: Interactive system configuration repair | D29: https://ieeexplore.ieee.org/document/8115673/citations | E29: System configuration languages provide powerful abstractions that simplify managing large-scale, networked systems. Thousands of organizations now use configuration languages, such as Puppet. However, specifications written in configuration languages can have bugs and the shell remains the simplest way to debug a misconfigured system. Unfortunately, it is unsafe to use the shell to fix problems when a system configuration language is in use: a fix applied from the shell may cause the system to drift from the state specified by the configuration language. Thus, despite their advantages, configuration languages force system administrators to give up the simplicity and familiarity of the shell. This paper presents a synthesis-based technique that allows administrators to use configuration languages and the shell in harmony. Administrators can fix errors using the shell and the technique automatically repairs the higher-level specification written in the configuration language. The approach (1) produces repairs that are consistent with the fix made using the shell; (2) produces repairs that are maintainable by minimizing edits made to the original specification; (3) ranks and presents multiple repairs when relevant; and (4) supports all shells the administrator may wish to use. We implement our technique for Puppet, a widely used system configuration language, and evaluate it on a suite of benchmarks under 42 repair scenarios. The top-ranked repair is selected by humans 76% of the time and the human-equivalent repair is ranked 1.31 on average. | F29: RankA* | G29: Organizations; Computer bugs; Maintenance engineering; Benchmark testing; Web servers | H29: 2017 32nd IEEE/ACM International Conference on Automated Software Engineering (ASE)
A30: 2015 | B30: Cito, Jürgen; Leitner, Philipp; Fritz, Thomas; Gall, Harald C. | C30: The making of cloud applications: an empirical study on software development for the cloud | D30: https://dl.acm.org/doi/10.1145/2786805.2786826 | E30: Cloud computing is gaining more and more traction as a deployment and provisioning model for software. While a large body of research already covers how to optimally operate a cloud system, we still lack insights into how professional software engineers actually use clouds, and how the cloud impacts development practices. This paper reports on the first systematic study on how software developers build applications for the cloud. We conducted a mixed-method study, consisting of qualitative interviews of 25 professional developers and a quantitative survey with 294 responses. Our results show that adopting the cloud has a profound impact throughout the software development process, as well as on how developers utilize tools and data in their daily work. Among other things, we found that (1) developers need better means to anticipate runtime problems and rigorously define metrics for improved fault localization and (2) the cloud offers an abundance of operational data, however, developers still often rely on their experience and intuition rather than utilizing metrics. From our findings, we extracted a set of guidelines for cloud development and identified challenges for researchers and tool vendors. | F30: RankA*
A31: 2017 | B31: Cito, Jürgen; Oliveira, Fábio; Leitner, Philipp; Nagpurkar, Priya; Gall, Harald C. | C31: Context-based analytics: establishing explicit links between runtime traces and source code | D31: https://dl.acm.org/doi/10.1109/ICSE-SEIP.2017.1 | E31: Diagnosing problems in large-scale, distributed applications running in cloud environments requires investigating different sources of information to reason about application state at any given time. Typical sources of information available to developers and operators include log statements and other runtime information collected by monitors, such as application and system metrics. Just as importantly, developers rely on information related to changes to the source code and configuration files (program code) when troubleshooting. This information is generally scattered, and it is up to the troubleshooter to inspect multiple implicitly-connected fragments thereof. Currently, different tools need to be used in conjunction, e.g., log aggregation tools, source- code management tools, and runtime-metric dashboards, each requiring different data sources and workflows. Not surprisingly, diagnosing problems is a difficult proposition. In this paper, we propose Context-Based Analytics, an approach that makes the links between runtime information and program-code fragments explicit by constructing a graph based on an application-context model. Implicit connections between information fragments are explicitly represented as edges in the graph. We designed a framework for expressing application-context models and implemented a prototype. Further, we instantiated our prototype framework with an application-context model for two real cloud applications, one from IBM and another from a major telecommunications provider. We applied context-based analytics to diagnose two issues taken from the issue tracker of the IBM application and found that our approach reduced the effort of diagnosing these issues. In particular, context-based analytics decreased the number of required analysis steps by 48% and the number of needed inspected traces by 40% on average as compared to a standard diagnosis approach. | F31: RankA*
A32: 2018 | B32: Cito, Jürgen; Leitner, Philipp; Bosshard, Christian; Knecht, Markus; Mazlami, Genc; Gall, Harald C. | C32: PerformanceHat: augmenting source code with runtime performance traces in the IDE | D32: https://dl.acm.org/doi/10.1145/3183440.3183481 | E32: Performance problems observed in production environments that have their origin in program code are immensely hard to localize and prevent. Data that can help solve such problems is usually found in external dashboards and is thus not integrated into the software development process. We propose an approach that augments source code with runtime traces to tightly integrate runtime performance traces into developer workflows. Our goal is to create operational awareness of performance problems in developers' code and contextualize this information to tasks they are currently working on. We implemented this approach as an Eclipse IDE plugin for Java applications that is available as an open source project on GitHub. A video of PerformanceHat in action is online: https://youtu.be/fTBBiylRhag | F32: RankA*
A33: 2022 | B33: Reis, David; Correia, Filipe F. | C33: Dockerlive : A live development environment for Dockerfiles | D33: https://ieeexplore.ieee.org/document/9833145 | E33: The process of developing Dockerfiles is perceived by many developers as slow and based on trial-and-error, and it is hardly immediate to see the result of a change introduced into a Dockerfile. In this work we propose a plugin for Visual Studio Code, which we name Dockerlive, and that has the purpose of shortening the length of feedback loops. Namely, the plugin is capable of providing information to developers on a number of Dockerfile elements, as the developer is writing the Dockerfile. We achieve this through dynamic analysis of the resulting container, which the plugin builds and runs in the background. | F33: RankB | G33: Cloud; Codes; Containers; Dockerfile; Feedback loop; IDE; Indexes; Live Programming; Visualization; Writing | H33: 2022 IEEE Symposium on Visual Languages and Human-Centric Computing (VL/HCC)
A34: 2020 | B34: Gao, Jiechao; Wang, Haoyu; Shen, Haiying | C34: Machine Learning Based Workload Prediction in Cloud Computing | D34: https://ieeexplore.ieee.org/document/9209730 | E34: As a widely used IT service, more and more companies shift their services to cloud datacenters. It is important for cloud service providers (CSPs) to provide cloud service resources with high elasticity and cost-effectiveness and then achieve good quality of service (QoS) for their clients. However, meeting QoS with cost-effective resource is a challenging problem for CSPs because the workloads of Virtual Machines (VMs) experience variation over time. It is highly necessary to provide an accurate VMs workload prediction method for resource provisioning to efficiently manage cloud resources. In this paper, we first compare the performance of representative state-of-the-art workload prediction methods. We suggest a method to conduct the prediction a certain time before the predicted time point in order to allow sufficient time for task scheduling based on predicted workload. To further improve the prediction accuracy, we introduce a clustering based workload prediction method, which first clusters all the tasks into several categories and then trains a prediction model for each category respectively. The trace-driven experiments based on Google cluster trace demonstrates that our clustering based workload prediction methods outperform other comparison methods and improve the prediction accuracy to around 90% both in CPU and memory. | F34: RankB | G34: Task analysis; Cloud computing; Machine learning; Predictive models; Cloud Computing; Google; Hidden Markov models; Workload Prediction | H34: 2020 29th International Conference on Computer Communications and Networks (ICCCN)
A35: 2018 | B35: Schwarz, Julian; Steffens, Andreas; Lichter, Horst | C35: Code Smells in Infrastructure as Code | D35: https://ieeexplore.ieee.org/document/8590193 | E35: Ensuring high quality in software systems is a wellknown and big challenge. Infrastructure as Code (IaC) gathered increasing popularity in recent years, but there is only little research done in terms of quality of this code. Like with programming languages we find a high diversity of languages and technologies. Existing research introduced code smells from traditional software engineering to the popular provisioning tool Puppet, which uses IaC to specify the desired state of environments. Results show that code smells are an adequate method to assess the quality of Puppet code. In this paper we extend the existing research by first applying code the IaC smells to an other technology and investigate if similar results can be achieved. We applied the code smells in two case studies to open and closed source IaC code repositories. The presented results indicate that IaC smells are present in other tools and technologies. Furthermore the results show that IaC smells are agnostic to the applied technology and can be defined on a technology agnostic level. Second, we introduce new code smells from the field of software engineering, which were not covered yet, to the domain of IaC. The paper presents a catalogue of 17 code smells which were applied to Chef and whose implementation is available as Open Source. | F35: RankC | G35: Software engineering; Best practices; code smells; Computer architecture; DevOps; Infrastructure As Code; Measurement; refactoring; software quality; Software systems; static analysis; Tools | H35: 2018 11th International Conference on the Quality of Information and Communications Technology (QUATIC)
A36: 2025 | B36: Pahl, Claus; Gunduz, Niyazi; Sezen, Övgüm; Ghamgosar, Ali; El Ioini, Nabil | C36: Infrastructure as Code -Technology Review and Research Challenges | D36: https://www.researchgate.net/publication/389406746_Infrastructure_as_Code_-Technology_Review_and_Research_Challenges | E36: The quality of software management in infrastructure operations for application software is important as automation in software operations continues to grow. Infrastructure as Code (IaC) refers to a systematic, technology-supported approach to manage deployment infrastructure for software applications. Sample contexts are general software automation, but also cloud and edge and various software-defined networking applications. DevOps (development and operations) practices, which are already applied in the Infrastructure as Code (IaC) context, need to be extended to cover the whole IaC life cycle from code generation to dynamic, automated control. The ultimate objective would range from IaC generation to full self-adaptation of IaC code in an automated setting. We review available IaC technologies based on a comprehensive comparison framework to capture the state-of-the-art. We also introduce an IaC-specific DevOps process. This serves as a basis to identify open research challenges. A discussion of defect categories is at the centre of this process. | F36: RankC
A37: 2017 | B37: Ewenike, Stanley; Benkhelifa, Elhadj; Chibelushi, Claude | C37: Cloud Based Collaborative Software Development: A Review, Gap Analysis and Future Directions | D37: https://ieeexplore.ieee.org/document/8308385 | E37: Organizations who have transitioned their development environments to the Cloud have started realizing benefits such as: cost reduction in hardware; relatively accelerated development process via reduction of time and effort to set up development and testing environments; unified management; service and functionality expansion; on-demand provisioning and access to resources and development environments. These benefits represent only a fraction of the full potential that could be achieved via leveraging Cloud Computing for the collaborative software development process. Related efforts in this area have been mainly in the areas of: asynchronous collaboration; collaboration in isolated aspects of the Software Development process, such as coding activities; use of open-source tools for contributing, improving, and managing code, etcetera. Although these efforts represent valid contributions and important enablers, they are still missing important aspects which enable a more holistic process, with solid theoretical foundation. This paper reviews this research area, in order to better assess factors and gaps creating the need to enhance the collaborative software development process in the Cloud, to better meet the pressure to collaboratively create better cloud-agnostic applications. | F37: RankC | G37: Tools; Cloud computing; Cloud; Adaptation models; Business; collaboration; Collaborative software; Collaborative software development; gap analysis | H37: 2017 IEEE/ACS 14th International Conference on Computer Systems and Applications (AICCSA)
A38: 2023 | B38: Zhang, Yue; Wu, Fan; Rahman, Akond | C38: Practitioner Perceptions of Ansible Test Smells | D38: https://ieeexplore.ieee.org/document/10092644 | E38: The practice of infrastructure as code (IaC) recommends automated management of computing infrastructure with application of quality assurance, such as linting and testing. To that end, researchers recently have investigated quality concerns in IaC test manifests by deriving a catalog of test smells. The relevance of the identified smells need to be quantified by obtaining feedback from practitioners. Such feedback can help the IaC community understand if smells have relevance amongst practitioners, and derive future research directions. We survey 30 practitioners to assess the relevance of three Ansible test smell categories namely, assertion roulette, local only testing, and remote mystery guest. We observe local only testing to be the most agreed upon test smell category, whereas, assertion roulette is the least agreed upon test smell category. Our findings provide a nuanced perspective of test smells for IaC, and lays the groundwork for future research. | F38: Short | G38: ansible; Codes; devops; empirical study; infrastructure as code; Quality assurance; smells; Software architecture; testing; Testing | H38: 2023 IEEE 20th International Conference on Software Architecture Companion (ICSA-C)
A39: 2023 | B39: Zhang, Yue; Rahman, Muktadir; Wu, Fan; Rahman, Akond | C39: Quality Assurance for Infrastructure Orchestrators: Emerging Results from Ansible | D39: https://ieeexplore.ieee.org/document/10092684 | E39: Infrastructure as code (IaC) is the practice of automatically managing computing infrastructure at scale. Despite yielding multiple benefits for organizations, the practice of IaC is susceptible to quality concerns, which can lead to large-scale consequences. While researchers have studied quality concerns in IaC manifests, quality aspects of infrastructure orchestrators, i.e., tools that implement the practice of IaC, remain an under-explored area. A systematic investigation of defects in infrastructure orchestrators can help foster further research in the domain of IaC. From our empirical study with 22,445 commits mined from the Ansible infrastructure orchestrator we observe (i) a defect density of 17.9 per KLOC, (ii) 12 categories of Ansible components for which defects appear, and (iii) the ‘Module’ component to include more defects than the other 11 components. Based on our empirical study, we provide recommendations for researchers to conduct future research to enhance the quality of infrastructure orchestrators. | F39: Short | G39: ansible; Codes; Correlation; devops; infrastructure as code; Organizations; Quality assurance; Software architecture; Systematics; Taxonomy | H39: 2023 IEEE 20th International Conference on Software Architecture Companion (ICSA-C)
A40: 2024 | B40: Mendis, Pemsith; Reeves, Wilson; Babar, Muhammad Ali; Zhang, Yue; Rahman, Akond | C40: Evaluating the Quality of Open Source Ansible Playbooks: An Executability Perspective | D40: https://dl.acm.org/doi/10.1145/3663530.3665019 | E40: Infrastructure as code (IaC) is the practice of automatically managing computing platforms, such as Internet of Things (IoT) platforms. IaC has gained popularity in recent years, yielding a plethora of software artifacts, such as Ansible playbooks that are available on social coding platforms. Despite the availability of open source software (OSS) Ansible playbooks, there is a lack of empirical research on the quality of these playbooks, which can hinder the progress of IaC-related research. To that end, we conduct an empirical study with 2,952 OSS Ansible playbooks where we evaluate the quality of OSS playbooks from the perspective of executability, i.e., if publicly available OSS Ansible playbooks can be executed without failures. From our empirical study, we observe 71.5% of the mined 2,952 Ansible playbooks cannot be executed as is because of four categories of failures. | F40: Workshop
C41: Vista do Terraform and AWS CDK: A Comparative Analysis of Infrastructure Management Tools | D41: https://sol.sbc.org.br/index.php/sbes/article/view/30404/30210 | E41: Infrastructure as Code is a fundamental concept in DevOps that automates infrastructure management processes using code. Several tools, such as Terraform and CDK, support this environment. Selecting the appropriate tool is crucial to a project’s success, yet there is ambiguity about the circumstances in which developers should choose between these tools. Therefore, this study aims to compare Terraform and CDK across four aspects: abstraction, scalability, maintainability, and performance. Our findings indicate that each tool performs particularly well in specific scenarios. For instance, Terraform is better suited for experienced teams focused on rapid implementations, while CDK is more appropriate for less experienced teams prioritizing resource efficiency during implementation.
A42: 2023 | B42: Reddy Konala, Pandu Ranga; Kumar, Vimal; Bainbridge, David | C42: SoK: Static Configuration Analysis in Infrastructure as Code Scripts | D42: https://ieeexplore.ieee.org/document/10224925 | E42: This SoK paper presents findings from a survey conducted on the current state of tools and techniques used in the static configuration analysis of Infrastructure as Code (IaC). Our findings highlight the increasing importance of ensuring the quality of IaC scripts through techniques such as detecting code and security smells. Our findings reveal that regular expressions are widely used, but this may not be a long-term or fully automated solution for detecting smells. Additionally, our study found that the majority of the tools and techniques are developed for infrastructure provisioning, rather than configuration management and image building. This raises concerns because configuring software is a high-risk task, with malicious actors constantly targeting software systems. Therefore, it is crucial for researchers to develop efficient and advanced techniques for detecting defects in configuration management and image building. The aim of this paper is to provide a detailed overview of the current state of research in this field, and to identify areas for future development. | G42: security; Software systems; Codes; empirical study; Security; devops; infrastructure as code; Buildings; code; Configuration management; defects; devsecops; smells; sok; static configuration analysis; survey; Surveys; Task analysis | H42: 2023 IEEE International Conference on Cyber Security and Resilience (CSR)
A43: 2019 | B43: RahmanAkond; WilliamsLaurie | C43: Source code properties of defective infrastructure as code scripts | D43: https://dl.acm.org/doi/10.1016/j.infsof.2019.04.013 | E43: Context In continuous deployment, software and services are rapidly deployed to end-users using an automated deployment pipeline. Defects in infrastructure as code (IaC) scripts can hinder the reliability of the automated deployment pipeline. We hypothesize that certain properties of IaC source code such as lines of code and hard-coded strings used as configuration values, show correlation with defective IaC scripts. Objective The objective of this paper is to help practitioners in increasing the quality of infrastructure as code (IaC) scripts through an empirical study that identifies source code properties of defective IaC scripts. Methodology We apply qualitative analysis on defect-related commits mined from open source software repositories to identify source code properties that correlate with defective IaC scripts. Next, we survey practitioners to assess the practitioner’s agreement level with the identified properties. We also construct defect prediction models using the identified properties for 2439 scripts collected from four datasets. Results We identify 10 source code properties that correlate with defective IaC scripts. Of the identified 10 properties we observe lines of code and hard-coded string i.e. putting strings as configuration values, to show the strongest correlation with defective IaC scripts. According to our survey analysis, majority of the practitioners show agreement for two properties: include, the property of executing external modules or scripts, and hard-coded string. Using the identified properties, our constructed defect prediction models show a precision of 0.70∼0.78, and a recall of 0.54∼0.67. Conclusion Based on our findings, we recommend practitioners to allocate sufficient inspection and testing efforts on IaC scripts that include any of the identified 10 source code properties of IaC scripts.
A44: 2023 | B44: Zeini, Ammar; Lennon, Ruth G.; Lennon, Patrick | C44: Securing Infrastructure as Code (IaC) through DevSecOps:A Comprehensive Risk Management Framework | D44: https://ieeexplore.ieee.org/document/10671452 | E44: Despite the evident advantages of Infrastructure as Code (IaC) in software development, the nature of bugs and potential threats arising from its implementation remains subject to ongoing investigation. The formulation of a list, enumerating potential threats during the IaC process remains an unattained goal. However, it is not enough to recounting IaC threats only, it is imperative for Development (Dev), Security (Sec), and Operations (Ops) teams to synergistically collaborate from early developmental stages to conduct thorough risks’ analysis, estimation, and mitigation procedures concerning IaC-related risks. Moreover, adhering to security standards and risk management framework throughout the IaC lifecycle will enhance the overall security of the deployment process. A risk management framework for IaC is essential. The extant risk management and threat modeling methodologies may necessitate tailoring to effectively protect the Software Development Lifecycle (SDLC) from IaC misuse. This research aims to identify threats that threaten IaC lifecycle or arise from the utilization of IaC. In addition, it tries to integrate IaC practices with the DevSecOps culture to devise a robust risk management framework and prescribe pertinent practices conducive to fostering secure IaC implementation. | G44: Codes; Infrastructure as Code; Security; Computer bugs; DevSecOps; Estimation; Prevention and mitigation; Risk management; Risk Management framework; Secure Deployment; Threat modeling | H44: 2023 Cyber Research Conference - Ireland (Cyber-RCI)
A45: 2023 | B45: Verdet, Alexandre; Hamdaqa, Mohammad; Silva, Leuson Da; Khomh, Foutse | C45: Exploring Security Practices in Infrastructure as Code: An Empirical Study | D45: http://arxiv.org/abs/2308.03952 | E45: Cloud computing has become popular thanks to the widespread use of Infrastructure as Code (IaC) tools, allowing the community to conveniently manage and configure cloud infrastructure using scripts. However, the scripting process itself does not automatically prevent practitioners from introducing misconfigurations, vulnerabilities, or privacy risks. As a result, ensuring security relies on practitioners understanding and the adoption of explicit policies, guidelines, or best practices. In order to understand how practitioners deal with this problem, in this work, we perform an empirical study analyzing the adoption of IaC scripted security best practices. First, we select and categorize widely recognized Terraform security practices promulgated in the industry for popular cloud providers such as AWS, Azure, and Google Cloud. Next, we assess the adoption of these practices by each cloud provider, analyzing a sample of 812 open-source projects hosted on GitHub. For that, we scan each project configuration files, looking for policy implementation through static analysis (checkov). Additionally, we investigate GitHub measures that might be correlated with adopting these best practices. The category Access policy emerges as the most widely adopted in all providers, while Encryption in rest are the most neglected policies. Regarding GitHub measures correlated with best practice adoption, we observe a positive, strong correlation between a repository number of stars and adopting practices in its cloud infrastructure. Based on our findings, we provide guidelines for cloud practitioners to limit infrastructure vulnerability and discuss further aspects associated with policies that have yet to be extensively embraced within the industry. | G45: Computer Science - Cryptography and Security; Computer Science - Software Engineering
A46: 2024 | B46: Abbas, Syed Imran; Garg, Ankit | C46: Integrating Emerging Technologies with Infrastructure as Code in Distributed Environments | D46: https://ieeexplore.ieee.org/document/10575600?denied= | E46: Manual provisioning of infrastructure limited flexibility, scalability, and stability in distributed environments. The adoption of Infrastructure as Code (IaC) principles has dramatically enhanced deployment agility, reducing infrastructure change implementation to mere minutes. Automation facilitated dynamic scaling, optimizing resource utilization and cost efficiency. By standardizing configurations as code, IaC improved consistency and reliability, mitigating the risks associated with configuration drift and security vulnerabilities. This shift significantly reduced operational overhead, allowing IT teams to concentrate on strategic initiatives. Uniform and auditable configurations strengthened security and compliance, ensuring adherence to regulatory standards. The integration of IaC with emerging technologies has revolutionized organizational operations, enabling enterprises to navigate complex digital landscapes with increased agility and resilience. Through automation and standardization, organizations are now better positioned for sustained success and competitiveness in the evolving digital era. | G46: security; Codes; Organizations; Automation; Costs; Stability criteria; agility; automation; compliance; configuration drift; deployment; digital transformation.; distributed environments; dynamic scaling; emerging technologies; Infrastructure as Code (IaC); operational efficiency; reliability; resource utilization; scalability; Scalability; Standards organizations | H46: 2024 3rd International Conference on Applied Artificial Intelligence and Computing (ICAAIC)
A47: 2023 | B47: Spielmann, David; Sokolowski, Daniel; Salvaneschi, Guido | C47: Extensible Testing for Infrastructure as Code | D47: https://dl.acm.org/doi/10.1145/3618305.3623607 | E47: Developers automate deployments with Languages Infrastructure as Code (PL-IaC) by implementing IaC programs in popular languages like TypeScript and Python. Yet, systematic testing---well established for high-velocity software development---is rarely applied to IaC programs IaC testing techniques either slow or require extensive development effort. To solve this dilemma, we develop ProTI, a novel IaC unit testing approach, and implement it for Pulumi TypeScript. Our preliminary experiments with simple type-based test case generators and oracles show ProTI can find bugs reliably in a short time, often without writing any additional testing code. ProTI's extensible plugin architecture allows combining, adopting, and experimenting with new approaches, opening the discussion about novel generators and oracles for efficient IaC testing.
A48: 2023 | B48: Rahman, Akond; Shamim, Shazibul Islam; Bose, Dibyendu Brinto; Pandita, Rahul | C48: Security Misconfigurations in Open Source Kubernetes Manifests: An Empirical Study | D48: https://dl.acm.org/doi/10.1145/3579639 | E48: Context: Kubernetes has emerged as the de-facto tool for automated container orchestration. Business and government organizations are increasingly adopting Kubernetes for automated software deployments. Kubernetes is being used to provision applications in a wide range of domains, such as time series forecasting, edge computing, and high-performance computing. Due to such a pervasive presence, Kubernetes-related security misconfigurations can cause large-scale security breaches. Thus, a systematic analysis of security misconfigurations in Kubernetes manifests, i.e., configuration files used for Kubernetes, can help practitioners secure their Kubernetes clusters.Objective: The goal of this paper is to help practitioners secure their Kubernetes clusters by identifying security misconfigurations that occur in Kubernetes manifests.Methodology: We conduct an empirical study with 2,039 Kubernetes manifests mined from 92 open-source software repositories to systematically characterize security misconfigurations in Kubernetes manifests. We also construct a static analysis tool called Security Linter for Kubernetes Manifests (SLI-KUBE) to quantify the frequency of the identified security misconfigurations.Results: In all, we identify 11 categories of security misconfigurations, such as absent resource limit, absent securityContext, and activation of hostIPC. Specifically, we identify 1,051 security misconfigurations in 2,039 manifests. We also observe the identified security misconfigurations affect entities that perform mesh-related load balancing, as well as provision pods and stateful applications. Furthermore, practitioners agreed to fix 60% of 10 misconfigurations reported by us.Conclusion: Our empirical study shows Kubernetes manifests to include security misconfigurations, which necessitates security-focused code reviews and application of static analysis when Kubernetes manifests are developed.
A49: 2024 | B49: Sroor, Maha; Mohanani, Rahul; Das, Teerath; Mikkonen, Tommi; Dasanayake, Sandun | C49: Practitioners' Perceptions of Security Issues in Software Containers: A Qualitative Study | D49: https://ieeexplore.ieee.org/document/10803348 | E49: Software containers have emerged as solutions for developing and deploying software applications. Despite the popularity and portability of containers, there is significant concern about container security, which hinders their adoption. Recent research has made efforts to investigate container security theoretically and experimentally. Meanwhile, software practitioners have also developed practices to improve and maintain container security based on their work experience. However, a notable gap exists in expressing practitioners' viewpoints on container security. Consequently, this study aims to understand practitioners' perceptions of container security and their man-agement strategies in real-world projects. We conducted semi-structured interviews with practitioners across various domains to explore their opinions on container security issues, causes, implications, tools, and practices. Our data analysis reveals emergent patterns in handling container security in real projects. These patterns are presented as a model that highlights the relationships between the major themes and how they affect each other. Our findings reveal that containers offer many advantages to software systems but face challenges in maintaining security. Finally, this research attempts to bridge the knowledge gap between academia and industry by providing a comprehensive understanding of container security issues as perceived by the practitioners and their interrelationships. | G49: Software engineering; Software systems; Security; Software; Software measurement; Containers; Interviews; con-tainer security; interviews; qualitative study; Refining; security issues; Security management; software container; Sustainable development | H49: 2024 50th Euromicro Conference on Software Engineering and Advanced Applications (SEAA)
A50: 2024 | B50: Gunathilake, Kavindu; Ekanayake, Indrajith | C50: K8s Pro Sentinel: Extend Secret Security in Kubernetes Cluster | D50: https://ieeexplore.ieee.org/document/10857769 | E50: Microservice architecture is widely adopted among distributed systems. It follows the modular approach that decomposes large software applications into independent services. Kubernetes has become the standard tool for managing these microservices. It stores sensitive information like database passwords, API keys, and access tokens as Secret Objects. There are security mechanisms employed to safeguard these confidential data, such as encryption, Role Based Access Control (RBAC), and the least privilege principle. However, manually configuring these measures is time-consuming, requires specialized knowledge, and is prone to human error, thereby increasing the risks of misconfiguration. This research introduces \mathrmK8\mathrms Pro Sentinel, an operator that automates the configuration of encryption and access control for Secret Objects by extending the Kubernetes API server. This automation reduces human error and enhances security within clusters. The performance and reliability of the Sentinel operator were evaluated using Red Hat Operator Scorecard and chaos engineering practices. | G50: Software; Testing; Servers; DevSecOps; Standards; Reliability engineering; Distributed Systems; Encryption; Information technology; Kubernetes Security; Measurement uncertainty; Microservice architectures; Microservices; Passwords; Secrets Management | H50: 2024 9th International Conference on Information Technology Research (ICITR)
A51: 2024 | B51: Diarra, Boubacar; Guillouard, Karine; Ouzzif, Meryem; Merle, Philippe; Stefani, Jean-Bernard | C51: In-Depth Analysis of Kubernetes Manifest Verification Tools for Robust CNF Deployment | D51: https://ieeexplore.ieee.org/document/10494445/citations?tabFilter=papers#citations | E51: Kubernetes has emerged as the leading platform for orchestrating cloud-native network functions (CNF). The description of the hardware and software architecture of systems to be deployed with Kubernetes is defined in configuration files called manifests. In order to address the errors that these manifests may contain, manifest verification tools have been developed. However, evaluating and selecting the most appropriate verification tool for a given project is a difficult task. To facilitate this evaluation process, we identified and characterized the most relevant verification capabilities, useful also in the CNF context. The selected capabilities serve as criteria for the evaluation of manifest verification tools. In total, we have identified 13 criteria, like the variety of verification types or the ability to carry out JSON Schema-based verification. The identified criteria were used to evaluate 16 of the most commonly used verification tools in the Kubernetes community. This evaluation revealed several shortcomings in the existing tools. | G51: Kubernetes; Cloud computing; Software architecture; CNF; evaluation criteria; Hardware; manifests verification; Model checking; Random access memory; robust CNF deployment; Robustness; Technological innovation; verification tools | H51: 2024 27th Conference on Innovation in Clouds, Internet and Networks (ICIN)
A52: 2024 | B52: Choi, Dongmin; Seo, Hyunmin; Kim, Kwanwoo; You, Myoungsung; Shin, Seungwon; Kim, Jinwoo | C52: Uncovering Threats in Container Systems: A Study on Misconfigured Container Components in the Wild | D52: https://ieeexplore.ieee.org/document/10788674 | E52: The increasing popularity of cloud computing has led to a significant rise in the use of container technology. Docker and Kubernetes have emerged as the de facto standards for container orchestration frameworks due to their reliability, flexibility, and ease of operation, supported by scalable, HTTP-based interfaces. Given the critical nature of infrastructure systems, container components within such orchestration frameworks should adhere to strict security levels. However, administrative misconfigurations can introduce serious vulnerabilities, exposing security-critical container components to external networks and allowing adversaries to discover and exploit them as attack vectors. In this paper, we investigate the security threats posed by misconfigured container components (MCC) that are exposed to the Internet. Through an Internet-scale measurement, we identify a total of 1,003,947 MCCs, with the majority operating under default configurations and outdated software versions. Our analysis reveals that renowned institutes, governments, and enterprises that are operating exposed MCCs, suggesting significant security risks. In addition, we conduct a real-world experiment within multi-branch campus network, scanning 150,235 IP addresses to uncover actual vulnerabilities in MCCs. We identify five distinct vulnerabilities that either leak sensitive information or allow remote code execution, demonstrating the real-world feasibility and potential impact of exploiting these misconfigured container components. | G52: Codes; Security; Software; Cloud computing; IP networks; Servers; Standards; Containers; Cloud computing security; HTTP; internet security; network security; Vectors
A53: 2023 | B53: Afifah, Fatma Nur; Dewantara, Nasrullah Pandu; Faiz, Ahmad Faris; Romansyah, Syahda; Negara, Ridha Muldina; Mayasari, Ratna; Astuti, Sri | C53: Cost-Effective Automation: Cloud-Based Monitoring Combining HPA with VPA for Scalable Startups | D53: https://ieeexplore.ieee.org/document/10335324 | E53: This paper proposes to automate server usage monitoring for resource metrics using Prometheus and Grafana. The main contribution of this work is to create a cost-effective web-based application monitoring system combining Horizontal Pod Autoscaler (HPA) and Vertical Pod Autoscaler (VPA), called Anbu, suitable for scalable startups. The web-based application monitoring system is achieved by comparing the monthly fee with the existing monitoring system. To validate the accuracy of Anbu, services in the Kubernetes cluster are tested in two cases using a load test. The first case is to scale the number of replicas set for the service according to CPU and memory. The second is to provide recommendations for the ideal number of CPUs and memory according to the history of their actual use. The results show that scalable startups can do automation monitoring with an Anbu usage fee for 24 hours of uptime of around 200 per month. It will save 139.04 less per month than the existing monitoring system. This price is suitable for scalable startups who still manually automate server usage with an annual salary of less than $100.000. | G53: Measurement; Automation; Computer bugs; Writing; Wireless communication; Grafana; HPA; Prometheus; Scalable Startups; Social networking (online); Telematics; VPA | H53: 2023 9th International Conference on Wireless and Telematics (ICWT)
A54: 2022 | B54: Reis, David; Piedade, Bruno; Correia, Filipe F.; Dias, João Pedro; Aguiar, Ademar | C54: Developing Docker and Docker-Compose Specifications: A Developers’ Survey | D54: https://ieeexplore.ieee.org/document/9658534 | E54: Cloud computing and Infrastructure-as-Code (IaC), supported by technologies such as Docker, have shaped how many software systems are built and deployed. Previous research has identified typical issues for some types of IaC specification but not why they come to be, or they have delved into collaboration aspects but not into technical ones. This work aims to characterize the activities around two particular kinds of IaC specification—Dockerfiles and docker-compose.yml files. We seek to know how they can be better supported and therefore study also what approaches and tools practitioners employ. We used an online questionnaire to gather data. The first part of the study reached 68 graduate students from a study program on informatics engineering, and the second one 120 professional software developers. The results show that most of the activities of the process of developing a Dockerfile are perceived as time-consuming, especially when the respondents are beginners with this technology. We also found that solving issues using trial-and-error approaches is very common and that many developers do not use ancillary tools to support the development of Dockerfiles and docker-compose.yml files. | G54: Measurement; Open source software; survey; Cloud computing; cloud computing; Social networking (online); Docker; docker-compose; orchestration; Software development management
A55: 2024 | B55: Liu, Jiali; Qin, Yuqin | C55: CSPUMS: Pioneering Integrated Monitoring in Multi-Service Provider Ecosystems | D55: https://ieeexplore.ieee.org/document/10569563 | E55: In the era of information interconnection, the evolution of enterprise digitalization necessitates the adoption of architectures that can support dynamic and complex business operations. Microservices architecture, characterized by its flexibility, scalability, and efficiency, has emerged as a pivotal solution for modern enterprises, enabling the decomposition of monolithic applications into independently deployable services. However, with the expansion of enterprises and the intricate nature of business operations, microservices architecture encounters challenges in service governance, monitoring, management, and integration in multi-vendor environments. Addressing these challenges, this paper introduces a Cross-Service Provider Unified Monitoring System (CSPUMS) tailored for microservice business platforms operating within multi-service provider ecosystems. CSPUMS, a novel three-layer system architecture, encompasses a data acquisition layer, a monitoring layer, and a data presentation layer, designed to ensure the reliability, performance, and security of service platforms across diverse cloud environments. Through the deployment of Docker container technology for data aggregation and the implementation of a multi-dimensional threshold alarm template, CSPUMS enhances operational monitoring, fault management, and service continuity in complex multi-service settings. This paper significantly enhances microservice platforms by providing integrated monitoring solutions for multi-cloud and multi-service environments, ensuring operational efficiency and agility for digitally transforming enterprises. | G55: Computer architecture; Cloud computing; Reliability engineering; Scalability; Microservice architectures; Docker; Ecosystems; Microservices architecture; Multi-service provider; Operation monitoring; Systems architecture | H55: 2024 9th International Conference on Cloud Computing and Big Data Analytics (ICCCBDA)
A56: 2024 | B56: Ueno, Masaru; Uchiumi, Tetsuya | C56: Migrating Existing Container Workload to Kubernetes - LLM Based Approach and Evaluation | D56: https://ieeexplore.ieee.org/document/10795024 | E56: Although Kubernetes has become a widespread open-source system that automates the management of containerized applications, its complexity can be a significant barrier, particularly for application developers unfamiliar with it. One approach employs large language models (LLMs) to assist developers in generating Kubernetes manifests; however it is currently impossible to determine whether the output satisfies given specifications and is comprehensible. In this study, we proposed a benchmarking method for evaluating the effectiveness of LLMs in synthesizing manifests, using the Compose specification - a standard widely adopted by application developers - as input. The proposed benchmarking method revealed that LLMs generally produce accurate results that compensate for simple specification gaps. However, we also observed that inline comments for readability were often omitted, and completion accuracy was low for atypical inputs with unclear intentions. | G56: Kubernetes; Market research; Configuration management; Pipelines; Standards; Software maintenance; Benchmark testing; Accuracy; Color; Dictionaries; LLM; Performance evaluation; program synthesis; Tuning | H56: 2024 IEEE International Conference on Software Maintenance and Evolution (ICSME)
A57: 2023 | B57: Rosa, Giovanni; Mastropaolo, Antonio; Scalabrino, Simone; Bavota, Gabriele; Oliveto, Rocco | C57: Automatically Generating Dockerfiles via Deep Learning: Challenges and Promises | D57: https://ieeexplore.ieee.org/document/10169074 | E57: Containerization allows developers to define the execution environment in which their software needs to be installed. Docker is the leading platform in this field, and developers that use it are required to write a Dockerfile for their software. Writing Dockerfiles is far from trivial, especially when the system has unusual requirements for its execution environment. Despite several tools exist to support developers in writing Dockerfiles, none of them is able to generate entire Dockerfiles from scratch given a high-level specification of the requirements of the execution environment. In this paper, we present a study in which we aim at understanding to what extent Deep Learning (DL), which has been proven successful for other coding tasks, can be used for this specific coding task. We preliminarily defined a structured natural language specification for Dockerfile requirements and a methodology that we use to automatically infer the requirements from the largest dataset of Dockerfiles currently available. We used the obtained dataset, with 670,982 instances, to train and test a Text-to-Text Transfer Transformer (T5) model, following the current state-of-the-art procedure for coding tasks, to automatically generate Dockerfiles from the structured specifications. The results of our evaluation show that T5 performs similarly to the more trivial IR-based baselines we considered. We also report the open challenges associated with the application of deep learning in the context of Dockerfile generation. | G57: Software; Task analysis; Encoding; Writing; deep learning; Deep learning; docker; Natural languages; Transformers | H57: 2023 IEEE/ACM International Conference on Software and System Processes (ICSSP)
